{
    "episodes_list": [
        {
            "file_id": "38d9993e0fc263bdb0fbe181602bb83c",
            "imdb_id": -1,
            "tvdb_id": -1,
            "tmdb_id": 14956,
            "saga": "Doll House",
            "season": 1,
            "episode": 1,
            "genre": [
                "Sci-Fi & Fantasy",
                "Action & Adventure",
                "Dramma"
            ],
            "title": "Riscatto morale",
            "fname": "/SerieTV/Doll House (2009) [a14956]/1.001 - Riscatto morale.mp4",
            "year": "2009",
            "plot": "Eliza Dushku interpreta una giovane donna di nome Echo, appartenente ad un gruppo di persone, chiamate \"attivi\" o \"doll\", totalmente controllate dalla misteriosa e segreta organizzazione \"Dollhouse\". Le doll sono in realt\u00e0 giovani di ambo i sessi, fisicamente attraenti e atletici, che si sono sottoposti (si suppone volontariamente) ad un procedimento di totale cancellazione dei ricordi delle loro pregresse esperienze di vita. In conseguenza di tale processo, la loro personalit\u00e0 diviene neutra, infantile, ingenua e quasi del tutto assente. La macchina che produce all'annullamento, e grazie a ci\u00f2, permette inoltre alla societ\u00e0 Dollhouse di imprimere a ciascun attivo sempre nuove e distinte personalit\u00e0, in base alle necessit\u00e0 contingenti dell'organizzazione.",
            "director": [],
            "actors": [
                "Eliza Dushku",
                "Fran Kranz",
                "Olivia Williams",
                "Dichen Lachman",
                "Enver Gjokaj",
                "Tahmoh Penikett",
                "Harry Lennix",
                "Amy Acker"
            ],
            "poster": "/oq5WPzUn7R0YcIk7QGwpXqvgSWO.jpg",
            "links": [
                {
                    "url": "http://51.77.159.233:30299/38d9993e0fc263bdb0fbe181602bb83c"
                }
            ]
        },
        {
            "file_id": "f1cec2cff6474d2919558dcea948c86f",
            "imdb_id": -1,
            "tvdb_id": -1,
            "tmdb_id": 14956,
            "saga": "Doll House",
            "season": 1,
            "episode": 2,
            "genre": [
                "Sci-Fi & Fantasy",
                "Action & Adventure",
                "Dramma"
            ],
            "title": "Il bersaglio",
            "fname": "/SerieTV/Doll House (2009) [a14956]/1.002 - Il bersaglio.mp4",
            "year": "2009",
            "plot": "Eliza Dushku interpreta una giovane donna di nome Echo, appartenente ad un gruppo di persone, chiamate \"attivi\" o \"doll\", totalmente controllate dalla misteriosa e segreta organizzazione \"Dollhouse\". Le doll sono in realt\u00e0 giovani di ambo i sessi, fisicamente attraenti e atletici, che si sono sottoposti (si suppone volontariamente) ad un procedimento di totale cancellazione dei ricordi delle loro pregresse esperienze di vita. In conseguenza di tale processo, la loro personalit\u00e0 diviene neutra, infantile, ingenua e quasi del tutto assente. La macchina che produce all'annullamento, e grazie a ci\u00f2, permette inoltre alla societ\u00e0 Dollhouse di imprimere a ciascun attivo sempre nuove e distinte personalit\u00e0, in base alle necessit\u00e0 contingenti dell'organizzazione.",
            "director": [],
            "actors": [
                "Eliza Dushku",
                "Fran Kranz",
                "Olivia Williams",
                "Dichen Lachman",
                "Enver Gjokaj",
                "Tahmoh Penikett",
                "Harry Lennix",
                "Amy Acker"
            ],
            "poster": "/oq5WPzUn7R0YcIk7QGwpXqvgSWO.jpg",
            "links": [
                {
                    "url": "http://51.77.159.233:30299/f1cec2cff6474d2919558dcea948c86f"
                }
            ]
        },
        {
            "file_id": "6f16e3aec00889a667e463b240bb206f",
            "imdb_id": -1,
            "tvdb_id": -1,
            "tmdb_id": 14956,
            "saga": "Doll House",
            "season": 1,
            "episode": 3,
            "genre": [
                "Sci-Fi & Fantasy",
                "Action & Adventure",
                "Dramma"
            ],
            "title": "L`ultimo spettacolo",
            "fname": "/SerieTV/Doll House (2009) [a14956]/1.003 - L`ultimo spettacolo.mp4",
            "year": "2009",
            "plot": "Eliza Dushku interpreta una giovane donna di nome Echo, appartenente ad un gruppo di persone, chiamate \"attivi\" o \"doll\", totalmente controllate dalla misteriosa e segreta organizzazione \"Dollhouse\". Le doll sono in realt\u00e0 giovani di ambo i sessi, fisicamente attraenti e atletici, che si sono sottoposti (si suppone volontariamente) ad un procedimento di totale cancellazione dei ricordi delle loro pregresse esperienze di vita. In conseguenza di tale processo, la loro personalit\u00e0 diviene neutra, infantile, ingenua e quasi del tutto assente. La macchina che produce all'annullamento, e grazie a ci\u00f2, permette inoltre alla societ\u00e0 Dollhouse di imprimere a ciascun attivo sempre nuove e distinte personalit\u00e0, in base alle necessit\u00e0 contingenti dell'organizzazione.",
            "director": [],
            "actors": [
                "Eliza Dushku",
                "Fran Kranz",
                "Olivia Williams",
                "Dichen Lachman",
                "Enver Gjokaj",
                "Tahmoh Penikett",
                "Harry Lennix",
                "Amy Acker"
            ],
            "poster": "/oq5WPzUn7R0YcIk7QGwpXqvgSWO.jpg",
            "links": [
                {
                    "url": "http://51.77.159.233:30299/6f16e3aec00889a667e463b240bb206f"
                }
            ]
        },
        {
            "file_id": "7847f8fe9cbf4916e2e4206e6a4a516b",
            "imdb_id": -1,
            "tvdb_id": -1,
            "tmdb_id": 14956,
            "saga": "Doll House",
            "season": 1,
            "episode": 4,
            "genre": [
                "Sci-Fi & Fantasy",
                "Action & Adventure",
                "Dramma"
            ],
            "title": "In trappola",
            "fname": "/SerieTV/Doll House (2009) [a14956]/1.004 - In trappola.mp4",
            "year": "2009",
            "plot": "Eliza Dushku interpreta una giovane donna di nome Echo, appartenente ad un gruppo di persone, chiamate \"attivi\" o \"doll\", totalmente controllate dalla misteriosa e segreta organizzazione \"Dollhouse\". Le doll sono in realt\u00e0 giovani di ambo i sessi, fisicamente attraenti e atletici, che si sono sottoposti (si suppone volontariamente) ad un procedimento di totale cancellazione dei ricordi delle loro pregresse esperienze di vita. In conseguenza di tale processo, la loro personalit\u00e0 diviene neutra, infantile, ingenua e quasi del tutto assente. La macchina che produce all'annullamento, e grazie a ci\u00f2, permette inoltre alla societ\u00e0 Dollhouse di imprimere a ciascun attivo sempre nuove e distinte personalit\u00e0, in base alle necessit\u00e0 contingenti dell'organizzazione.",
            "director": [],
            "actors": [
                "Eliza Dushku",
                "Fran Kranz",
                "Olivia Williams",
                "Dichen Lachman",
                "Enver Gjokaj",
                "Tahmoh Penikett",
                "Harry Lennix",
                "Amy Acker"
            ],
            "poster": "/oq5WPzUn7R0YcIk7QGwpXqvgSWO.jpg",
            "links": [
                {
                    "url": "http://51.77.159.233:30299/7847f8fe9cbf4916e2e4206e6a4a516b"
                }
            ]
        },
        {
            "file_id": "f2057160469076a2a843f2c5b3a6a1e2",
            "imdb_id": -1,
            "tvdb_id": -1,
            "tmdb_id": 14956,
            "saga": "Doll House",
            "season": 1,
            "episode": 5,
            "genre": [
                "Sci-Fi & Fantasy",
                "Action & Adventure",
                "Dramma"
            ],
            "title": "Fede",
            "fname": "/SerieTV/Doll House (2009) [a14956]/1.005 - Fede.mp4",
            "year": "2009",
            "plot": "Eliza Dushku interpreta una giovane donna di nome Echo, appartenente ad un gruppo di persone, chiamate \"attivi\" o \"doll\", totalmente controllate dalla misteriosa e segreta organizzazione \"Dollhouse\". Le doll sono in realt\u00e0 giovani di ambo i sessi, fisicamente attraenti e atletici, che si sono sottoposti (si suppone volontariamente) ad un procedimento di totale cancellazione dei ricordi delle loro pregresse esperienze di vita. In conseguenza di tale processo, la loro personalit\u00e0 diviene neutra, infantile, ingenua e quasi del tutto assente. La macchina che produce all'annullamento, e grazie a ci\u00f2, permette inoltre alla societ\u00e0 Dollhouse di imprimere a ciascun attivo sempre nuove e distinte personalit\u00e0, in base alle necessit\u00e0 contingenti dell'organizzazione.",
            "director": [],
            "actors": [
                "Eliza Dushku",
                "Fran Kranz",
                "Olivia Williams",
                "Dichen Lachman",
                "Enver Gjokaj",
                "Tahmoh Penikett",
                "Harry Lennix",
                "Amy Acker"
            ],
            "poster": "/oq5WPzUn7R0YcIk7QGwpXqvgSWO.jpg",
            "links": [
                {
                    "url": "http://51.77.159.233:30299/f2057160469076a2a843f2c5b3a6a1e2"
                }
            ]
        },
        {
            "file_id": "4e8f45d9607553cbb61806af9cf78c4a",
            "imdb_id": -1,
            "tvdb_id": -1,
            "tmdb_id": 14956,
            "saga": "Doll House",
            "season": 1,
            "episode": 6,
            "genre": [
                "Sci-Fi & Fantasy",
                "Action & Adventure",
                "Dramma"
            ],
            "title": "Doppio inganno",
            "fname": "/SerieTV/Doll House (2009) [a14956]/1.006 - Doppio inganno.mp4",
            "year": "2009",
            "plot": "Eliza Dushku interpreta una giovane donna di nome Echo, appartenente ad un gruppo di persone, chiamate \"attivi\" o \"doll\", totalmente controllate dalla misteriosa e segreta organizzazione \"Dollhouse\". Le doll sono in realt\u00e0 giovani di ambo i sessi, fisicamente attraenti e atletici, che si sono sottoposti (si suppone volontariamente) ad un procedimento di totale cancellazione dei ricordi delle loro pregresse esperienze di vita. In conseguenza di tale processo, la loro personalit\u00e0 diviene neutra, infantile, ingenua e quasi del tutto assente. La macchina che produce all'annullamento, e grazie a ci\u00f2, permette inoltre alla societ\u00e0 Dollhouse di imprimere a ciascun attivo sempre nuove e distinte personalit\u00e0, in base alle necessit\u00e0 contingenti dell'organizzazione.",
            "director": [],
            "actors": [
                "Eliza Dushku",
                "Fran Kranz",
                "Olivia Williams",
                "Dichen Lachman",
                "Enver Gjokaj",
                "Tahmoh Penikett",
                "Harry Lennix",
                "Amy Acker"
            ],
            "poster": "/oq5WPzUn7R0YcIk7QGwpXqvgSWO.jpg",
            "links": [
                {
                    "url": "http://51.77.159.233:30299/4e8f45d9607553cbb61806af9cf78c4a"
                }
            ]
        },
        {
            "file_id": "e3a1e04621944806983914b5adf5e74d",
            "imdb_id": -1,
            "tvdb_id": -1,
            "tmdb_id": 14956,
            "saga": "Doll House",
            "season": 1,
            "episode": 7,
            "genre": [
                "Sci-Fi & Fantasy",
                "Action & Adventure",
                "Dramma"
            ],
            "title": "Echi",
            "fname": "/SerieTV/Doll House (2009) [a14956]/1.007 - Echi.mp4",
            "year": "2009",
            "plot": "Eliza Dushku interpreta una giovane donna di nome Echo, appartenente ad un gruppo di persone, chiamate \"attivi\" o \"doll\", totalmente controllate dalla misteriosa e segreta organizzazione \"Dollhouse\". Le doll sono in realt\u00e0 giovani di ambo i sessi, fisicamente attraenti e atletici, che si sono sottoposti (si suppone volontariamente) ad un procedimento di totale cancellazione dei ricordi delle loro pregresse esperienze di vita. In conseguenza di tale processo, la loro personalit\u00e0 diviene neutra, infantile, ingenua e quasi del tutto assente. La macchina che produce all'annullamento, e grazie a ci\u00f2, permette inoltre alla societ\u00e0 Dollhouse di imprimere a ciascun attivo sempre nuove e distinte personalit\u00e0, in base alle necessit\u00e0 contingenti dell'organizzazione.",
            "director": [],
            "actors": [
                "Eliza Dushku",
                "Fran Kranz",
                "Olivia Williams",
                "Dichen Lachman",
                "Enver Gjokaj",
                "Tahmoh Penikett",
                "Harry Lennix",
                "Amy Acker"
            ],
            "poster": "/oq5WPzUn7R0YcIk7QGwpXqvgSWO.jpg",
            "links": [
                {
                    "url": "http://51.77.159.233:30299/e3a1e04621944806983914b5adf5e74d"
                }
            ]
        },
        {
            "file_id": "5013079f5ad02d72c3de8c9666ce0f60",
            "imdb_id": -1,
            "tvdb_id": -1,
            "tmdb_id": 14956,
            "saga": "Doll House",
            "season": 1,
            "episode": 8,
            "genre": [
                "Sci-Fi & Fantasy",
                "Action & Adventure",
                "Dramma"
            ],
            "title": "Ferite aperte",
            "fname": "/SerieTV/Doll House (2009) [a14956]/1.008 - Ferite aperte.mp4",
            "year": "2009",
            "plot": "Eliza Dushku interpreta una giovane donna di nome Echo, appartenente ad un gruppo di persone, chiamate \"attivi\" o \"doll\", totalmente controllate dalla misteriosa e segreta organizzazione \"Dollhouse\". Le doll sono in realt\u00e0 giovani di ambo i sessi, fisicamente attraenti e atletici, che si sono sottoposti (si suppone volontariamente) ad un procedimento di totale cancellazione dei ricordi delle loro pregresse esperienze di vita. In conseguenza di tale processo, la loro personalit\u00e0 diviene neutra, infantile, ingenua e quasi del tutto assente. La macchina che produce all'annullamento, e grazie a ci\u00f2, permette inoltre alla societ\u00e0 Dollhouse di imprimere a ciascun attivo sempre nuove e distinte personalit\u00e0, in base alle necessit\u00e0 contingenti dell'organizzazione.",
            "director": [],
            "actors": [
                "Eliza Dushku",
                "Fran Kranz",
                "Olivia Williams",
                "Dichen Lachman",
                "Enver Gjokaj",
                "Tahmoh Penikett",
                "Harry Lennix",
                "Amy Acker"
            ],
            "poster": "/oq5WPzUn7R0YcIk7QGwpXqvgSWO.jpg",
            "links": [
                {
                    "url": "http://51.77.159.233:30299/5013079f5ad02d72c3de8c9666ce0f60"
                }
            ]
        },
        {
            "file_id": "0f6cde9e7eee0171d20846ee4775dc1b",
            "imdb_id": -1,
            "tvdb_id": -1,
            "tmdb_id": 14956,
            "saga": "Doll House",
            "season": 1,
            "episode": 9,
            "genre": [
                "Sci-Fi & Fantasy",
                "Action & Adventure",
                "Dramma"
            ],
            "title": "La spia",
            "fname": "/SerieTV/Doll House (2009) [a14956]/1.009 - La spia.mp4",
            "year": "2009",
            "plot": "Eliza Dushku interpreta una giovane donna di nome Echo, appartenente ad un gruppo di persone, chiamate \"attivi\" o \"doll\", totalmente controllate dalla misteriosa e segreta organizzazione \"Dollhouse\". Le doll sono in realt\u00e0 giovani di ambo i sessi, fisicamente attraenti e atletici, che si sono sottoposti (si suppone volontariamente) ad un procedimento di totale cancellazione dei ricordi delle loro pregresse esperienze di vita. In conseguenza di tale processo, la loro personalit\u00e0 diviene neutra, infantile, ingenua e quasi del tutto assente. La macchina che produce all'annullamento, e grazie a ci\u00f2, permette inoltre alla societ\u00e0 Dollhouse di imprimere a ciascun attivo sempre nuove e distinte personalit\u00e0, in base alle necessit\u00e0 contingenti dell'organizzazione.",
            "director": [],
            "actors": [
                "Eliza Dushku",
                "Fran Kranz",
                "Olivia Williams",
                "Dichen Lachman",
                "Enver Gjokaj",
                "Tahmoh Penikett",
                "Harry Lennix",
                "Amy Acker"
            ],
            "poster": "/oq5WPzUn7R0YcIk7QGwpXqvgSWO.jpg",
            "links": [
                {
                    "url": "http://51.77.159.233:30299/0f6cde9e7eee0171d20846ee4775dc1b"
                }
            ]
        },
        {
            "file_id": "2b7c4186c7d3784d15a9ad336826d346",
            "imdb_id": -1,
            "tvdb_id": -1,
            "tmdb_id": 14956,
            "saga": "Doll House",
            "season": 1,
            "episode": 10,
            "genre": [
                "Sci-Fi & Fantasy",
                "Action & Adventure",
                "Dramma"
            ],
            "title": "Un`amica speciale",
            "fname": "/SerieTV/Doll House (2009) [a14956]/1.010 - Un`amica speciale.mp4",
            "year": "2009",
            "plot": "Eliza Dushku interpreta una giovane donna di nome Echo, appartenente ad un gruppo di persone, chiamate \"attivi\" o \"doll\", totalmente controllate dalla misteriosa e segreta organizzazione \"Dollhouse\". Le doll sono in realt\u00e0 giovani di ambo i sessi, fisicamente attraenti e atletici, che si sono sottoposti (si suppone volontariamente) ad un procedimento di totale cancellazione dei ricordi delle loro pregresse esperienze di vita. In conseguenza di tale processo, la loro personalit\u00e0 diviene neutra, infantile, ingenua e quasi del tutto assente. La macchina che produce all'annullamento, e grazie a ci\u00f2, permette inoltre alla societ\u00e0 Dollhouse di imprimere a ciascun attivo sempre nuove e distinte personalit\u00e0, in base alle necessit\u00e0 contingenti dell'organizzazione.",
            "director": [],
            "actors": [
                "Eliza Dushku",
                "Fran Kranz",
                "Olivia Williams",
                "Dichen Lachman",
                "Enver Gjokaj",
                "Tahmoh Penikett",
                "Harry Lennix",
                "Amy Acker"
            ],
            "poster": "/oq5WPzUn7R0YcIk7QGwpXqvgSWO.jpg",
            "links": [
                {
                    "url": "http://51.77.159.233:30299/2b7c4186c7d3784d15a9ad336826d346"
                }
            ]
        },
        {
            "file_id": "20ae37cda04912c616289a484a6ab818",
            "imdb_id": -1,
            "tvdb_id": -1,
            "tmdb_id": 14956,
            "saga": "Doll House",
            "season": 1,
            "episode": 11,
            "genre": [
                "Sci-Fi & Fantasy",
                "Action & Adventure",
                "Dramma"
            ],
            "title": "Fuga dalla dollhouse",
            "fname": "/SerieTV/Doll House (2009) [a14956]/1.011 - Fuga dalla dollhouse.mp4",
            "year": "2009",
            "plot": "Eliza Dushku interpreta una giovane donna di nome Echo, appartenente ad un gruppo di persone, chiamate \"attivi\" o \"doll\", totalmente controllate dalla misteriosa e segreta organizzazione \"Dollhouse\". Le doll sono in realt\u00e0 giovani di ambo i sessi, fisicamente attraenti e atletici, che si sono sottoposti (si suppone volontariamente) ad un procedimento di totale cancellazione dei ricordi delle loro pregresse esperienze di vita. In conseguenza di tale processo, la loro personalit\u00e0 diviene neutra, infantile, ingenua e quasi del tutto assente. La macchina che produce all'annullamento, e grazie a ci\u00f2, permette inoltre alla societ\u00e0 Dollhouse di imprimere a ciascun attivo sempre nuove e distinte personalit\u00e0, in base alle necessit\u00e0 contingenti dell'organizzazione.",
            "director": [],
            "actors": [
                "Eliza Dushku",
                "Fran Kranz",
                "Olivia Williams",
                "Dichen Lachman",
                "Enver Gjokaj",
                "Tahmoh Penikett",
                "Harry Lennix",
                "Amy Acker"
            ],
            "poster": "/oq5WPzUn7R0YcIk7QGwpXqvgSWO.jpg",
            "links": [
                {
                    "url": "http://51.77.159.233:30299/20ae37cda04912c616289a484a6ab818"
                }
            ]
        },
        {
            "file_id": "606f2591ccfccb0c6415a4aeacfddbf6",
            "imdb_id": -1,
            "tvdb_id": -1,
            "tmdb_id": 14956,
            "saga": "Doll House",
            "season": 1,
            "episode": 12,
            "genre": [
                "Sci-Fi & Fantasy",
                "Action & Adventure",
                "Dramma"
            ],
            "title": "La numero uno",
            "fname": "/SerieTV/Doll House (2009) [a14956]/1.012 - La numero uno.mp4",
            "year": "2009",
            "plot": "Eliza Dushku interpreta una giovane donna di nome Echo, appartenente ad un gruppo di persone, chiamate \"attivi\" o \"doll\", totalmente controllate dalla misteriosa e segreta organizzazione \"Dollhouse\". Le doll sono in realt\u00e0 giovani di ambo i sessi, fisicamente attraenti e atletici, che si sono sottoposti (si suppone volontariamente) ad un procedimento di totale cancellazione dei ricordi delle loro pregresse esperienze di vita. In conseguenza di tale processo, la loro personalit\u00e0 diviene neutra, infantile, ingenua e quasi del tutto assente. La macchina che produce all'annullamento, e grazie a ci\u00f2, permette inoltre alla societ\u00e0 Dollhouse di imprimere a ciascun attivo sempre nuove e distinte personalit\u00e0, in base alle necessit\u00e0 contingenti dell'organizzazione.",
            "director": [],
            "actors": [
                "Eliza Dushku",
                "Fran Kranz",
                "Olivia Williams",
                "Dichen Lachman",
                "Enver Gjokaj",
                "Tahmoh Penikett",
                "Harry Lennix",
                "Amy Acker"
            ],
            "poster": "/oq5WPzUn7R0YcIk7QGwpXqvgSWO.jpg",
            "links": [
                {
                    "url": "http://51.77.159.233:30299/606f2591ccfccb0c6415a4aeacfddbf6"
                }
            ]
        },
        {
            "file_id": "087cf8abca75a258cfddbb88c0516fc1",
            "imdb_id": -1,
            "tvdb_id": -1,
            "tmdb_id": 14956,
            "saga": "Doll House",
            "season": 1,
            "episode": 13,
            "genre": [
                "Sci-Fi & Fantasy",
                "Action & Adventure",
                "Dramma"
            ],
            "title": "Epitaph one",
            "fname": "/SerieTV/Doll House (2009) [a14956]/1.013 - Epitaph one.mp4",
            "year": "2009",
            "plot": "Eliza Dushku interpreta una giovane donna di nome Echo, appartenente ad un gruppo di persone, chiamate \"attivi\" o \"doll\", totalmente controllate dalla misteriosa e segreta organizzazione \"Dollhouse\". Le doll sono in realt\u00e0 giovani di ambo i sessi, fisicamente attraenti e atletici, che si sono sottoposti (si suppone volontariamente) ad un procedimento di totale cancellazione dei ricordi delle loro pregresse esperienze di vita. In conseguenza di tale processo, la loro personalit\u00e0 diviene neutra, infantile, ingenua e quasi del tutto assente. La macchina che produce all'annullamento, e grazie a ci\u00f2, permette inoltre alla societ\u00e0 Dollhouse di imprimere a ciascun attivo sempre nuove e distinte personalit\u00e0, in base alle necessit\u00e0 contingenti dell'organizzazione.",
            "director": [],
            "actors": [
                "Eliza Dushku",
                "Fran Kranz",
                "Olivia Williams",
                "Dichen Lachman",
                "Enver Gjokaj",
                "Tahmoh Penikett",
                "Harry Lennix",
                "Amy Acker"
            ],
            "poster": "/oq5WPzUn7R0YcIk7QGwpXqvgSWO.jpg",
            "links": [
                {
                    "url": "http://51.77.159.233:30299/087cf8abca75a258cfddbb88c0516fc1"
                }
            ]
        },
        {
            "file_id": "6a1eccb3d47b0b5ea5fcf2552de96463",
            "imdb_id": -1,
            "tvdb_id": -1,
            "tmdb_id": 14956,
            "saga": "Doll House",
            "season": 2,
            "episode": 1,
            "genre": [
                "Sci-Fi & Fantasy",
                "Action & Adventure",
                "Dramma"
            ],
            "title": "Voti",
            "fname": "/SerieTV/Doll House (2009) [a14956]/2.001 - Voti.mp4",
            "year": "2009",
            "plot": "Eliza Dushku interpreta una giovane donna di nome Echo, appartenente ad un gruppo di persone, chiamate \"attivi\" o \"doll\", totalmente controllate dalla misteriosa e segreta organizzazione \"Dollhouse\". Le doll sono in realt\u00e0 giovani di ambo i sessi, fisicamente attraenti e atletici, che si sono sottoposti (si suppone volontariamente) ad un procedimento di totale cancellazione dei ricordi delle loro pregresse esperienze di vita. In conseguenza di tale processo, la loro personalit\u00e0 diviene neutra, infantile, ingenua e quasi del tutto assente. La macchina che produce all'annullamento, e grazie a ci\u00f2, permette inoltre alla societ\u00e0 Dollhouse di imprimere a ciascun attivo sempre nuove e distinte personalit\u00e0, in base alle necessit\u00e0 contingenti dell'organizzazione.",
            "director": [],
            "actors": [
                "Eliza Dushku",
                "Fran Kranz",
                "Olivia Williams",
                "Dichen Lachman",
                "Enver Gjokaj",
                "Tahmoh Penikett",
                "Harry Lennix",
                "Amy Acker"
            ],
            "poster": "/oq5WPzUn7R0YcIk7QGwpXqvgSWO.jpg",
            "links": [
                {
                    "url": "http://51.77.159.233:30299/6a1eccb3d47b0b5ea5fcf2552de96463"
                }
            ]
        },
        {
            "file_id": "74981f8e5bb997636821ae49b658a202",
            "imdb_id": -1,
            "tvdb_id": -1,
            "tmdb_id": 14956,
            "saga": "Doll House",
            "season": 2,
            "episode": 2,
            "genre": [
                "Sci-Fi & Fantasy",
                "Action & Adventure",
                "Dramma"
            ],
            "title": "Istinto",
            "fname": "/SerieTV/Doll House (2009) [a14956]/2.002 - Istinto.mp4",
            "year": "2009",
            "plot": "Eliza Dushku interpreta una giovane donna di nome Echo, appartenente ad un gruppo di persone, chiamate \"attivi\" o \"doll\", totalmente controllate dalla misteriosa e segreta organizzazione \"Dollhouse\". Le doll sono in realt\u00e0 giovani di ambo i sessi, fisicamente attraenti e atletici, che si sono sottoposti (si suppone volontariamente) ad un procedimento di totale cancellazione dei ricordi delle loro pregresse esperienze di vita. In conseguenza di tale processo, la loro personalit\u00e0 diviene neutra, infantile, ingenua e quasi del tutto assente. La macchina che produce all'annullamento, e grazie a ci\u00f2, permette inoltre alla societ\u00e0 Dollhouse di imprimere a ciascun attivo sempre nuove e distinte personalit\u00e0, in base alle necessit\u00e0 contingenti dell'organizzazione.",
            "director": [],
            "actors": [
                "Eliza Dushku",
                "Fran Kranz",
                "Olivia Williams",
                "Dichen Lachman",
                "Enver Gjokaj",
                "Tahmoh Penikett",
                "Harry Lennix",
                "Amy Acker"
            ],
            "poster": "/oq5WPzUn7R0YcIk7QGwpXqvgSWO.jpg",
            "links": [
                {
                    "url": "http://51.77.159.233:30299/74981f8e5bb997636821ae49b658a202"
                }
            ]
        },
        {
            "file_id": "81e8103b18d9f87ae6d7bbe35ae79fe8",
            "imdb_id": -1,
            "tvdb_id": -1,
            "tmdb_id": 14956,
            "saga": "Doll House",
            "season": 2,
            "episode": 3,
            "genre": [
                "Sci-Fi & Fantasy",
                "Action & Adventure",
                "Dramma"
            ],
            "title": "Scambio di personalit\u00e0",
            "fname": "/SerieTV/Doll House (2009) [a14956]/2.003 - Scambio di personalit\u00e0.mp4",
            "year": "2009",
            "plot": "Eliza Dushku interpreta una giovane donna di nome Echo, appartenente ad un gruppo di persone, chiamate \"attivi\" o \"doll\", totalmente controllate dalla misteriosa e segreta organizzazione \"Dollhouse\". Le doll sono in realt\u00e0 giovani di ambo i sessi, fisicamente attraenti e atletici, che si sono sottoposti (si suppone volontariamente) ad un procedimento di totale cancellazione dei ricordi delle loro pregresse esperienze di vita. In conseguenza di tale processo, la loro personalit\u00e0 diviene neutra, infantile, ingenua e quasi del tutto assente. La macchina che produce all'annullamento, e grazie a ci\u00f2, permette inoltre alla societ\u00e0 Dollhouse di imprimere a ciascun attivo sempre nuove e distinte personalit\u00e0, in base alle necessit\u00e0 contingenti dell'organizzazione.",
            "director": [],
            "actors": [
                "Eliza Dushku",
                "Fran Kranz",
                "Olivia Williams",
                "Dichen Lachman",
                "Enver Gjokaj",
                "Tahmoh Penikett",
                "Harry Lennix",
                "Amy Acker"
            ],
            "poster": "/oq5WPzUn7R0YcIk7QGwpXqvgSWO.jpg",
            "links": [
                {
                    "url": "http://51.77.159.233:30299/81e8103b18d9f87ae6d7bbe35ae79fe8"
                }
            ]
        },
        {
            "file_id": "d9fee8e4c8e13e73c407b956f196b0a7",
            "imdb_id": -1,
            "tvdb_id": -1,
            "tmdb_id": 14956,
            "saga": "Doll House",
            "season": 2,
            "episode": 4,
            "genre": [
                "Sci-Fi & Fantasy",
                "Action & Adventure",
                "Dramma"
            ],
            "title": "Un amore malato",
            "fname": "/SerieTV/Doll House (2009) [a14956]/2.004 - Un amore malato.mp4",
            "year": "2009",
            "plot": "Eliza Dushku interpreta una giovane donna di nome Echo, appartenente ad un gruppo di persone, chiamate \"attivi\" o \"doll\", totalmente controllate dalla misteriosa e segreta organizzazione \"Dollhouse\". Le doll sono in realt\u00e0 giovani di ambo i sessi, fisicamente attraenti e atletici, che si sono sottoposti (si suppone volontariamente) ad un procedimento di totale cancellazione dei ricordi delle loro pregresse esperienze di vita. In conseguenza di tale processo, la loro personalit\u00e0 diviene neutra, infantile, ingenua e quasi del tutto assente. La macchina che produce all'annullamento, e grazie a ci\u00f2, permette inoltre alla societ\u00e0 Dollhouse di imprimere a ciascun attivo sempre nuove e distinte personalit\u00e0, in base alle necessit\u00e0 contingenti dell'organizzazione.",
            "director": [],
            "actors": [
                "Eliza Dushku",
                "Fran Kranz",
                "Olivia Williams",
                "Dichen Lachman",
                "Enver Gjokaj",
                "Tahmoh Penikett",
                "Harry Lennix",
                "Amy Acker"
            ],
            "poster": "/oq5WPzUn7R0YcIk7QGwpXqvgSWO.jpg",
            "links": [
                {
                    "url": "http://51.77.159.233:30299/d9fee8e4c8e13e73c407b956f196b0a7"
                }
            ]
        },
        {
            "file_id": "827364c26398e288e4fce99742c78d18",
            "imdb_id": -1,
            "tvdb_id": -1,
            "tmdb_id": 14956,
            "saga": "Doll House",
            "season": 2,
            "episode": 5,
            "genre": [
                "Sci-Fi & Fantasy",
                "Action & Adventure",
                "Dramma"
            ],
            "title": "Il complotto",
            "fname": "/SerieTV/Doll House (2009) [a14956]/2.005 - Il complotto.mp4",
            "year": "2009",
            "plot": "Eliza Dushku interpreta una giovane donna di nome Echo, appartenente ad un gruppo di persone, chiamate \"attivi\" o \"doll\", totalmente controllate dalla misteriosa e segreta organizzazione \"Dollhouse\". Le doll sono in realt\u00e0 giovani di ambo i sessi, fisicamente attraenti e atletici, che si sono sottoposti (si suppone volontariamente) ad un procedimento di totale cancellazione dei ricordi delle loro pregresse esperienze di vita. In conseguenza di tale processo, la loro personalit\u00e0 diviene neutra, infantile, ingenua e quasi del tutto assente. La macchina che produce all'annullamento, e grazie a ci\u00f2, permette inoltre alla societ\u00e0 Dollhouse di imprimere a ciascun attivo sempre nuove e distinte personalit\u00e0, in base alle necessit\u00e0 contingenti dell'organizzazione.",
            "director": [],
            "actors": [
                "Eliza Dushku",
                "Fran Kranz",
                "Olivia Williams",
                "Dichen Lachman",
                "Enver Gjokaj",
                "Tahmoh Penikett",
                "Harry Lennix",
                "Amy Acker"
            ],
            "poster": "/oq5WPzUn7R0YcIk7QGwpXqvgSWO.jpg",
            "links": [
                {
                    "url": "http://51.77.159.233:30299/827364c26398e288e4fce99742c78d18"
                }
            ]
        },
        {
            "file_id": "672efb868b2a013b3a7ab66dc8b3dada",
            "imdb_id": -1,
            "tvdb_id": -1,
            "tmdb_id": 14956,
            "saga": "Doll House",
            "season": 2,
            "episode": 6,
            "genre": [
                "Sci-Fi & Fantasy",
                "Action & Adventure",
                "Dramma"
            ],
            "title": "Liberi dalla dollhouse",
            "fname": "/SerieTV/Doll House (2009) [a14956]/2.006 - Liberi dalla dollhouse.mp4",
            "year": "2009",
            "plot": "Eliza Dushku interpreta una giovane donna di nome Echo, appartenente ad un gruppo di persone, chiamate \"attivi\" o \"doll\", totalmente controllate dalla misteriosa e segreta organizzazione \"Dollhouse\". Le doll sono in realt\u00e0 giovani di ambo i sessi, fisicamente attraenti e atletici, che si sono sottoposti (si suppone volontariamente) ad un procedimento di totale cancellazione dei ricordi delle loro pregresse esperienze di vita. In conseguenza di tale processo, la loro personalit\u00e0 diviene neutra, infantile, ingenua e quasi del tutto assente. La macchina che produce all'annullamento, e grazie a ci\u00f2, permette inoltre alla societ\u00e0 Dollhouse di imprimere a ciascun attivo sempre nuove e distinte personalit\u00e0, in base alle necessit\u00e0 contingenti dell'organizzazione.",
            "director": [],
            "actors": [
                "Eliza Dushku",
                "Fran Kranz",
                "Olivia Williams",
                "Dichen Lachman",
                "Enver Gjokaj",
                "Tahmoh Penikett",
                "Harry Lennix",
                "Amy Acker"
            ],
            "poster": "/oq5WPzUn7R0YcIk7QGwpXqvgSWO.jpg",
            "links": [
                {
                    "url": "http://51.77.159.233:30299/672efb868b2a013b3a7ab66dc8b3dada"
                }
            ]
        },
        {
            "file_id": "d2fee193e55696c752461e3280d52c33",
            "imdb_id": -1,
            "tvdb_id": -1,
            "tmdb_id": 14956,
            "saga": "Doll House",
            "season": 2,
            "episode": 7,
            "genre": [
                "Sci-Fi & Fantasy",
                "Action & Adventure",
                "Dramma"
            ],
            "title": "Donna non identificata",
            "fname": "/SerieTV/Doll House (2009) [a14956]/2.007 - Donna non identificata.mp4",
            "year": "2009",
            "plot": "Eliza Dushku interpreta una giovane donna di nome Echo, appartenente ad un gruppo di persone, chiamate \"attivi\" o \"doll\", totalmente controllate dalla misteriosa e segreta organizzazione \"Dollhouse\". Le doll sono in realt\u00e0 giovani di ambo i sessi, fisicamente attraenti e atletici, che si sono sottoposti (si suppone volontariamente) ad un procedimento di totale cancellazione dei ricordi delle loro pregresse esperienze di vita. In conseguenza di tale processo, la loro personalit\u00e0 diviene neutra, infantile, ingenua e quasi del tutto assente. La macchina che produce all'annullamento, e grazie a ci\u00f2, permette inoltre alla societ\u00e0 Dollhouse di imprimere a ciascun attivo sempre nuove e distinte personalit\u00e0, in base alle necessit\u00e0 contingenti dell'organizzazione.",
            "director": [],
            "actors": [
                "Eliza Dushku",
                "Fran Kranz",
                "Olivia Williams",
                "Dichen Lachman",
                "Enver Gjokaj",
                "Tahmoh Penikett",
                "Harry Lennix",
                "Amy Acker"
            ],
            "poster": "/oq5WPzUn7R0YcIk7QGwpXqvgSWO.jpg",
            "links": [
                {
                    "url": "http://51.77.159.233:30299/d2fee193e55696c752461e3280d52c33"
                }
            ]
        },
        {
            "file_id": "4dcb97d0043733f6fadbf82f340f791b",
            "imdb_id": -1,
            "tvdb_id": -1,
            "tmdb_id": 14956,
            "saga": "Doll House",
            "season": 2,
            "episode": 8,
            "genre": [
                "Sci-Fi & Fantasy",
                "Action & Adventure",
                "Dramma"
            ],
            "title": "Un amore immenso",
            "fname": "/SerieTV/Doll House (2009) [a14956]/2.008 - Un amore immenso.mp4",
            "year": "2009",
            "plot": "Eliza Dushku interpreta una giovane donna di nome Echo, appartenente ad un gruppo di persone, chiamate \"attivi\" o \"doll\", totalmente controllate dalla misteriosa e segreta organizzazione \"Dollhouse\". Le doll sono in realt\u00e0 giovani di ambo i sessi, fisicamente attraenti e atletici, che si sono sottoposti (si suppone volontariamente) ad un procedimento di totale cancellazione dei ricordi delle loro pregresse esperienze di vita. In conseguenza di tale processo, la loro personalit\u00e0 diviene neutra, infantile, ingenua e quasi del tutto assente. La macchina che produce all'annullamento, e grazie a ci\u00f2, permette inoltre alla societ\u00e0 Dollhouse di imprimere a ciascun attivo sempre nuove e distinte personalit\u00e0, in base alle necessit\u00e0 contingenti dell'organizzazione.",
            "director": [],
            "actors": [
                "Eliza Dushku",
                "Fran Kranz",
                "Olivia Williams",
                "Dichen Lachman",
                "Enver Gjokaj",
                "Tahmoh Penikett",
                "Harry Lennix",
                "Amy Acker"
            ],
            "poster": "/oq5WPzUn7R0YcIk7QGwpXqvgSWO.jpg",
            "links": [
                {
                    "url": "http://51.77.159.233:30299/4dcb97d0043733f6fadbf82f340f791b"
                }
            ]
        },
        {
            "file_id": "6abbb84e6b1bf257dadd06ad329eda85",
            "imdb_id": -1,
            "tvdb_id": -1,
            "tmdb_id": 14956,
            "saga": "Doll House",
            "season": 2,
            "episode": 9,
            "genre": [
                "Sci-Fi & Fantasy",
                "Action & Adventure",
                "Dramma"
            ],
            "title": "Contratto scaduto",
            "fname": "/SerieTV/Doll House (2009) [a14956]/2.009 - Contratto scaduto.mp4",
            "year": "2009",
            "plot": "Eliza Dushku interpreta una giovane donna di nome Echo, appartenente ad un gruppo di persone, chiamate \"attivi\" o \"doll\", totalmente controllate dalla misteriosa e segreta organizzazione \"Dollhouse\". Le doll sono in realt\u00e0 giovani di ambo i sessi, fisicamente attraenti e atletici, che si sono sottoposti (si suppone volontariamente) ad un procedimento di totale cancellazione dei ricordi delle loro pregresse esperienze di vita. In conseguenza di tale processo, la loro personalit\u00e0 diviene neutra, infantile, ingenua e quasi del tutto assente. La macchina che produce all'annullamento, e grazie a ci\u00f2, permette inoltre alla societ\u00e0 Dollhouse di imprimere a ciascun attivo sempre nuove e distinte personalit\u00e0, in base alle necessit\u00e0 contingenti dell'organizzazione.",
            "director": [],
            "actors": [
                "Eliza Dushku",
                "Fran Kranz",
                "Olivia Williams",
                "Dichen Lachman",
                "Enver Gjokaj",
                "Tahmoh Penikett",
                "Harry Lennix",
                "Amy Acker"
            ],
            "poster": "/oq5WPzUn7R0YcIk7QGwpXqvgSWO.jpg",
            "links": [
                {
                    "url": "http://51.77.159.233:30299/6abbb84e6b1bf257dadd06ad329eda85"
                }
            ]
        },
        {
            "file_id": "4eb22099e70748591e62277d5650e66e",
            "imdb_id": -1,
            "tvdb_id": -1,
            "tmdb_id": 14956,
            "saga": "Doll House",
            "season": 2,
            "episode": 10,
            "genre": [
                "Sci-Fi & Fantasy",
                "Action & Adventure",
                "Dramma"
            ],
            "title": "Il segreto",
            "fname": "/SerieTV/Doll House (2009) [a14956]/2.010 - Il segreto.mp4",
            "year": "2009",
            "plot": "Eliza Dushku interpreta una giovane donna di nome Echo, appartenente ad un gruppo di persone, chiamate \"attivi\" o \"doll\", totalmente controllate dalla misteriosa e segreta organizzazione \"Dollhouse\". Le doll sono in realt\u00e0 giovani di ambo i sessi, fisicamente attraenti e atletici, che si sono sottoposti (si suppone volontariamente) ad un procedimento di totale cancellazione dei ricordi delle loro pregresse esperienze di vita. In conseguenza di tale processo, la loro personalit\u00e0 diviene neutra, infantile, ingenua e quasi del tutto assente. La macchina che produce all'annullamento, e grazie a ci\u00f2, permette inoltre alla societ\u00e0 Dollhouse di imprimere a ciascun attivo sempre nuove e distinte personalit\u00e0, in base alle necessit\u00e0 contingenti dell'organizzazione.",
            "director": [],
            "actors": [
                "Eliza Dushku",
                "Fran Kranz",
                "Olivia Williams",
                "Dichen Lachman",
                "Enver Gjokaj",
                "Tahmoh Penikett",
                "Harry Lennix",
                "Amy Acker"
            ],
            "poster": "/oq5WPzUn7R0YcIk7QGwpXqvgSWO.jpg",
            "links": [
                {
                    "url": "http://51.77.159.233:30299/4eb22099e70748591e62277d5650e66e"
                }
            ]
        },
        {
            "file_id": "68a928884b64817dcd7ee0b39b92eda5",
            "imdb_id": -1,
            "tvdb_id": -1,
            "tmdb_id": 14956,
            "saga": "Doll House",
            "season": 2,
            "episode": 11,
            "genre": [
                "Sci-Fi & Fantasy",
                "Action & Adventure",
                "Dramma"
            ],
            "title": "Pericolo imminente",
            "fname": "/SerieTV/Doll House (2009) [a14956]/2.011 - Pericolo imminente.mp4",
            "year": "2009",
            "plot": "Eliza Dushku interpreta una giovane donna di nome Echo, appartenente ad un gruppo di persone, chiamate \"attivi\" o \"doll\", totalmente controllate dalla misteriosa e segreta organizzazione \"Dollhouse\". Le doll sono in realt\u00e0 giovani di ambo i sessi, fisicamente attraenti e atletici, che si sono sottoposti (si suppone volontariamente) ad un procedimento di totale cancellazione dei ricordi delle loro pregresse esperienze di vita. In conseguenza di tale processo, la loro personalit\u00e0 diviene neutra, infantile, ingenua e quasi del tutto assente. La macchina che produce all'annullamento, e grazie a ci\u00f2, permette inoltre alla societ\u00e0 Dollhouse di imprimere a ciascun attivo sempre nuove e distinte personalit\u00e0, in base alle necessit\u00e0 contingenti dell'organizzazione.",
            "director": [],
            "actors": [
                "Eliza Dushku",
                "Fran Kranz",
                "Olivia Williams",
                "Dichen Lachman",
                "Enver Gjokaj",
                "Tahmoh Penikett",
                "Harry Lennix",
                "Amy Acker"
            ],
            "poster": "/oq5WPzUn7R0YcIk7QGwpXqvgSWO.jpg",
            "links": [
                {
                    "url": "http://51.77.159.233:30299/68a928884b64817dcd7ee0b39b92eda5"
                }
            ]
        },
        {
            "file_id": "2fd7399854ab06e8ecc5c38424305870",
            "imdb_id": -1,
            "tvdb_id": -1,
            "tmdb_id": 14956,
            "saga": "Doll House",
            "season": 2,
            "episode": 12,
            "genre": [
                "Sci-Fi & Fantasy",
                "Action & Adventure",
                "Dramma"
            ],
            "title": "Resa dei conti",
            "fname": "/SerieTV/Doll House (2009) [a14956]/2.012 - Resa dei conti.mp4",
            "year": "2009",
            "plot": "Eliza Dushku interpreta una giovane donna di nome Echo, appartenente ad un gruppo di persone, chiamate \"attivi\" o \"doll\", totalmente controllate dalla misteriosa e segreta organizzazione \"Dollhouse\". Le doll sono in realt\u00e0 giovani di ambo i sessi, fisicamente attraenti e atletici, che si sono sottoposti (si suppone volontariamente) ad un procedimento di totale cancellazione dei ricordi delle loro pregresse esperienze di vita. In conseguenza di tale processo, la loro personalit\u00e0 diviene neutra, infantile, ingenua e quasi del tutto assente. La macchina che produce all'annullamento, e grazie a ci\u00f2, permette inoltre alla societ\u00e0 Dollhouse di imprimere a ciascun attivo sempre nuove e distinte personalit\u00e0, in base alle necessit\u00e0 contingenti dell'organizzazione.",
            "director": [],
            "actors": [
                "Eliza Dushku",
                "Fran Kranz",
                "Olivia Williams",
                "Dichen Lachman",
                "Enver Gjokaj",
                "Tahmoh Penikett",
                "Harry Lennix",
                "Amy Acker"
            ],
            "poster": "/oq5WPzUn7R0YcIk7QGwpXqvgSWO.jpg",
            "links": [
                {
                    "url": "http://51.77.159.233:30299/2fd7399854ab06e8ecc5c38424305870"
                }
            ]
        },
        {
            "file_id": "b6ecc613c1db0acf9b39b1450ed9082b",
            "imdb_id": -1,
            "tvdb_id": -1,
            "tmdb_id": 14956,
            "saga": "Doll House",
            "season": 2,
            "episode": 13,
            "genre": [
                "Sci-Fi & Fantasy",
                "Action & Adventure",
                "Dramma"
            ],
            "title": "Epitaph two il ritorno",
            "fname": "/SerieTV/Doll House (2009) [a14956]/2.013 - Epitaph two il ritorno.mp4",
            "year": "2009",
            "plot": "Eliza Dushku interpreta una giovane donna di nome Echo, appartenente ad un gruppo di persone, chiamate \"attivi\" o \"doll\", totalmente controllate dalla misteriosa e segreta organizzazione \"Dollhouse\". Le doll sono in realt\u00e0 giovani di ambo i sessi, fisicamente attraenti e atletici, che si sono sottoposti (si suppone volontariamente) ad un procedimento di totale cancellazione dei ricordi delle loro pregresse esperienze di vita. In conseguenza di tale processo, la loro personalit\u00e0 diviene neutra, infantile, ingenua e quasi del tutto assente. La macchina che produce all'annullamento, e grazie a ci\u00f2, permette inoltre alla societ\u00e0 Dollhouse di imprimere a ciascun attivo sempre nuove e distinte personalit\u00e0, in base alle necessit\u00e0 contingenti dell'organizzazione.",
            "director": [],
            "actors": [
                "Eliza Dushku",
                "Fran Kranz",
                "Olivia Williams",
                "Dichen Lachman",
                "Enver Gjokaj",
                "Tahmoh Penikett",
                "Harry Lennix",
                "Amy Acker"
            ],
            "poster": "/oq5WPzUn7R0YcIk7QGwpXqvgSWO.jpg",
            "links": [
                {
                    "url": "http://51.77.159.233:30299/b6ecc613c1db0acf9b39b1450ed9082b"
                }
            ]
        }
    ]
}