{
    "episodes_list": [
        {
            "file_id": "ee7ebf53bda66b3b31d159cdb890f344",
            "tmdb_id": 36664,
            "saga": "Georgie",
            "season": 1,
            "episode": 1,
            "genre": ["Animazione"],
            "title": "Il segreto del bracciale",
            "fname": "/Anime & Cartoni/Georgie [a36664]/1.01 - Il segreto del bracciale.avi",
            "year": "1983",
            "plot": "Georgie (\u30ec\u30c7\u30a3\u30b8\u30e7\u30fc\u30b8\u30a3\uff01) \u00e8 un anime del 1982 di Yumiko Igarashi ambientato nel XIX secolo tra l'Australia e l'Inghilterra che racconta le avventure di una ragazza alla ricerca delle proprie origini.",
            "actors": ["Yuriko Yamamoto", "Hideyuki Hori", "Isao Nagahisa", "Reiko Kit\u014d", "Sakiko Tamagawa", "Eiko Hisamura", "Ky\u014dsuke Maki", "Miyuki Ueda", "Y\u00fbji Mitsuya", "Yasuko End\u014d", "Hirotaka Suzuoki", "Kei Tomiyama", "Mami Koyama", "Masaaki Tsukada", "Yu Shimaka", "Masane Tsukayama"],
            "links": [
                {
                    "url": "http://51.77.159.233:30299/ee7ebf53bda66b3b31d159cdb890f344"
                }
            ]
        },
        {
            "file_id": "d0fba20c5fb74b5269f91a847e190bbe",
            "tmdb_id": 36664,
            "saga": "Georgie",
            "season": 1,
            "episode": 2,
            "genre": ["Animazione"],
            "title": "Tutti al lavoro!",
            "fname": "/Anime & Cartoni/Georgie [a36664]/1.02 - Tutti al lavoro!.avi",
            "year": "1983",
            "plot": "Georgie (\u30ec\u30c7\u30a3\u30b8\u30e7\u30fc\u30b8\u30a3\uff01) \u00e8 un anime del 1982 di Yumiko Igarashi ambientato nel XIX secolo tra l'Australia e l'Inghilterra che racconta le avventure di una ragazza alla ricerca delle proprie origini.",
            "actors": ["Yuriko Yamamoto", "Hideyuki Hori", "Isao Nagahisa", "Reiko Kit\u014d", "Sakiko Tamagawa", "Eiko Hisamura", "Ky\u014dsuke Maki", "Miyuki Ueda", "Y\u00fbji Mitsuya", "Yasuko End\u014d", "Hirotaka Suzuoki", "Kei Tomiyama", "Mami Koyama", "Masaaki Tsukada", "Yu Shimaka", "Masane Tsukayama"],
            "links": [
                {
                    "url": "http://51.77.159.233:30299/d0fba20c5fb74b5269f91a847e190bbe"
                }
            ]
        },
        {
            "file_id": "d09cb4e0669ae1384c4f0ff07a2597ec",
            "tmdb_id": 36664,
            "saga": "Georgie",
            "season": 1,
            "episode": 3,
            "genre": ["Animazione"],
            "title": "Sull'isola Lucertola",
            "fname": "/Anime & Cartoni/Georgie [a36664]/1.03 - Sull'isola Lucertola.avi",
            "year": "1983",
            "plot": "Georgie (\u30ec\u30c7\u30a3\u30b8\u30e7\u30fc\u30b8\u30a3\uff01) \u00e8 un anime del 1982 di Yumiko Igarashi ambientato nel XIX secolo tra l'Australia e l'Inghilterra che racconta le avventure di una ragazza alla ricerca delle proprie origini.",
            "actors": ["Yuriko Yamamoto", "Hideyuki Hori", "Isao Nagahisa", "Reiko Kit\u014d", "Sakiko Tamagawa", "Eiko Hisamura", "Ky\u014dsuke Maki", "Miyuki Ueda", "Y\u00fbji Mitsuya", "Yasuko End\u014d", "Hirotaka Suzuoki", "Kei Tomiyama", "Mami Koyama", "Masaaki Tsukada", "Yu Shimaka", "Masane Tsukayama"],
            "links": [
                {
                    "url": "http://51.77.159.233:30299/d09cb4e0669ae1384c4f0ff07a2597ec"
                }
            ]
        },
        {
            "file_id": "b87021576902c8914cdd33c4ff33aabb",
            "tmdb_id": 36664,
            "saga": "Georgie",
            "season": 1,
            "episode": 4,
            "genre": ["Animazione"],
            "title": "Pap\u00e0 muore",
            "fname": "/Anime & Cartoni/Georgie [a36664]/1.04 - Pap\u00e0 muore.avi",
            "year": "1983",
            "plot": "Georgie (\u30ec\u30c7\u30a3\u30b8\u30e7\u30fc\u30b8\u30a3\uff01) \u00e8 un anime del 1982 di Yumiko Igarashi ambientato nel XIX secolo tra l'Australia e l'Inghilterra che racconta le avventure di una ragazza alla ricerca delle proprie origini.",
            "actors": ["Yuriko Yamamoto", "Hideyuki Hori", "Isao Nagahisa", "Reiko Kit\u014d", "Sakiko Tamagawa", "Eiko Hisamura", "Ky\u014dsuke Maki", "Miyuki Ueda", "Y\u00fbji Mitsuya", "Yasuko End\u014d", "Hirotaka Suzuoki", "Kei Tomiyama", "Mami Koyama", "Masaaki Tsukada", "Yu Shimaka", "Masane Tsukayama"],
            "links": [
                {
                    "url": "http://51.77.159.233:30299/b87021576902c8914cdd33c4ff33aabb"
                }
            ]
        },
        {
            "file_id": "406729b4be2299eb6c709ed17adad181",
            "tmdb_id": 36664,
            "saga": "Georgie",
            "season": 1,
            "episode": 5,
            "genre": ["Animazione"],
            "title": "La nostra fattoria",
            "fname": "/Anime & Cartoni/Georgie [a36664]/1.05 - La nostra fattoria.avi",
            "year": "1983",
            "plot": "Georgie (\u30ec\u30c7\u30a3\u30b8\u30e7\u30fc\u30b8\u30a3\uff01) \u00e8 un anime del 1982 di Yumiko Igarashi ambientato nel XIX secolo tra l'Australia e l'Inghilterra che racconta le avventure di una ragazza alla ricerca delle proprie origini.",
            "actors": ["Yuriko Yamamoto", "Hideyuki Hori", "Isao Nagahisa", "Reiko Kit\u014d", "Sakiko Tamagawa", "Eiko Hisamura", "Ky\u014dsuke Maki", "Miyuki Ueda", "Y\u00fbji Mitsuya", "Yasuko End\u014d", "Hirotaka Suzuoki", "Kei Tomiyama", "Mami Koyama", "Masaaki Tsukada", "Yu Shimaka", "Masane Tsukayama"],
            "links": [
                {
                    "url": "http://51.77.159.233:30299/406729b4be2299eb6c709ed17adad181"
                }
            ]
        },
        {
            "file_id": "97065aab55f2b1b4a5208e06949170d4",
            "tmdb_id": 36664,
            "saga": "Georgie",
            "season": 1,
            "episode": 6,
            "genre": ["Animazione"],
            "title": "Sogni",
            "fname": "/Anime & Cartoni/Georgie [a36664]/1.06 - Sogni.avi",
            "year": "1983",
            "plot": "Georgie (\u30ec\u30c7\u30a3\u30b8\u30e7\u30fc\u30b8\u30a3\uff01) \u00e8 un anime del 1982 di Yumiko Igarashi ambientato nel XIX secolo tra l'Australia e l'Inghilterra che racconta le avventure di una ragazza alla ricerca delle proprie origini.",
            "actors": ["Yuriko Yamamoto", "Hideyuki Hori", "Isao Nagahisa", "Reiko Kit\u014d", "Sakiko Tamagawa", "Eiko Hisamura", "Ky\u014dsuke Maki", "Miyuki Ueda", "Y\u00fbji Mitsuya", "Yasuko End\u014d", "Hirotaka Suzuoki", "Kei Tomiyama", "Mami Koyama", "Masaaki Tsukada", "Yu Shimaka", "Masane Tsukayama"],
            "links": [
                {
                    "url": "http://51.77.159.233:30299/97065aab55f2b1b4a5208e06949170d4"
                }
            ]
        },
        {
            "file_id": "873e16b5ba1b0b52d78feacf1d330cb0",
            "tmdb_id": 36664,
            "saga": "Georgie",
            "season": 1,
            "episode": 7,
            "genre": ["Animazione"],
            "title": "L'attore girovago",
            "fname": "/Anime & Cartoni/Georgie [a36664]/1.07 - L'attore girovago.avi",
            "year": "1983",
            "plot": "Georgie (\u30ec\u30c7\u30a3\u30b8\u30e7\u30fc\u30b8\u30a3\uff01) \u00e8 un anime del 1982 di Yumiko Igarashi ambientato nel XIX secolo tra l'Australia e l'Inghilterra che racconta le avventure di una ragazza alla ricerca delle proprie origini.",
            "actors": ["Yuriko Yamamoto", "Hideyuki Hori", "Isao Nagahisa", "Reiko Kit\u014d", "Sakiko Tamagawa", "Eiko Hisamura", "Ky\u014dsuke Maki", "Miyuki Ueda", "Y\u00fbji Mitsuya", "Yasuko End\u014d", "Hirotaka Suzuoki", "Kei Tomiyama", "Mami Koyama", "Masaaki Tsukada", "Yu Shimaka", "Masane Tsukayama"],
            "links": [
                {
                    "url": "http://51.77.159.233:30299/873e16b5ba1b0b52d78feacf1d330cb0"
                }
            ]
        },
        {
            "file_id": "1980a1d162b7645107432c80faf731d0",
            "tmdb_id": 36664,
            "saga": "Georgie",
            "season": 1,
            "episode": 8,
            "genre": ["Animazione"],
            "title": "Scuola ke passione",
            "fname": "/Anime & Cartoni/Georgie [a36664]/1.08 - Scuola ke passione.avi",
            "year": "1983",
            "plot": "Georgie (\u30ec\u30c7\u30a3\u30b8\u30e7\u30fc\u30b8\u30a3\uff01) \u00e8 un anime del 1982 di Yumiko Igarashi ambientato nel XIX secolo tra l'Australia e l'Inghilterra che racconta le avventure di una ragazza alla ricerca delle proprie origini.",
            "actors": ["Yuriko Yamamoto", "Hideyuki Hori", "Isao Nagahisa", "Reiko Kit\u014d", "Sakiko Tamagawa", "Eiko Hisamura", "Ky\u014dsuke Maki", "Miyuki Ueda", "Y\u00fbji Mitsuya", "Yasuko End\u014d", "Hirotaka Suzuoki", "Kei Tomiyama", "Mami Koyama", "Masaaki Tsukada", "Yu Shimaka", "Masane Tsukayama"],
            "links": [
                {
                    "url": "http://51.77.159.233:30299/1980a1d162b7645107432c80faf731d0"
                }
            ]
        },
        {
            "file_id": "eac56990ea09348b30913cc66dda0a06",
            "tmdb_id": 36664,
            "saga": "Georgie",
            "season": 1,
            "episode": 9,
            "genre": ["Animazione"],
            "title": "Il cambiamento di Abel",
            "fname": "/Anime & Cartoni/Georgie [a36664]/1.09 - Il cambiamento di Abel.avi",
            "year": "1983",
            "plot": "Georgie (\u30ec\u30c7\u30a3\u30b8\u30e7\u30fc\u30b8\u30a3\uff01) \u00e8 un anime del 1982 di Yumiko Igarashi ambientato nel XIX secolo tra l'Australia e l'Inghilterra che racconta le avventure di una ragazza alla ricerca delle proprie origini.",
            "actors": ["Yuriko Yamamoto", "Hideyuki Hori", "Isao Nagahisa", "Reiko Kit\u014d", "Sakiko Tamagawa", "Eiko Hisamura", "Ky\u014dsuke Maki", "Miyuki Ueda", "Y\u00fbji Mitsuya", "Yasuko End\u014d", "Hirotaka Suzuoki", "Kei Tomiyama", "Mami Koyama", "Masaaki Tsukada", "Yu Shimaka", "Masane Tsukayama"],
            "links": [
                {
                    "url": "http://51.77.159.233:30299/eac56990ea09348b30913cc66dda0a06"
                }
            ]
        },
        {
            "file_id": "66f6ec685ec640354b041b1c577929b3",
            "tmdb_id": 36664,
            "saga": "Georgie",
            "season": 1,
            "episode": 10,
            "genre": ["Animazione"],
            "title": "Un regalo per la mamma",
            "fname": "/Anime & Cartoni/Georgie [a36664]/1.10 - Un regalo per la mamma.avi",
            "year": "1983",
            "plot": "Georgie (\u30ec\u30c7\u30a3\u30b8\u30e7\u30fc\u30b8\u30a3\uff01) \u00e8 un anime del 1982 di Yumiko Igarashi ambientato nel XIX secolo tra l'Australia e l'Inghilterra che racconta le avventure di una ragazza alla ricerca delle proprie origini.",
            "actors": ["Yuriko Yamamoto", "Hideyuki Hori", "Isao Nagahisa", "Reiko Kit\u014d", "Sakiko Tamagawa", "Eiko Hisamura", "Ky\u014dsuke Maki", "Miyuki Ueda", "Y\u00fbji Mitsuya", "Yasuko End\u014d", "Hirotaka Suzuoki", "Kei Tomiyama", "Mami Koyama", "Masaaki Tsukada", "Yu Shimaka", "Masane Tsukayama"],
            "links": [
                {
                    "url": "http://51.77.159.233:30299/66f6ec685ec640354b041b1c577929b3"
                }
            ]
        },
        {
            "file_id": "6ea9e989c1cbcc953b5985be980746f8",
            "tmdb_id": 36664,
            "saga": "Georgie",
            "season": 1,
            "episode": 11,
            "genre": ["Animazione"],
            "title": "Un visitatore inaspettato",
            "fname": "/Anime & Cartoni/Georgie [a36664]/1.11 - Un visitatore inaspettato.avi",
            "year": "1983",
            "plot": "Georgie (\u30ec\u30c7\u30a3\u30b8\u30e7\u30fc\u30b8\u30a3\uff01) \u00e8 un anime del 1982 di Yumiko Igarashi ambientato nel XIX secolo tra l'Australia e l'Inghilterra che racconta le avventure di una ragazza alla ricerca delle proprie origini.",
            "actors": ["Yuriko Yamamoto", "Hideyuki Hori", "Isao Nagahisa", "Reiko Kit\u014d", "Sakiko Tamagawa", "Eiko Hisamura", "Ky\u014dsuke Maki", "Miyuki Ueda", "Y\u00fbji Mitsuya", "Yasuko End\u014d", "Hirotaka Suzuoki", "Kei Tomiyama", "Mami Koyama", "Masaaki Tsukada", "Yu Shimaka", "Masane Tsukayama"],
            "links": [
                {
                    "url": "http://51.77.159.233:30299/6ea9e989c1cbcc953b5985be980746f8"
                }
            ]
        },
        {
            "file_id": "160da67eebaf78f29557070cf5d94cf0",
            "tmdb_id": 36664,
            "saga": "Georgie",
            "season": 1,
            "episode": 12,
            "genre": ["Animazione"],
            "title": "La camera separata",
            "fname": "/Anime & Cartoni/Georgie [a36664]/1.12 - La camera separata.avi",
            "year": "1983",
            "plot": "Georgie (\u30ec\u30c7\u30a3\u30b8\u30e7\u30fc\u30b8\u30a3\uff01) \u00e8 un anime del 1982 di Yumiko Igarashi ambientato nel XIX secolo tra l'Australia e l'Inghilterra che racconta le avventure di una ragazza alla ricerca delle proprie origini.",
            "actors": ["Yuriko Yamamoto", "Hideyuki Hori", "Isao Nagahisa", "Reiko Kit\u014d", "Sakiko Tamagawa", "Eiko Hisamura", "Ky\u014dsuke Maki", "Miyuki Ueda", "Y\u00fbji Mitsuya", "Yasuko End\u014d", "Hirotaka Suzuoki", "Kei Tomiyama", "Mami Koyama", "Masaaki Tsukada", "Yu Shimaka", "Masane Tsukayama"],
            "links": [
                {
                    "url": "http://51.77.159.233:30299/160da67eebaf78f29557070cf5d94cf0"
                }
            ]
        },
        {
            "file_id": "1ce971be06912cb656ae791051395f7e",
            "tmdb_id": 36664,
            "saga": "Georgie",
            "season": 1,
            "episode": 13,
            "genre": ["Animazione"],
            "title": "Abel \u00e8 geloso",
            "fname": "/Anime & Cartoni/Georgie [a36664]/1.13 - Abel \u00e8 geloso.avi",
            "year": "1983",
            "plot": "Georgie (\u30ec\u30c7\u30a3\u30b8\u30e7\u30fc\u30b8\u30a3\uff01) \u00e8 un anime del 1982 di Yumiko Igarashi ambientato nel XIX secolo tra l'Australia e l'Inghilterra che racconta le avventure di una ragazza alla ricerca delle proprie origini.",
            "actors": ["Yuriko Yamamoto", "Hideyuki Hori", "Isao Nagahisa", "Reiko Kit\u014d", "Sakiko Tamagawa", "Eiko Hisamura", "Ky\u014dsuke Maki", "Miyuki Ueda", "Y\u00fbji Mitsuya", "Yasuko End\u014d", "Hirotaka Suzuoki", "Kei Tomiyama", "Mami Koyama", "Masaaki Tsukada", "Yu Shimaka", "Masane Tsukayama"],
            "links": [
                {
                    "url": "http://51.77.159.233:30299/1ce971be06912cb656ae791051395f7e"
                }
            ]
        },
        {
            "file_id": "cfb3104e6f767fb2b2171fc7c7f4d80e",
            "tmdb_id": 36664,
            "saga": "Georgie",
            "season": 1,
            "episode": 14,
            "genre": ["Animazione"],
            "title": "Voglia di crescere",
            "fname": "/Anime & Cartoni/Georgie [a36664]/1.14 - Voglia di crescere.avi",
            "year": "1983",
            "plot": "Georgie (\u30ec\u30c7\u30a3\u30b8\u30e7\u30fc\u30b8\u30a3\uff01) \u00e8 un anime del 1982 di Yumiko Igarashi ambientato nel XIX secolo tra l'Australia e l'Inghilterra che racconta le avventure di una ragazza alla ricerca delle proprie origini.",
            "actors": ["Yuriko Yamamoto", "Hideyuki Hori", "Isao Nagahisa", "Reiko Kit\u014d", "Sakiko Tamagawa", "Eiko Hisamura", "Ky\u014dsuke Maki", "Miyuki Ueda", "Y\u00fbji Mitsuya", "Yasuko End\u014d", "Hirotaka Suzuoki", "Kei Tomiyama", "Mami Koyama", "Masaaki Tsukada", "Yu Shimaka", "Masane Tsukayama"],
            "links": [
                {
                    "url": "http://51.77.159.233:30299/cfb3104e6f767fb2b2171fc7c7f4d80e"
                }
            ]
        },
        {
            "file_id": "efad59a6d261882561e182286766e8ba",
            "tmdb_id": 36664,
            "saga": "Georgie",
            "season": 1,
            "episode": 15,
            "genre": ["Animazione"],
            "title": "Primi turbamenti",
            "fname": "/Anime & Cartoni/Georgie [a36664]/1.15 - Primi turbamenti.avi",
            "year": "1983",
            "plot": "Georgie (\u30ec\u30c7\u30a3\u30b8\u30e7\u30fc\u30b8\u30a3\uff01) \u00e8 un anime del 1982 di Yumiko Igarashi ambientato nel XIX secolo tra l'Australia e l'Inghilterra che racconta le avventure di una ragazza alla ricerca delle proprie origini.",
            "actors": ["Yuriko Yamamoto", "Hideyuki Hori", "Isao Nagahisa", "Reiko Kit\u014d", "Sakiko Tamagawa", "Eiko Hisamura", "Ky\u014dsuke Maki", "Miyuki Ueda", "Y\u00fbji Mitsuya", "Yasuko End\u014d", "Hirotaka Suzuoki", "Kei Tomiyama", "Mami Koyama", "Masaaki Tsukada", "Yu Shimaka", "Masane Tsukayama"],
            "links": [
                {
                    "url": "http://51.77.159.233:30299/efad59a6d261882561e182286766e8ba"
                }
            ]
        },
        {
            "file_id": "0bf36b97cb3b8521e76227db1eac9d03",
            "tmdb_id": 36664,
            "saga": "Georgie",
            "season": 1,
            "episode": 16,
            "genre": ["Animazione"],
            "title": "Il compleanno di Becky",
            "fname": "/Anime & Cartoni/Georgie [a36664]/1.16 - Il compleanno di Becky.avi",
            "year": "1983",
            "plot": "Georgie (\u30ec\u30c7\u30a3\u30b8\u30e7\u30fc\u30b8\u30a3\uff01) \u00e8 un anime del 1982 di Yumiko Igarashi ambientato nel XIX secolo tra l'Australia e l'Inghilterra che racconta le avventure di una ragazza alla ricerca delle proprie origini.",
            "actors": ["Yuriko Yamamoto", "Hideyuki Hori", "Isao Nagahisa", "Reiko Kit\u014d", "Sakiko Tamagawa", "Eiko Hisamura", "Ky\u014dsuke Maki", "Miyuki Ueda", "Y\u00fbji Mitsuya", "Yasuko End\u014d", "Hirotaka Suzuoki", "Kei Tomiyama", "Mami Koyama", "Masaaki Tsukada", "Yu Shimaka", "Masane Tsukayama"],
            "links": [
                {
                    "url": "http://51.77.159.233:30299/0bf36b97cb3b8521e76227db1eac9d03"
                }
            ]
        },
        {
            "file_id": "22d5196d3f6ad02050e2d03c9034dc24",
            "tmdb_id": 36664,
            "saga": "Georgie",
            "season": 1,
            "episode": 17,
            "genre": ["Animazione"],
            "title": "La bugia di Arthur",
            "fname": "/Anime & Cartoni/Georgie [a36664]/1.17 - La bugia di Arthur.avi",
            "year": "1983",
            "plot": "Georgie (\u30ec\u30c7\u30a3\u30b8\u30e7\u30fc\u30b8\u30a3\uff01) \u00e8 un anime del 1982 di Yumiko Igarashi ambientato nel XIX secolo tra l'Australia e l'Inghilterra che racconta le avventure di una ragazza alla ricerca delle proprie origini.",
            "actors": ["Yuriko Yamamoto", "Hideyuki Hori", "Isao Nagahisa", "Reiko Kit\u014d", "Sakiko Tamagawa", "Eiko Hisamura", "Ky\u014dsuke Maki", "Miyuki Ueda", "Y\u00fbji Mitsuya", "Yasuko End\u014d", "Hirotaka Suzuoki", "Kei Tomiyama", "Mami Koyama", "Masaaki Tsukada", "Yu Shimaka", "Masane Tsukayama"],
            "links": [
                {
                    "url": "http://51.77.159.233:30299/22d5196d3f6ad02050e2d03c9034dc24"
                }
            ]
        },
        {
            "file_id": "7cf27cd895620a39da541fb84b07f0ea",
            "tmdb_id": 36664,
            "saga": "Georgie",
            "season": 1,
            "episode": 18,
            "genre": ["Animazione"],
            "title": "Una amica per Lupp",
            "fname": "/Anime & Cartoni/Georgie [a36664]/1.18 - Una amica per Lupp.avi",
            "year": "1983",
            "plot": "Georgie (\u30ec\u30c7\u30a3\u30b8\u30e7\u30fc\u30b8\u30a3\uff01) \u00e8 un anime del 1982 di Yumiko Igarashi ambientato nel XIX secolo tra l'Australia e l'Inghilterra che racconta le avventure di una ragazza alla ricerca delle proprie origini.",
            "actors": ["Yuriko Yamamoto", "Hideyuki Hori", "Isao Nagahisa", "Reiko Kit\u014d", "Sakiko Tamagawa", "Eiko Hisamura", "Ky\u014dsuke Maki", "Miyuki Ueda", "Y\u00fbji Mitsuya", "Yasuko End\u014d", "Hirotaka Suzuoki", "Kei Tomiyama", "Mami Koyama", "Masaaki Tsukada", "Yu Shimaka", "Masane Tsukayama"],
            "links": [
                {
                    "url": "http://51.77.159.233:30299/7cf27cd895620a39da541fb84b07f0ea"
                }
            ]
        },
        {
            "file_id": "c3b05de4c151862c07f290b26a61aa99",
            "tmdb_id": 36664,
            "saga": "Georgie",
            "season": 1,
            "episode": 19,
            "genre": ["Animazione"],
            "title": "Una difficile decisione",
            "fname": "/Anime & Cartoni/Georgie [a36664]/1.19 - Una difficile decisione.avi",
            "year": "1983",
            "plot": "Georgie (\u30ec\u30c7\u30a3\u30b8\u30e7\u30fc\u30b8\u30a3\uff01) \u00e8 un anime del 1982 di Yumiko Igarashi ambientato nel XIX secolo tra l'Australia e l'Inghilterra che racconta le avventure di una ragazza alla ricerca delle proprie origini.",
            "actors": ["Yuriko Yamamoto", "Hideyuki Hori", "Isao Nagahisa", "Reiko Kit\u014d", "Sakiko Tamagawa", "Eiko Hisamura", "Ky\u014dsuke Maki", "Miyuki Ueda", "Y\u00fbji Mitsuya", "Yasuko End\u014d", "Hirotaka Suzuoki", "Kei Tomiyama", "Mami Koyama", "Masaaki Tsukada", "Yu Shimaka", "Masane Tsukayama"],
            "links": [
                {
                    "url": "http://51.77.159.233:30299/c3b05de4c151862c07f290b26a61aa99"
                }
            ]
        },
        {
            "file_id": "fa3b72b4b922ca5db906e0d7dc4931d1",
            "tmdb_id": 36664,
            "saga": "Georgie",
            "season": 1,
            "episode": 20,
            "genre": ["Animazione"],
            "title": "Il futuro del capitano",
            "fname": "/Anime & Cartoni/Georgie [a36664]/1.20 - Il futuro del capitano.avi",
            "year": "1983",
            "plot": "Georgie (\u30ec\u30c7\u30a3\u30b8\u30e7\u30fc\u30b8\u30a3\uff01) \u00e8 un anime del 1982 di Yumiko Igarashi ambientato nel XIX secolo tra l'Australia e l'Inghilterra che racconta le avventure di una ragazza alla ricerca delle proprie origini.",
            "actors": ["Yuriko Yamamoto", "Hideyuki Hori", "Isao Nagahisa", "Reiko Kit\u014d", "Sakiko Tamagawa", "Eiko Hisamura", "Ky\u014dsuke Maki", "Miyuki Ueda", "Y\u00fbji Mitsuya", "Yasuko End\u014d", "Hirotaka Suzuoki", "Kei Tomiyama", "Mami Koyama", "Masaaki Tsukada", "Yu Shimaka", "Masane Tsukayama"],
            "links": [
                {
                    "url": "http://51.77.159.233:30299/fa3b72b4b922ca5db906e0d7dc4931d1"
                }
            ]
        },
        {
            "file_id": "e460a468d9500c238a96f28ef694bcfa",
            "tmdb_id": 36664,
            "saga": "Georgie",
            "season": 1,
            "episode": 21,
            "genre": ["Animazione"],
            "title": "Un incontro imbarazzante",
            "fname": "/Anime & Cartoni/Georgie [a36664]/1.21 - Un incontro imbarazzante.avi",
            "year": "1983",
            "plot": "Georgie (\u30ec\u30c7\u30a3\u30b8\u30e7\u30fc\u30b8\u30a3\uff01) \u00e8 un anime del 1982 di Yumiko Igarashi ambientato nel XIX secolo tra l'Australia e l'Inghilterra che racconta le avventure di una ragazza alla ricerca delle proprie origini.",
            "actors": ["Yuriko Yamamoto", "Hideyuki Hori", "Isao Nagahisa", "Reiko Kit\u014d", "Sakiko Tamagawa", "Eiko Hisamura", "Ky\u014dsuke Maki", "Miyuki Ueda", "Y\u00fbji Mitsuya", "Yasuko End\u014d", "Hirotaka Suzuoki", "Kei Tomiyama", "Mami Koyama", "Masaaki Tsukada", "Yu Shimaka", "Masane Tsukayama"],
            "links": [
                {
                    "url": "http://51.77.159.233:30299/e460a468d9500c238a96f28ef694bcfa"
                }
            ]
        },
        {
            "file_id": "3bf477829bb44fec0adf6e394db79173",
            "tmdb_id": 36664,
            "saga": "Georgie",
            "season": 1,
            "episode": 22,
            "genre": ["Animazione"],
            "title": "Bentornato Abel",
            "fname": "/Anime & Cartoni/Georgie [a36664]/1.22 - Bentornato Abel.avi",
            "year": "1983",
            "plot": "Georgie (\u30ec\u30c7\u30a3\u30b8\u30e7\u30fc\u30b8\u30a3\uff01) \u00e8 un anime del 1982 di Yumiko Igarashi ambientato nel XIX secolo tra l'Australia e l'Inghilterra che racconta le avventure di una ragazza alla ricerca delle proprie origini.",
            "actors": ["Yuriko Yamamoto", "Hideyuki Hori", "Isao Nagahisa", "Reiko Kit\u014d", "Sakiko Tamagawa", "Eiko Hisamura", "Ky\u014dsuke Maki", "Miyuki Ueda", "Y\u00fbji Mitsuya", "Yasuko End\u014d", "Hirotaka Suzuoki", "Kei Tomiyama", "Mami Koyama", "Masaaki Tsukada", "Yu Shimaka", "Masane Tsukayama"],
            "links": [
                {
                    "url": "http://51.77.159.233:30299/3bf477829bb44fec0adf6e394db79173"
                }
            ]
        },
        {
            "file_id": "ed734edd71148c0e8ef25a1c7d39637a",
            "tmdb_id": 36664,
            "saga": "Georgie",
            "season": 1,
            "episode": 23,
            "genre": ["Animazione"],
            "title": "La nuova ferrovia",
            "fname": "/Anime & Cartoni/Georgie [a36664]/1.23 - La nuova ferrovia.avi",
            "year": "1983",
            "plot": "Georgie (\u30ec\u30c7\u30a3\u30b8\u30e7\u30fc\u30b8\u30a3\uff01) \u00e8 un anime del 1982 di Yumiko Igarashi ambientato nel XIX secolo tra l'Australia e l'Inghilterra che racconta le avventure di una ragazza alla ricerca delle proprie origini.",
            "actors": ["Yuriko Yamamoto", "Hideyuki Hori", "Isao Nagahisa", "Reiko Kit\u014d", "Sakiko Tamagawa", "Eiko Hisamura", "Ky\u014dsuke Maki", "Miyuki Ueda", "Y\u00fbji Mitsuya", "Yasuko End\u014d", "Hirotaka Suzuoki", "Kei Tomiyama", "Mami Koyama", "Masaaki Tsukada", "Yu Shimaka", "Masane Tsukayama"],
            "links": [
                {
                    "url": "http://51.77.159.233:30299/ed734edd71148c0e8ef25a1c7d39637a"
                }
            ]
        },
        {
            "file_id": "42dba60cdb389f0b970b859a3540060a",
            "tmdb_id": 36664,
            "saga": "Georgie",
            "season": 1,
            "episode": 24,
            "genre": ["Animazione"],
            "title": "Il primo bacio",
            "fname": "/Anime & Cartoni/Georgie [a36664]/1.24 - Il primo bacio.avi",
            "year": "1983",
            "plot": "Georgie (\u30ec\u30c7\u30a3\u30b8\u30e7\u30fc\u30b8\u30a3\uff01) \u00e8 un anime del 1982 di Yumiko Igarashi ambientato nel XIX secolo tra l'Australia e l'Inghilterra che racconta le avventure di una ragazza alla ricerca delle proprie origini.",
            "actors": ["Yuriko Yamamoto", "Hideyuki Hori", "Isao Nagahisa", "Reiko Kit\u014d", "Sakiko Tamagawa", "Eiko Hisamura", "Ky\u014dsuke Maki", "Miyuki Ueda", "Y\u00fbji Mitsuya", "Yasuko End\u014d", "Hirotaka Suzuoki", "Kei Tomiyama", "Mami Koyama", "Masaaki Tsukada", "Yu Shimaka", "Masane Tsukayama"],
            "links": [
                {
                    "url": "http://51.77.159.233:30299/42dba60cdb389f0b970b859a3540060a"
                }
            ]
        },
        {
            "file_id": "0a529884bc5a39bab9a00b6d17b5650c",
            "tmdb_id": 36664,
            "saga": "Georgie",
            "season": 1,
            "episode": 25,
            "genre": ["Animazione"],
            "title": "Una dolorosa scoperta",
            "fname": "/Anime & Cartoni/Georgie [a36664]/1.25 - Una dolorosa scoperta.avi",
            "year": "1983",
            "plot": "Georgie (\u30ec\u30c7\u30a3\u30b8\u30e7\u30fc\u30b8\u30a3\uff01) \u00e8 un anime del 1982 di Yumiko Igarashi ambientato nel XIX secolo tra l'Australia e l'Inghilterra che racconta le avventure di una ragazza alla ricerca delle proprie origini.",
            "actors": ["Yuriko Yamamoto", "Hideyuki Hori", "Isao Nagahisa", "Reiko Kit\u014d", "Sakiko Tamagawa", "Eiko Hisamura", "Ky\u014dsuke Maki", "Miyuki Ueda", "Y\u00fbji Mitsuya", "Yasuko End\u014d", "Hirotaka Suzuoki", "Kei Tomiyama", "Mami Koyama", "Masaaki Tsukada", "Yu Shimaka", "Masane Tsukayama"],
            "links": [
                {
                    "url": "http://51.77.159.233:30299/0a529884bc5a39bab9a00b6d17b5650c"
                }
            ]
        },
        {
            "file_id": "3f77ffe02b5041a5263a0ca099c7ef1f",
            "tmdb_id": 36664,
            "saga": "Georgie",
            "season": 1,
            "episode": 26,
            "genre": ["Animazione"],
            "title": "Notte tempestosa",
            "fname": "/Anime & Cartoni/Georgie [a36664]/1.26 - Notte tempestosa.avi",
            "year": "1983",
            "plot": "Georgie (\u30ec\u30c7\u30a3\u30b8\u30e7\u30fc\u30b8\u30a3\uff01) \u00e8 un anime del 1982 di Yumiko Igarashi ambientato nel XIX secolo tra l'Australia e l'Inghilterra che racconta le avventure di una ragazza alla ricerca delle proprie origini.",
            "actors": ["Yuriko Yamamoto", "Hideyuki Hori", "Isao Nagahisa", "Reiko Kit\u014d", "Sakiko Tamagawa", "Eiko Hisamura", "Ky\u014dsuke Maki", "Miyuki Ueda", "Y\u00fbji Mitsuya", "Yasuko End\u014d", "Hirotaka Suzuoki", "Kei Tomiyama", "Mami Koyama", "Masaaki Tsukada", "Yu Shimaka", "Masane Tsukayama"],
            "links": [
                {
                    "url": "http://51.77.159.233:30299/3f77ffe02b5041a5263a0ca099c7ef1f"
                }
            ]
        },
        {
            "file_id": "5e0e9119215bfce482d4344b2e817849",
            "tmdb_id": 36664,
            "saga": "Georgie",
            "season": 1,
            "episode": 27,
            "genre": ["Animazione"],
            "title": "Il segreto svelato",
            "fname": "/Anime & Cartoni/Georgie [a36664]/1.27 - Il segreto svelato.avi",
            "year": "1983",
            "plot": "Georgie (\u30ec\u30c7\u30a3\u30b8\u30e7\u30fc\u30b8\u30a3\uff01) \u00e8 un anime del 1982 di Yumiko Igarashi ambientato nel XIX secolo tra l'Australia e l'Inghilterra che racconta le avventure di una ragazza alla ricerca delle proprie origini.",
            "actors": ["Yuriko Yamamoto", "Hideyuki Hori", "Isao Nagahisa", "Reiko Kit\u014d", "Sakiko Tamagawa", "Eiko Hisamura", "Ky\u014dsuke Maki", "Miyuki Ueda", "Y\u00fbji Mitsuya", "Yasuko End\u014d", "Hirotaka Suzuoki", "Kei Tomiyama", "Mami Koyama", "Masaaki Tsukada", "Yu Shimaka", "Masane Tsukayama"],
            "links": [
                {
                    "url": "http://51.77.159.233:30299/5e0e9119215bfce482d4344b2e817849"
                }
            ]
        },
        {
            "file_id": "25bea3c6e2af2fd52b6c0121051825ef",
            "tmdb_id": 36664,
            "saga": "Georgie",
            "season": 1,
            "episode": 28,
            "genre": ["Animazione"],
            "title": "Rivali in amore",
            "fname": "/Anime & Cartoni/Georgie [a36664]/1.28 - Rivali in amore.avi",
            "year": "1983",
            "plot": "Georgie (\u30ec\u30c7\u30a3\u30b8\u30e7\u30fc\u30b8\u30a3\uff01) \u00e8 un anime del 1982 di Yumiko Igarashi ambientato nel XIX secolo tra l'Australia e l'Inghilterra che racconta le avventure di una ragazza alla ricerca delle proprie origini.",
            "actors": ["Yuriko Yamamoto", "Hideyuki Hori", "Isao Nagahisa", "Reiko Kit\u014d", "Sakiko Tamagawa", "Eiko Hisamura", "Ky\u014dsuke Maki", "Miyuki Ueda", "Y\u00fbji Mitsuya", "Yasuko End\u014d", "Hirotaka Suzuoki", "Kei Tomiyama", "Mami Koyama", "Masaaki Tsukada", "Yu Shimaka", "Masane Tsukayama"],
            "links": [
                {
                    "url": "http://51.77.159.233:30299/25bea3c6e2af2fd52b6c0121051825ef"
                }
            ]
        },
        {
            "file_id": "2a72fff6f59a8420ab0a6a38b0a3ea66",
            "tmdb_id": 36664,
            "saga": "Georgie",
            "season": 1,
            "episode": 29,
            "genre": ["Animazione"],
            "title": "Il lungo viaggio",
            "fname": "/Anime & Cartoni/Georgie [a36664]/1.29 - Il lungo viaggio.avi",
            "year": "1983",
            "plot": "Georgie (\u30ec\u30c7\u30a3\u30b8\u30e7\u30fc\u30b8\u30a3\uff01) \u00e8 un anime del 1982 di Yumiko Igarashi ambientato nel XIX secolo tra l'Australia e l'Inghilterra che racconta le avventure di una ragazza alla ricerca delle proprie origini.",
            "actors": ["Yuriko Yamamoto", "Hideyuki Hori", "Isao Nagahisa", "Reiko Kit\u014d", "Sakiko Tamagawa", "Eiko Hisamura", "Ky\u014dsuke Maki", "Miyuki Ueda", "Y\u00fbji Mitsuya", "Yasuko End\u014d", "Hirotaka Suzuoki", "Kei Tomiyama", "Mami Koyama", "Masaaki Tsukada", "Yu Shimaka", "Masane Tsukayama"],
            "links": [
                {
                    "url": "http://51.77.159.233:30299/2a72fff6f59a8420ab0a6a38b0a3ea66"
                }
            ]
        },
        {
            "file_id": "26e1e36636bff9033f65c2c628ea8111",
            "tmdb_id": 36664,
            "saga": "Georgie",
            "season": 1,
            "episode": 30,
            "genre": ["Animazione"],
            "title": "Alla ricerca del passato",
            "fname": "/Anime & Cartoni/Georgie [a36664]/1.30 - Alla ricerca del passato .avi",
            "year": "1983",
            "plot": "Georgie (\u30ec\u30c7\u30a3\u30b8\u30e7\u30fc\u30b8\u30a3\uff01) \u00e8 un anime del 1982 di Yumiko Igarashi ambientato nel XIX secolo tra l'Australia e l'Inghilterra che racconta le avventure di una ragazza alla ricerca delle proprie origini.",
            "actors": ["Yuriko Yamamoto", "Hideyuki Hori", "Isao Nagahisa", "Reiko Kit\u014d", "Sakiko Tamagawa", "Eiko Hisamura", "Ky\u014dsuke Maki", "Miyuki Ueda", "Y\u00fbji Mitsuya", "Yasuko End\u014d", "Hirotaka Suzuoki", "Kei Tomiyama", "Mami Koyama", "Masaaki Tsukada", "Yu Shimaka", "Masane Tsukayama"],
            "links": [
                {
                    "url": "http://51.77.159.233:30299/26e1e36636bff9033f65c2c628ea8111"
                }
            ]
        },
        {
            "file_id": "1ebe4508fea1771ea0b4462440f25db2",
            "tmdb_id": 36664,
            "saga": "Georgie",
            "season": 1,
            "episode": 31,
            "genre": ["Animazione"],
            "title": "Da mozzo a cameriere",
            "fname": "/Anime & Cartoni/Georgie [a36664]/1.31 - Da mozzo a cameriere.avi",
            "year": "1983",
            "plot": "Georgie (\u30ec\u30c7\u30a3\u30b8\u30e7\u30fc\u30b8\u30a3\uff01) \u00e8 un anime del 1982 di Yumiko Igarashi ambientato nel XIX secolo tra l'Australia e l'Inghilterra che racconta le avventure di una ragazza alla ricerca delle proprie origini.",
            "actors": ["Yuriko Yamamoto", "Hideyuki Hori", "Isao Nagahisa", "Reiko Kit\u014d", "Sakiko Tamagawa", "Eiko Hisamura", "Ky\u014dsuke Maki", "Miyuki Ueda", "Y\u00fbji Mitsuya", "Yasuko End\u014d", "Hirotaka Suzuoki", "Kei Tomiyama", "Mami Koyama", "Masaaki Tsukada", "Yu Shimaka", "Masane Tsukayama"],
            "links": [
                {
                    "url": "http://51.77.159.233:30299/1ebe4508fea1771ea0b4462440f25db2"
                }
            ]
        },
        {
            "file_id": "58db4ced67eaa26397c3cbeb87529037",
            "tmdb_id": 36664,
            "saga": "Georgie",
            "season": 1,
            "episode": 32,
            "genre": ["Animazione"],
            "title": "Tre navi, tre sogni",
            "fname": "/Anime & Cartoni/Georgie [a36664]/1.32 - Tre navi, tre sogni.avi",
            "year": "1983",
            "plot": "Georgie (\u30ec\u30c7\u30a3\u30b8\u30e7\u30fc\u30b8\u30a3\uff01) \u00e8 un anime del 1982 di Yumiko Igarashi ambientato nel XIX secolo tra l'Australia e l'Inghilterra che racconta le avventure di una ragazza alla ricerca delle proprie origini.",
            "actors": ["Yuriko Yamamoto", "Hideyuki Hori", "Isao Nagahisa", "Reiko Kit\u014d", "Sakiko Tamagawa", "Eiko Hisamura", "Ky\u014dsuke Maki", "Miyuki Ueda", "Y\u00fbji Mitsuya", "Yasuko End\u014d", "Hirotaka Suzuoki", "Kei Tomiyama", "Mami Koyama", "Masaaki Tsukada", "Yu Shimaka", "Masane Tsukayama"],
            "links": [
                {
                    "url": "http://51.77.159.233:30299/58db4ced67eaa26397c3cbeb87529037"
                }
            ]
        },
        {
            "file_id": "ec5d5624fabbe850e540b48c35d72270",
            "tmdb_id": 36664,
            "saga": "Georgie",
            "season": 1,
            "episode": 33,
            "genre": ["Animazione"],
            "title": "Una terribile trappola",
            "fname": "/Anime & Cartoni/Georgie [a36664]/1.33 - Una terribile trappola.avi",
            "year": "1983",
            "plot": "Georgie (\u30ec\u30c7\u30a3\u30b8\u30e7\u30fc\u30b8\u30a3\uff01) \u00e8 un anime del 1982 di Yumiko Igarashi ambientato nel XIX secolo tra l'Australia e l'Inghilterra che racconta le avventure di una ragazza alla ricerca delle proprie origini.",
            "actors": ["Yuriko Yamamoto", "Hideyuki Hori", "Isao Nagahisa", "Reiko Kit\u014d", "Sakiko Tamagawa", "Eiko Hisamura", "Ky\u014dsuke Maki", "Miyuki Ueda", "Y\u00fbji Mitsuya", "Yasuko End\u014d", "Hirotaka Suzuoki", "Kei Tomiyama", "Mami Koyama", "Masaaki Tsukada", "Yu Shimaka", "Masane Tsukayama"],
            "links": [
                {
                    "url": "http://51.77.159.233:30299/ec5d5624fabbe850e540b48c35d72270"
                }
            ]
        },
        {
            "file_id": "3337fda6ee1792d09413f7b8583a6fa7",
            "tmdb_id": 36664,
            "saga": "Georgie",
            "season": 1,
            "episode": 34,
            "genre": ["Animazione"],
            "title": "Finalmente a Londra",
            "fname": "/Anime & Cartoni/Georgie [a36664]/1.34 - Finalmente a Londra.avi",
            "year": "1983",
            "plot": "Georgie (\u30ec\u30c7\u30a3\u30b8\u30e7\u30fc\u30b8\u30a3\uff01) \u00e8 un anime del 1982 di Yumiko Igarashi ambientato nel XIX secolo tra l'Australia e l'Inghilterra che racconta le avventure di una ragazza alla ricerca delle proprie origini.",
            "actors": ["Yuriko Yamamoto", "Hideyuki Hori", "Isao Nagahisa", "Reiko Kit\u014d", "Sakiko Tamagawa", "Eiko Hisamura", "Ky\u014dsuke Maki", "Miyuki Ueda", "Y\u00fbji Mitsuya", "Yasuko End\u014d", "Hirotaka Suzuoki", "Kei Tomiyama", "Mami Koyama", "Masaaki Tsukada", "Yu Shimaka", "Masane Tsukayama"],
            "links": [
                {
                    "url": "http://51.77.159.233:30299/3337fda6ee1792d09413f7b8583a6fa7"
                }
            ]
        },
        {
            "file_id": "5afd38415010d1eeef594297e218876b",
            "tmdb_id": 36664,
            "saga": "Georgie",
            "season": 1,
            "episode": 35,
            "genre": ["Animazione"],
            "title": "Il sogno della nonna",
            "fname": "/Anime & Cartoni/Georgie [a36664]/1.35 - Il sogno della nonna.avi",
            "year": "1983",
            "plot": "Georgie (\u30ec\u30c7\u30a3\u30b8\u30e7\u30fc\u30b8\u30a3\uff01) \u00e8 un anime del 1982 di Yumiko Igarashi ambientato nel XIX secolo tra l'Australia e l'Inghilterra che racconta le avventure di una ragazza alla ricerca delle proprie origini.",
            "actors": ["Yuriko Yamamoto", "Hideyuki Hori", "Isao Nagahisa", "Reiko Kit\u014d", "Sakiko Tamagawa", "Eiko Hisamura", "Ky\u014dsuke Maki", "Miyuki Ueda", "Y\u00fbji Mitsuya", "Yasuko End\u014d", "Hirotaka Suzuoki", "Kei Tomiyama", "Mami Koyama", "Masaaki Tsukada", "Yu Shimaka", "Masane Tsukayama"],
            "links": [
                {
                    "url": "http://51.77.159.233:30299/5afd38415010d1eeef594297e218876b"
                }
            ]
        },
        {
            "file_id": "4161a9a0c06e19907f6dded3aa2772d4",
            "tmdb_id": 36664,
            "saga": "Georgie",
            "season": 1,
            "episode": 36,
            "genre": ["Animazione"],
            "title": "Preparativi di nozze",
            "fname": "/Anime & Cartoni/Georgie [a36664]/1.36 - Preparativi di nozze.avi",
            "year": "1983",
            "plot": "Georgie (\u30ec\u30c7\u30a3\u30b8\u30e7\u30fc\u30b8\u30a3\uff01) \u00e8 un anime del 1982 di Yumiko Igarashi ambientato nel XIX secolo tra l'Australia e l'Inghilterra che racconta le avventure di una ragazza alla ricerca delle proprie origini.",
            "actors": ["Yuriko Yamamoto", "Hideyuki Hori", "Isao Nagahisa", "Reiko Kit\u014d", "Sakiko Tamagawa", "Eiko Hisamura", "Ky\u014dsuke Maki", "Miyuki Ueda", "Y\u00fbji Mitsuya", "Yasuko End\u014d", "Hirotaka Suzuoki", "Kei Tomiyama", "Mami Koyama", "Masaaki Tsukada", "Yu Shimaka", "Masane Tsukayama"],
            "links": [
                {
                    "url": "http://51.77.159.233:30299/4161a9a0c06e19907f6dded3aa2772d4"
                }
            ]
        },
        {
            "file_id": "c64333be865537cf443d5d1653012b64",
            "tmdb_id": 36664,
            "saga": "Georgie",
            "season": 1,
            "episode": 37,
            "genre": ["Animazione"],
            "title": "Delusioni per Elise",
            "fname": "/Anime & Cartoni/Georgie [a36664]/1.37 - Delusioni per Elise.avi",
            "year": "1983",
            "plot": "Georgie (\u30ec\u30c7\u30a3\u30b8\u30e7\u30fc\u30b8\u30a3\uff01) \u00e8 un anime del 1982 di Yumiko Igarashi ambientato nel XIX secolo tra l'Australia e l'Inghilterra che racconta le avventure di una ragazza alla ricerca delle proprie origini.",
            "actors": ["Yuriko Yamamoto", "Hideyuki Hori", "Isao Nagahisa", "Reiko Kit\u014d", "Sakiko Tamagawa", "Eiko Hisamura", "Ky\u014dsuke Maki", "Miyuki Ueda", "Y\u00fbji Mitsuya", "Yasuko End\u014d", "Hirotaka Suzuoki", "Kei Tomiyama", "Mami Koyama", "Masaaki Tsukada", "Yu Shimaka", "Masane Tsukayama"],
            "links": [
                {
                    "url": "http://51.77.159.233:30299/c64333be865537cf443d5d1653012b64"
                }
            ]
        },
        {
            "file_id": "ae61b7152c9ed8affa0d89db19cafb33",
            "tmdb_id": 36664,
            "saga": "Georgie",
            "season": 1,
            "episode": 38,
            "genre": ["Animazione"],
            "title": "Due nuovi amici",
            "fname": "/Anime & Cartoni/Georgie [a36664]/1.38 - Due nuovi amici.avi",
            "year": "1983",
            "plot": "Georgie (\u30ec\u30c7\u30a3\u30b8\u30e7\u30fc\u30b8\u30a3\uff01) \u00e8 un anime del 1982 di Yumiko Igarashi ambientato nel XIX secolo tra l'Australia e l'Inghilterra che racconta le avventure di una ragazza alla ricerca delle proprie origini.",
            "actors": ["Yuriko Yamamoto", "Hideyuki Hori", "Isao Nagahisa", "Reiko Kit\u014d", "Sakiko Tamagawa", "Eiko Hisamura", "Ky\u014dsuke Maki", "Miyuki Ueda", "Y\u00fbji Mitsuya", "Yasuko End\u014d", "Hirotaka Suzuoki", "Kei Tomiyama", "Mami Koyama", "Masaaki Tsukada", "Yu Shimaka", "Masane Tsukayama"],
            "links": [
                {
                    "url": "http://51.77.159.233:30299/ae61b7152c9ed8affa0d89db19cafb33"
                }
            ]
        },
        {
            "file_id": "f30fbe1f24ca85ce42cc363f1e8db2ae",
            "tmdb_id": 36664,
            "saga": "Georgie",
            "season": 1,
            "episode": 39,
            "genre": ["Animazione"],
            "title": "Al ballo reale",
            "fname": "/Anime & Cartoni/Georgie [a36664]/1.39 - Al ballo reale.avi",
            "year": "1983",
            "plot": "Georgie (\u30ec\u30c7\u30a3\u30b8\u30e7\u30fc\u30b8\u30a3\uff01) \u00e8 un anime del 1982 di Yumiko Igarashi ambientato nel XIX secolo tra l'Australia e l'Inghilterra che racconta le avventure di una ragazza alla ricerca delle proprie origini.",
            "actors": ["Yuriko Yamamoto", "Hideyuki Hori", "Isao Nagahisa", "Reiko Kit\u014d", "Sakiko Tamagawa", "Eiko Hisamura", "Ky\u014dsuke Maki", "Miyuki Ueda", "Y\u00fbji Mitsuya", "Yasuko End\u014d", "Hirotaka Suzuoki", "Kei Tomiyama", "Mami Koyama", "Masaaki Tsukada", "Yu Shimaka", "Masane Tsukayama"],
            "links": [
                {
                    "url": "http://51.77.159.233:30299/f30fbe1f24ca85ce42cc363f1e8db2ae"
                }
            ]
        },
        {
            "file_id": "52b1da27e3a8ae7f11cf9fd20e1350ef",
            "tmdb_id": 36664,
            "saga": "Georgie",
            "season": 1,
            "episode": 40,
            "genre": ["Animazione"],
            "title": "Di nuovo in viaggio",
            "fname": "/Anime & Cartoni/Georgie [a36664]/1.40 - Di nuovo in viaggio.avi",
            "year": "1983",
            "plot": "Georgie (\u30ec\u30c7\u30a3\u30b8\u30e7\u30fc\u30b8\u30a3\uff01) \u00e8 un anime del 1982 di Yumiko Igarashi ambientato nel XIX secolo tra l'Australia e l'Inghilterra che racconta le avventure di una ragazza alla ricerca delle proprie origini.",
            "actors": ["Yuriko Yamamoto", "Hideyuki Hori", "Isao Nagahisa", "Reiko Kit\u014d", "Sakiko Tamagawa", "Eiko Hisamura", "Ky\u014dsuke Maki", "Miyuki Ueda", "Y\u00fbji Mitsuya", "Yasuko End\u014d", "Hirotaka Suzuoki", "Kei Tomiyama", "Mami Koyama", "Masaaki Tsukada", "Yu Shimaka", "Masane Tsukayama"],
            "links": [
                {
                    "url": "http://51.77.159.233:30299/52b1da27e3a8ae7f11cf9fd20e1350ef"
                }
            ]
        },
        {
            "file_id": "85a751717de3afcded7b3658027ed2db",
            "tmdb_id": 36664,
            "saga": "Georgie",
            "season": 1,
            "episode": 41,
            "genre": ["Animazione"],
            "title": "La forza della speranza",
            "fname": "/Anime & Cartoni/Georgie [a36664]/1.41 - La forza della speranza.avi",
            "year": "1983",
            "plot": "Georgie (\u30ec\u30c7\u30a3\u30b8\u30e7\u30fc\u30b8\u30a3\uff01) \u00e8 un anime del 1982 di Yumiko Igarashi ambientato nel XIX secolo tra l'Australia e l'Inghilterra che racconta le avventure di una ragazza alla ricerca delle proprie origini.",
            "actors": ["Yuriko Yamamoto", "Hideyuki Hori", "Isao Nagahisa", "Reiko Kit\u014d", "Sakiko Tamagawa", "Eiko Hisamura", "Ky\u014dsuke Maki", "Miyuki Ueda", "Y\u00fbji Mitsuya", "Yasuko End\u014d", "Hirotaka Suzuoki", "Kei Tomiyama", "Mami Koyama", "Masaaki Tsukada", "Yu Shimaka", "Masane Tsukayama"],
            "links": [
                {
                    "url": "http://51.77.159.233:30299/85a751717de3afcded7b3658027ed2db"
                }
            ]
        },
        {
            "file_id": "68585a61f97f003b1918eca71c48b02c",
            "tmdb_id": 36664,
            "saga": "Georgie",
            "season": 1,
            "episode": 42,
            "genre": ["Animazione"],
            "title": "La prigionia di Arthur",
            "fname": "/Anime & Cartoni/Georgie [a36664]/1.42 - La prigionia di Arthur.avi",
            "year": "1983",
            "plot": "Georgie (\u30ec\u30c7\u30a3\u30b8\u30e7\u30fc\u30b8\u30a3\uff01) \u00e8 un anime del 1982 di Yumiko Igarashi ambientato nel XIX secolo tra l'Australia e l'Inghilterra che racconta le avventure di una ragazza alla ricerca delle proprie origini.",
            "actors": ["Yuriko Yamamoto", "Hideyuki Hori", "Isao Nagahisa", "Reiko Kit\u014d", "Sakiko Tamagawa", "Eiko Hisamura", "Ky\u014dsuke Maki", "Miyuki Ueda", "Y\u00fbji Mitsuya", "Yasuko End\u014d", "Hirotaka Suzuoki", "Kei Tomiyama", "Mami Koyama", "Masaaki Tsukada", "Yu Shimaka", "Masane Tsukayama"],
            "links": [
                {
                    "url": "http://51.77.159.233:30299/68585a61f97f003b1918eca71c48b02c"
                }
            ]
        },
        {
            "file_id": "41a32fad14f5700cedaea2395380433c",
            "tmdb_id": 36664,
            "saga": "Georgie",
            "season": 1,
            "episode": 43,
            "genre": ["Animazione"],
            "title": "Un amore impossibile",
            "fname": "/Anime & Cartoni/Georgie [a36664]/1.43 - Un amore impossibile.avi",
            "year": "1983",
            "plot": "Georgie (\u30ec\u30c7\u30a3\u30b8\u30e7\u30fc\u30b8\u30a3\uff01) \u00e8 un anime del 1982 di Yumiko Igarashi ambientato nel XIX secolo tra l'Australia e l'Inghilterra che racconta le avventure di una ragazza alla ricerca delle proprie origini.",
            "actors": ["Yuriko Yamamoto", "Hideyuki Hori", "Isao Nagahisa", "Reiko Kit\u014d", "Sakiko Tamagawa", "Eiko Hisamura", "Ky\u014dsuke Maki", "Miyuki Ueda", "Y\u00fbji Mitsuya", "Yasuko End\u014d", "Hirotaka Suzuoki", "Kei Tomiyama", "Mami Koyama", "Masaaki Tsukada", "Yu Shimaka", "Masane Tsukayama"],
            "links": [
                {
                    "url": "http://51.77.159.233:30299/41a32fad14f5700cedaea2395380433c"
                }
            ]
        },
        {
            "file_id": "fd52b120cbc21cc0aa32d0d1a56faf66",
            "tmdb_id": 36664,
            "saga": "Georgie",
            "season": 1,
            "episode": 44,
            "genre": ["Animazione"],
            "title": "Arthur in pericolo",
            "fname": "/Anime & Cartoni/Georgie [a36664]/1.44 - Arthur in pericolo.avi",
            "year": "1983",
            "plot": "Georgie (\u30ec\u30c7\u30a3\u30b8\u30e7\u30fc\u30b8\u30a3\uff01) \u00e8 un anime del 1982 di Yumiko Igarashi ambientato nel XIX secolo tra l'Australia e l'Inghilterra che racconta le avventure di una ragazza alla ricerca delle proprie origini.",
            "actors": ["Yuriko Yamamoto", "Hideyuki Hori", "Isao Nagahisa", "Reiko Kit\u014d", "Sakiko Tamagawa", "Eiko Hisamura", "Ky\u014dsuke Maki", "Miyuki Ueda", "Y\u00fbji Mitsuya", "Yasuko End\u014d", "Hirotaka Suzuoki", "Kei Tomiyama", "Mami Koyama", "Masaaki Tsukada", "Yu Shimaka", "Masane Tsukayama"],
            "links": [
                {
                    "url": "http://51.77.159.233:30299/fd52b120cbc21cc0aa32d0d1a56faf66"
                }
            ]
        },
        {
            "file_id": "f463f49e9a1ac9686d263ebfa718e1e7",
            "tmdb_id": 36664,
            "saga": "Georgie",
            "season": 1,
            "episode": 45,
            "genre": ["Animazione"],
            "title": "Finalmente insieme",
            "fname": "/Anime & Cartoni/Georgie [a36664]/1.45 - Finalmente insieme.avi",
            "year": "1983",
            "plot": "Georgie (\u30ec\u30c7\u30a3\u30b8\u30e7\u30fc\u30b8\u30a3\uff01) \u00e8 un anime del 1982 di Yumiko Igarashi ambientato nel XIX secolo tra l'Australia e l'Inghilterra che racconta le avventure di una ragazza alla ricerca delle proprie origini.",
            "actors": ["Yuriko Yamamoto", "Hideyuki Hori", "Isao Nagahisa", "Reiko Kit\u014d", "Sakiko Tamagawa", "Eiko Hisamura", "Ky\u014dsuke Maki", "Miyuki Ueda", "Y\u00fbji Mitsuya", "Yasuko End\u014d", "Hirotaka Suzuoki", "Kei Tomiyama", "Mami Koyama", "Masaaki Tsukada", "Yu Shimaka", "Masane Tsukayama"],
            "links": [
                {
                    "url": "http://51.77.159.233:30299/f463f49e9a1ac9686d263ebfa718e1e7"
                }
            ]
        }
    ]
}