{
    "episodes_list": [
        {
            "file_id": "3eb61404f53cfa9ba72e4f760e998f02",
            "tmdb_id": 25114,
            "saga": "L'Uomo Tigre",
            "season": 1,
            "episode": 1,
            "genre": ["Animazione", "Dramma"],
            "title": "Il Demone Giallo",
            "fname": "/Anime & Cartoni/L'Uomo Tigre (1969) [a25114]/1.001 - Il Demone Giallo.avi",
            "year": "1969",
            "actors": ["Kei Tomiyama", "Katsuji Mori", "Chisato Nakajima", "Keiichi Noda"],
            "links": [
                {
                    "url": "http://51.77.159.233:30299/3eb61404f53cfa9ba72e4f760e998f02"
                }
            ]
        },
        {
            "file_id": "7b3b29702fb4f7e867ea4a4fa48d62e0",
            "tmdb_id": 25114,
            "saga": "L'Uomo Tigre",
            "season": 1,
            "episode": 2,
            "genre": ["Animazione", "Dramma"],
            "title": "La fuga di Kenta",
            "fname": "/Anime & Cartoni/L'Uomo Tigre (1969) [a25114]/1.002 - La fuga di Kenta.avi",
            "year": "1969",
            "actors": ["Kei Tomiyama", "Katsuji Mori", "Chisato Nakajima", "Keiichi Noda"],
            "links": [
                {
                    "url": "http://51.77.159.233:30299/7b3b29702fb4f7e867ea4a4fa48d62e0"
                }
            ]
        },
        {
            "file_id": "f1f83ac4361fa077567ab5ca70e529bd",
            "tmdb_id": 25114,
            "saga": "L'Uomo Tigre",
            "season": 1,
            "episode": 3,
            "genre": ["Animazione", "Dramma"],
            "title": "Il Ritorno Di Naoto",
            "fname": "/Anime & Cartoni/L'Uomo Tigre (1969) [a25114]/1.003 - Il Ritorno Di Naoto.avi",
            "year": "1969",
            "actors": ["Kei Tomiyama", "Katsuji Mori", "Chisato Nakajima", "Keiichi Noda"],
            "links": [
                {
                    "url": "http://51.77.159.233:30299/f1f83ac4361fa077567ab5ca70e529bd"
                }
            ]
        },
        {
            "file_id": "31bdaed7ddee61a3f0937da4a425d156",
            "tmdb_id": 25114,
            "saga": "L'Uomo Tigre",
            "season": 1,
            "episode": 4,
            "genre": ["Animazione", "Dramma"],
            "title": "La Legge Della Tana Delle Tigri",
            "fname": "/Anime & Cartoni/L'Uomo Tigre (1969) [a25114]/1.004 - La Legge Della Tana Delle Tigri.avi",
            "year": "1969",
            "actors": ["Kei Tomiyama", "Katsuji Mori", "Chisato Nakajima", "Keiichi Noda"],
            "links": [
                {
                    "url": "http://51.77.159.233:30299/31bdaed7ddee61a3f0937da4a425d156"
                }
            ]
        },
        {
            "file_id": "8ca926d0b2650d009b57c9ba0683f85e",
            "tmdb_id": 25114,
            "saga": "L'Uomo Tigre",
            "season": 1,
            "episode": 5,
            "genre": ["Animazione", "Dramma"],
            "title": "Uomo Tigre Sfida Mister X",
            "fname": "/Anime & Cartoni/L'Uomo Tigre (1969) [a25114]/1.005 - Uomo Tigre Sfida Mister X.avi",
            "year": "1969",
            "actors": ["Kei Tomiyama", "Katsuji Mori", "Chisato Nakajima", "Keiichi Noda"],
            "links": [
                {
                    "url": "http://51.77.159.233:30299/8ca926d0b2650d009b57c9ba0683f85e"
                }
            ]
        },
        {
            "file_id": "23da51e5929bc7f9ef233c2bb7733383",
            "tmdb_id": 25114,
            "saga": "L'Uomo Tigre",
            "season": 1,
            "episode": 6,
            "genre": ["Animazione", "Dramma"],
            "title": "Pitone Nero",
            "fname": "/Anime & Cartoni/L'Uomo Tigre (1969) [a25114]/1.006 - Pitone Nero.avi",
            "year": "1969",
            "actors": ["Kei Tomiyama", "Katsuji Mori", "Chisato Nakajima", "Keiichi Noda"],
            "links": [
                {
                    "url": "http://51.77.159.233:30299/23da51e5929bc7f9ef233c2bb7733383"
                }
            ]
        },
        {
            "file_id": "a2160ab92b37cb806891e2889dc7fa2c",
            "tmdb_id": 25114,
            "saga": "L'Uomo Tigre",
            "season": 1,
            "episode": 7,
            "genre": ["Animazione", "Dramma"],
            "title": "Incontro Leale",
            "fname": "/Anime & Cartoni/L'Uomo Tigre (1969) [a25114]/1.007 - Incontro Leale.avi",
            "year": "1969",
            "actors": ["Kei Tomiyama", "Katsuji Mori", "Chisato Nakajima", "Keiichi Noda"],
            "links": [
                {
                    "url": "http://51.77.159.233:30299/a2160ab92b37cb806891e2889dc7fa2c"
                }
            ]
        },
        {
            "file_id": "603a45b8ad5d2a40259af791a35ce499",
            "tmdb_id": 25114,
            "saga": "L'Uomo Tigre",
            "season": 1,
            "episode": 8,
            "genre": ["Animazione", "Dramma"],
            "title": "La Trappola",
            "fname": "/Anime & Cartoni/L'Uomo Tigre (1969) [a25114]/1.008 - La Trappola.avi",
            "year": "1969",
            "actors": ["Kei Tomiyama", "Katsuji Mori", "Chisato Nakajima", "Keiichi Noda"],
            "links": [
                {
                    "url": "http://51.77.159.233:30299/603a45b8ad5d2a40259af791a35ce499"
                }
            ]
        },
        {
            "file_id": "069d62a97b99f7956b3734d4bd31ee63",
            "tmdb_id": 25114,
            "saga": "L'Uomo Tigre",
            "season": 1,
            "episode": 9,
            "genre": ["Animazione", "Dramma"],
            "title": "L'uomo Gorilla",
            "fname": "/Anime & Cartoni/L'Uomo Tigre (1969) [a25114]/1.009 - L'uomo Gorilla.avi",
            "year": "1969",
            "actors": ["Kei Tomiyama", "Katsuji Mori", "Chisato Nakajima", "Keiichi Noda"],
            "links": [
                {
                    "url": "http://51.77.159.233:30299/069d62a97b99f7956b3734d4bd31ee63"
                }
            ]
        },
        {
            "file_id": "15befd3e17f09fe31233b77d2f74036b",
            "tmdb_id": 25114,
            "saga": "L'Uomo Tigre",
            "season": 1,
            "episode": 10,
            "genre": ["Animazione", "Dramma"],
            "title": "Il Colpo Del Ponte",
            "fname": "/Anime & Cartoni/L'Uomo Tigre (1969) [a25114]/1.010 - Il Colpo Del Ponte.avi",
            "year": "1969",
            "actors": ["Kei Tomiyama", "Katsuji Mori", "Chisato Nakajima", "Keiichi Noda"],
            "links": [
                {
                    "url": "http://51.77.159.233:30299/15befd3e17f09fe31233b77d2f74036b"
                }
            ]
        },
        {
            "file_id": "5121d7385d833e8afab8b772e54400ef",
            "tmdb_id": 25114,
            "saga": "L'Uomo Tigre",
            "season": 1,
            "episode": 11,
            "genre": ["Animazione", "Dramma"],
            "title": "Lega Mondiale Professionisti",
            "fname": "/Anime & Cartoni/L'Uomo Tigre (1969) [a25114]/1.011 - Lega Mondiale Professionisti.avi",
            "year": "1969",
            "actors": ["Kei Tomiyama", "Katsuji Mori", "Chisato Nakajima", "Keiichi Noda"],
            "links": [
                {
                    "url": "http://51.77.159.233:30299/5121d7385d833e8afab8b772e54400ef"
                }
            ]
        },
        {
            "file_id": "11759b6f39da269141f4ea687fc41192",
            "tmdb_id": 25114,
            "saga": "L'Uomo Tigre",
            "season": 1,
            "episode": 12,
            "genre": ["Animazione", "Dramma"],
            "title": "Una Buona Ragione Per Vincere",
            "fname": "/Anime & Cartoni/L'Uomo Tigre (1969) [a25114]/1.012 - Una Buona Ragione Per Vincere.avi",
            "year": "1969",
            "actors": ["Kei Tomiyama", "Katsuji Mori", "Chisato Nakajima", "Keiichi Noda"],
            "links": [
                {
                    "url": "http://51.77.159.233:30299/11759b6f39da269141f4ea687fc41192"
                }
            ]
        },
        {
            "file_id": "62c03067af1a9aaf83648755621b523b",
            "tmdb_id": 25114,
            "saga": "L'Uomo Tigre",
            "season": 1,
            "episode": 13,
            "genre": ["Animazione", "Dramma"],
            "title": "Stella Di Teschio",
            "fname": "/Anime & Cartoni/L'Uomo Tigre (1969) [a25114]/1.013 - Stella Di Teschio.avi",
            "year": "1969",
            "actors": ["Kei Tomiyama", "Katsuji Mori", "Chisato Nakajima", "Keiichi Noda"],
            "links": [
                {
                    "url": "http://51.77.159.233:30299/62c03067af1a9aaf83648755621b523b"
                }
            ]
        },
        {
            "file_id": "9345a2ce6cb535cfa3b804b9b42ceaf4",
            "tmdb_id": 25114,
            "saga": "L'Uomo Tigre",
            "season": 1,
            "episode": 14,
            "genre": ["Animazione", "Dramma"],
            "title": "Il Ricatto Di Mister X",
            "fname": "/Anime & Cartoni/L'Uomo Tigre (1969) [a25114]/1.014 - Il Ricatto Di Mister X.avi",
            "year": "1969",
            "actors": ["Kei Tomiyama", "Katsuji Mori", "Chisato Nakajima", "Keiichi Noda"],
            "links": [
                {
                    "url": "http://51.77.159.233:30299/9345a2ce6cb535cfa3b804b9b42ceaf4"
                }
            ]
        },
        {
            "file_id": "bca6ec680f55ea65bb34a28b21d2d3ff",
            "tmdb_id": 25114,
            "saga": "L'Uomo Tigre",
            "season": 1,
            "episode": 15,
            "genre": ["Animazione", "Dramma"],
            "title": "Il Televisore Rotto",
            "fname": "/Anime & Cartoni/L'Uomo Tigre (1969) [a25114]/1.015 - Il Televisore Rotto.avi",
            "year": "1969",
            "actors": ["Kei Tomiyama", "Katsuji Mori", "Chisato Nakajima", "Keiichi Noda"],
            "links": [
                {
                    "url": "http://51.77.159.233:30299/bca6ec680f55ea65bb34a28b21d2d3ff"
                }
            ]
        },
        {
            "file_id": "8ea07a41977ce2619d1710551cf2c6d2",
            "tmdb_id": 25114,
            "saga": "L'Uomo Tigre",
            "season": 1,
            "episode": 16,
            "genre": ["Animazione", "Dramma"],
            "title": "La Prima Sconfitta",
            "fname": "/Anime & Cartoni/L'Uomo Tigre (1969) [a25114]/1.016 - La Prima Sconfitta.avi",
            "year": "1969",
            "actors": ["Kei Tomiyama", "Katsuji Mori", "Chisato Nakajima", "Keiichi Noda"],
            "links": [
                {
                    "url": "http://51.77.159.233:30299/8ea07a41977ce2619d1710551cf2c6d2"
                }
            ]
        },
        {
            "file_id": "7211c7b54b1d50f655dac93d08b41795",
            "tmdb_id": 25114,
            "saga": "L'Uomo Tigre",
            "season": 1,
            "episode": 17,
            "genre": ["Animazione", "Dramma"],
            "title": "Una Tigre Non Fugge",
            "fname": "/Anime & Cartoni/L'Uomo Tigre (1969) [a25114]/1.017 - Una Tigre Non Fugge.avi",
            "year": "1969",
            "actors": ["Kei Tomiyama", "Katsuji Mori", "Chisato Nakajima", "Keiichi Noda"],
            "links": [
                {
                    "url": "http://51.77.159.233:30299/7211c7b54b1d50f655dac93d08b41795"
                }
            ]
        },
        {
            "file_id": "80e640b26cf279980a02256d8824202a",
            "tmdb_id": 25114,
            "saga": "L'Uomo Tigre",
            "season": 1,
            "episode": 18,
            "genre": ["Animazione", "Dramma"],
            "title": "Il Confronto",
            "fname": "/Anime & Cartoni/L'Uomo Tigre (1969) [a25114]/1.018 - Il Confronto.avi",
            "year": "1969",
            "actors": ["Kei Tomiyama", "Katsuji Mori", "Chisato Nakajima", "Keiichi Noda"],
            "links": [
                {
                    "url": "http://51.77.159.233:30299/80e640b26cf279980a02256d8824202a"
                }
            ]
        },
        {
            "file_id": "c40a650e00200c9827c08b7d4efeb0b6",
            "tmdb_id": 25114,
            "saga": "L'Uomo Tigre",
            "season": 1,
            "episode": 19,
            "genre": ["Animazione", "Dramma"],
            "title": "Due Ore Prima Del Match",
            "fname": "/Anime & Cartoni/L'Uomo Tigre (1969) [a25114]/1.019 - Due Ore Prima Del Match.avi",
            "year": "1969",
            "actors": ["Kei Tomiyama", "Katsuji Mori", "Chisato Nakajima", "Keiichi Noda"],
            "links": [
                {
                    "url": "http://51.77.159.233:30299/c40a650e00200c9827c08b7d4efeb0b6"
                }
            ]
        },
        {
            "file_id": "7c0f441208477277b9c3aa4be56e2e3a",
            "tmdb_id": 25114,
            "saga": "L'Uomo Tigre",
            "season": 1,
            "episode": 20,
            "genre": ["Animazione", "Dramma"],
            "title": "L'ombra Di Tana Delle Tigri",
            "fname": "/Anime & Cartoni/L'Uomo Tigre (1969) [a25114]/1.020 - L'ombra Di Tana Delle Tigri.avi",
            "year": "1969",
            "actors": ["Kei Tomiyama", "Katsuji Mori", "Chisato Nakajima", "Keiichi Noda"],
            "links": [
                {
                    "url": "http://51.77.159.233:30299/7c0f441208477277b9c3aa4be56e2e3a"
                }
            ]
        },
        {
            "file_id": "efddd52f3981189f7c36228c51aaa915",
            "tmdb_id": 25114,
            "saga": "L'Uomo Tigre",
            "season": 1,
            "episode": 21,
            "genre": ["Animazione", "Dramma"],
            "title": "La Vendetta Di Fang Il Rosso",
            "fname": "/Anime & Cartoni/L'Uomo Tigre (1969) [a25114]/1.021 - La Vendetta Di Fang Il Rosso.avi",
            "year": "1969",
            "actors": ["Kei Tomiyama", "Katsuji Mori", "Chisato Nakajima", "Keiichi Noda"],
            "links": [
                {
                    "url": "http://51.77.159.233:30299/efddd52f3981189f7c36228c51aaa915"
                }
            ]
        },
        {
            "file_id": "53ea90c3c7f93c600a379b3a331d2ce3",
            "tmdb_id": 25114,
            "saga": "L'Uomo Tigre",
            "season": 1,
            "episode": 22,
            "genre": ["Animazione", "Dramma"],
            "title": "Una Speranza Per Domani",
            "fname": "/Anime & Cartoni/L'Uomo Tigre (1969) [a25114]/1.022 - Una Speranza Per Domani.avi",
            "year": "1969",
            "actors": ["Kei Tomiyama", "Katsuji Mori", "Chisato Nakajima", "Keiichi Noda"],
            "links": [
                {
                    "url": "http://51.77.159.233:30299/53ea90c3c7f93c600a379b3a331d2ce3"
                }
            ]
        },
        {
            "file_id": "ef29b12be66529358529eb450c04ba97",
            "tmdb_id": 25114,
            "saga": "L'Uomo Tigre",
            "season": 1,
            "episode": 23,
            "genre": ["Animazione", "Dramma"],
            "title": "L Uomo Tigre Rischia La Vita",
            "fname": "/Anime & Cartoni/L'Uomo Tigre (1969) [a25114]/1.023 - L Uomo Tigre Rischia La Vita.avi",
            "year": "1969",
            "actors": ["Kei Tomiyama", "Katsuji Mori", "Chisato Nakajima", "Keiichi Noda"],
            "links": [
                {
                    "url": "http://51.77.159.233:30299/ef29b12be66529358529eb450c04ba97"
                }
            ]
        },
        {
            "file_id": "c325fc76f5e46793db394f2d0489edad",
            "tmdb_id": 25114,
            "saga": "L'Uomo Tigre",
            "season": 1,
            "episode": 24,
            "genre": ["Animazione", "Dramma"],
            "title": "I Lottatori Mascherati",
            "fname": "/Anime & Cartoni/L'Uomo Tigre (1969) [a25114]/1.024 - I Lottatori Mascherati.avi",
            "year": "1969",
            "actors": ["Kei Tomiyama", "Katsuji Mori", "Chisato Nakajima", "Keiichi Noda"],
            "links": [
                {
                    "url": "http://51.77.159.233:30299/c325fc76f5e46793db394f2d0489edad"
                }
            ]
        },
        {
            "file_id": "11e1c8d6965c2aa97a4d35ad5d1da25f",
            "tmdb_id": 25114,
            "saga": "L'Uomo Tigre",
            "season": 1,
            "episode": 25,
            "genre": ["Animazione", "Dramma"],
            "title": "Maschera D Oro",
            "fname": "/Anime & Cartoni/L'Uomo Tigre (1969) [a25114]/1.025 - Maschera D Oro.avi",
            "year": "1969",
            "actors": ["Kei Tomiyama", "Katsuji Mori", "Chisato Nakajima", "Keiichi Noda"],
            "links": [
                {
                    "url": "http://51.77.159.233:30299/11e1c8d6965c2aa97a4d35ad5d1da25f"
                }
            ]
        },
        {
            "file_id": "7a3f1377fc1d1733f2c499148515c4ec",
            "tmdb_id": 25114,
            "saga": "L'Uomo Tigre",
            "season": 1,
            "episode": 26,
            "genre": ["Animazione", "Dramma"],
            "title": "Grande Zebra",
            "fname": "/Anime & Cartoni/L'Uomo Tigre (1969) [a25114]/1.026 - Grande Zebra.avi",
            "year": "1969",
            "actors": ["Kei Tomiyama", "Katsuji Mori", "Chisato Nakajima", "Keiichi Noda"],
            "links": [
                {
                    "url": "http://51.77.159.233:30299/7a3f1377fc1d1733f2c499148515c4ec"
                }
            ]
        },
        {
            "file_id": "cc5b7c9d0fa252109e8188403054236e",
            "tmdb_id": 25114,
            "saga": "L'Uomo Tigre",
            "season": 1,
            "episode": 27,
            "genre": ["Animazione", "Dramma"],
            "title": "Attento Uomo Tigre",
            "fname": "/Anime & Cartoni/L'Uomo Tigre (1969) [a25114]/1.027 - Attento Uomo Tigre.avi",
            "year": "1969",
            "actors": ["Kei Tomiyama", "Katsuji Mori", "Chisato Nakajima", "Keiichi Noda"],
            "links": [
                {
                    "url": "http://51.77.159.233:30299/cc5b7c9d0fa252109e8188403054236e"
                }
            ]
        },
        {
            "file_id": "0fef5f3e482c1ab421871d2737a99a64",
            "tmdb_id": 25114,
            "saga": "L'Uomo Tigre",
            "season": 1,
            "episode": 28,
            "genre": ["Animazione", "Dramma"],
            "title": "La Tana Delle Tigri",
            "fname": "/Anime & Cartoni/L'Uomo Tigre (1969) [a25114]/1.028 - La Tana Delle Tigri.avi",
            "year": "1969",
            "actors": ["Kei Tomiyama", "Katsuji Mori", "Chisato Nakajima", "Keiichi Noda"],
            "links": [
                {
                    "url": "http://51.77.159.233:30299/0fef5f3e482c1ab421871d2737a99a64"
                }
            ]
        },
        {
            "file_id": "d66f37d8ada339413611443ac44f84b1",
            "tmdb_id": 25114,
            "saga": "L'Uomo Tigre",
            "season": 1,
            "episode": 29,
            "genre": ["Animazione", "Dramma"],
            "title": "La Sfida",
            "fname": "/Anime & Cartoni/L'Uomo Tigre (1969) [a25114]/1.029 - La Sfida.avi",
            "year": "1969",
            "actors": ["Kei Tomiyama", "Katsuji Mori", "Chisato Nakajima", "Keiichi Noda"],
            "links": [
                {
                    "url": "http://51.77.159.233:30299/d66f37d8ada339413611443ac44f84b1"
                }
            ]
        },
        {
            "file_id": "071e256d0919e764ae771c1edee68b95",
            "tmdb_id": 25114,
            "saga": "L'Uomo Tigre",
            "season": 1,
            "episode": 30,
            "genre": ["Animazione", "Dramma"],
            "title": "Un Grande Lottatore",
            "fname": "/Anime & Cartoni/L'Uomo Tigre (1969) [a25114]/1.030 - Un Grande Lottatore.avi",
            "year": "1969",
            "actors": ["Kei Tomiyama", "Katsuji Mori", "Chisato Nakajima", "Keiichi Noda"],
            "links": [
                {
                    "url": "http://51.77.159.233:30299/071e256d0919e764ae771c1edee68b95"
                }
            ]
        },
        {
            "file_id": "f2172ae470cf631884cece1eabd615a2",
            "tmdb_id": 25114,
            "saga": "L'Uomo Tigre",
            "season": 1,
            "episode": 31,
            "genre": ["Animazione", "Dramma"],
            "title": "L Allenamento",
            "fname": "/Anime & Cartoni/L'Uomo Tigre (1969) [a25114]/1.031 - L Allenamento.avi",
            "year": "1969",
            "actors": ["Kei Tomiyama", "Katsuji Mori", "Chisato Nakajima", "Keiichi Noda"],
            "links": [
                {
                    "url": "http://51.77.159.233:30299/f2172ae470cf631884cece1eabd615a2"
                }
            ]
        },
        {
            "file_id": "4f3ebcec9d641d040e8fbe8922e921e4",
            "tmdb_id": 25114,
            "saga": "L'Uomo Tigre",
            "season": 1,
            "episode": 32,
            "genre": ["Animazione", "Dramma"],
            "title": "Mossa Vincente",
            "fname": "/Anime & Cartoni/L'Uomo Tigre (1969) [a25114]/1.032 - Mossa Vincente.avi",
            "year": "1969",
            "actors": ["Kei Tomiyama", "Katsuji Mori", "Chisato Nakajima", "Keiichi Noda"],
            "links": [
                {
                    "url": "http://51.77.159.233:30299/4f3ebcec9d641d040e8fbe8922e921e4"
                }
            ]
        },
        {
            "file_id": "2528df22afa71fbdab614a32a7029338",
            "tmdb_id": 25114,
            "saga": "L'Uomo Tigre",
            "season": 1,
            "episode": 33,
            "genre": ["Animazione", "Dramma"],
            "title": "Il Grande Incontro",
            "fname": "/Anime & Cartoni/L'Uomo Tigre (1969) [a25114]/1.033 - Il Grande Incontro.avi",
            "year": "1969",
            "actors": ["Kei Tomiyama", "Katsuji Mori", "Chisato Nakajima", "Keiichi Noda"],
            "links": [
                {
                    "url": "http://51.77.159.233:30299/2528df22afa71fbdab614a32a7029338"
                }
            ]
        },
        {
            "file_id": "aac30f8d0f254a7b9bea33c873444ebf",
            "tmdb_id": 25114,
            "saga": "L'Uomo Tigre",
            "season": 1,
            "episode": 34,
            "genre": ["Animazione", "Dramma"],
            "title": "Ragazzi Nella Tana Delle Tigri",
            "fname": "/Anime & Cartoni/L'Uomo Tigre (1969) [a25114]/1.034 - Ragazzi Nella Tana Delle Tigri.avi",
            "year": "1969",
            "actors": ["Kei Tomiyama", "Katsuji Mori", "Chisato Nakajima", "Keiichi Noda"],
            "links": [
                {
                    "url": "http://51.77.159.233:30299/aac30f8d0f254a7b9bea33c873444ebf"
                }
            ]
        },
        {
            "file_id": "2a0a85cfc3f6920b97495de16f0347c7",
            "tmdb_id": 25114,
            "saga": "L'Uomo Tigre",
            "season": 1,
            "episode": 35,
            "genre": ["Animazione", "Dramma"],
            "title": "La Strada Del Campione",
            "fname": "/Anime & Cartoni/L'Uomo Tigre (1969) [a25114]/1.035 - La Strada Del Campione.avi",
            "year": "1969",
            "actors": ["Kei Tomiyama", "Katsuji Mori", "Chisato Nakajima", "Keiichi Noda"],
            "links": [
                {
                    "url": "http://51.77.159.233:30299/2a0a85cfc3f6920b97495de16f0347c7"
                }
            ]
        },
        {
            "file_id": "8f5ac415499c2da6d05f3eec7172e2c2",
            "tmdb_id": 25114,
            "saga": "L'Uomo Tigre",
            "season": 1,
            "episode": 36,
            "genre": ["Animazione", "Dramma"],
            "title": "Campionati Di Lotta",
            "fname": "/Anime & Cartoni/L'Uomo Tigre (1969) [a25114]/1.036 - Campionati Di Lotta.avi",
            "year": "1969",
            "actors": ["Kei Tomiyama", "Katsuji Mori", "Chisato Nakajima", "Keiichi Noda"],
            "links": [
                {
                    "url": "http://51.77.159.233:30299/8f5ac415499c2da6d05f3eec7172e2c2"
                }
            ]
        },
        {
            "file_id": "74f39426037dc4dc6cd5cb9a6bcc485b",
            "tmdb_id": 25114,
            "saga": "L'Uomo Tigre",
            "season": 1,
            "episode": 37,
            "genre": ["Animazione", "Dramma"],
            "title": "L Uomo Delle Nevi",
            "fname": "/Anime & Cartoni/L'Uomo Tigre (1969) [a25114]/1.037 - L Uomo Delle Nevi.avi",
            "year": "1969",
            "actors": ["Kei Tomiyama", "Katsuji Mori", "Chisato Nakajima", "Keiichi Noda"],
            "links": [
                {
                    "url": "http://51.77.159.233:30299/74f39426037dc4dc6cd5cb9a6bcc485b"
                }
            ]
        },
        {
            "file_id": "8de0b4ea32eb29ce01eb5404e3553e8b",
            "tmdb_id": 25114,
            "saga": "L'Uomo Tigre",
            "season": 1,
            "episode": 38,
            "genre": ["Animazione", "Dramma"],
            "title": "I Campionati",
            "fname": "/Anime & Cartoni/L'Uomo Tigre (1969) [a25114]/1.038 - I Campionati.avi",
            "year": "1969",
            "actors": ["Kei Tomiyama", "Katsuji Mori", "Chisato Nakajima", "Keiichi Noda"],
            "links": [
                {
                    "url": "http://51.77.159.233:30299/8de0b4ea32eb29ce01eb5404e3553e8b"
                }
            ]
        },
        {
            "file_id": "5b8fb536e10332b287742d0732038397",
            "tmdb_id": 25114,
            "saga": "L'Uomo Tigre",
            "season": 1,
            "episode": 39,
            "genre": ["Animazione", "Dramma"],
            "title": "La Vittoria",
            "fname": "/Anime & Cartoni/L'Uomo Tigre (1969) [a25114]/1.039 - La Vittoria.avi",
            "year": "1969",
            "actors": ["Kei Tomiyama", "Katsuji Mori", "Chisato Nakajima", "Keiichi Noda"],
            "links": [
                {
                    "url": "http://51.77.159.233:30299/5b8fb536e10332b287742d0732038397"
                }
            ]
        },
        {
            "file_id": "42cc02489d6b601731b3fa4f17e74676",
            "tmdb_id": 25114,
            "saga": "L'Uomo Tigre",
            "season": 1,
            "episode": 40,
            "genre": ["Animazione", "Dramma"],
            "title": "Tigre Immortale",
            "fname": "/Anime & Cartoni/L'Uomo Tigre (1969) [a25114]/1.040 - Tigre Immortale.avi",
            "year": "1969",
            "actors": ["Kei Tomiyama", "Katsuji Mori", "Chisato Nakajima", "Keiichi Noda"],
            "links": [
                {
                    "url": "http://51.77.159.233:30299/42cc02489d6b601731b3fa4f17e74676"
                }
            ]
        },
        {
            "file_id": "d5b02106ae49c7ecb697f9d9c70e334e",
            "tmdb_id": 25114,
            "saga": "L'Uomo Tigre",
            "season": 1,
            "episode": 41,
            "genre": ["Animazione", "Dramma"],
            "title": "Maschera Di Morte",
            "fname": "/Anime & Cartoni/L'Uomo Tigre (1969) [a25114]/1.041 - Maschera Di Morte.avi",
            "year": "1969",
            "actors": ["Kei Tomiyama", "Katsuji Mori", "Chisato Nakajima", "Keiichi Noda"],
            "links": [
                {
                    "url": "http://51.77.159.233:30299/d5b02106ae49c7ecb697f9d9c70e334e"
                }
            ]
        },
        {
            "file_id": "6eb62f1b45aee896ba84287a4afd27e2",
            "tmdb_id": 25114,
            "saga": "L'Uomo Tigre",
            "season": 1,
            "episode": 42,
            "genre": ["Animazione", "Dramma"],
            "title": "Lo Spirito Di Un Guerriero",
            "fname": "/Anime & Cartoni/L'Uomo Tigre (1969) [a25114]/1.042 - Lo Spirito Di Un Guerriero.avi",
            "year": "1969",
            "actors": ["Kei Tomiyama", "Katsuji Mori", "Chisato Nakajima", "Keiichi Noda"],
            "links": [
                {
                    "url": "http://51.77.159.233:30299/6eb62f1b45aee896ba84287a4afd27e2"
                }
            ]
        },
        {
            "file_id": "89536a548cef1f8394f28ed88005e3de",
            "tmdb_id": 25114,
            "saga": "L'Uomo Tigre",
            "season": 1,
            "episode": 43,
            "genre": ["Animazione", "Dramma"],
            "title": "Il Lottatore Malvagio",
            "fname": "/Anime & Cartoni/L'Uomo Tigre (1969) [a25114]/1.043 - Il Lottatore Malvagio.avi",
            "year": "1969",
            "actors": ["Kei Tomiyama", "Katsuji Mori", "Chisato Nakajima", "Keiichi Noda"],
            "links": [
                {
                    "url": "http://51.77.159.233:30299/89536a548cef1f8394f28ed88005e3de"
                }
            ]
        },
        {
            "file_id": "3112cf05424a916ecc40fe6397c8e7b9",
            "tmdb_id": 25114,
            "saga": "L'Uomo Tigre",
            "season": 1,
            "episode": 44,
            "genre": ["Animazione", "Dramma"],
            "title": "Il Rimorso",
            "fname": "/Anime & Cartoni/L'Uomo Tigre (1969) [a25114]/1.044 - Il Rimorso.avi",
            "year": "1969",
            "actors": ["Kei Tomiyama", "Katsuji Mori", "Chisato Nakajima", "Keiichi Noda"],
            "links": [
                {
                    "url": "http://51.77.159.233:30299/3112cf05424a916ecc40fe6397c8e7b9"
                }
            ]
        },
        {
            "file_id": "246a341231207b012af10814859a0d08",
            "tmdb_id": 25114,
            "saga": "L'Uomo Tigre",
            "season": 1,
            "episode": 45,
            "genre": ["Animazione", "Dramma"],
            "title": "La Nuova Maschera",
            "fname": "/Anime & Cartoni/L'Uomo Tigre (1969) [a25114]/1.045 - La Nuova Maschera.avi",
            "year": "1969",
            "actors": ["Kei Tomiyama", "Katsuji Mori", "Chisato Nakajima", "Keiichi Noda"],
            "links": [
                {
                    "url": "http://51.77.159.233:30299/246a341231207b012af10814859a0d08"
                }
            ]
        },
        {
            "file_id": "ea6f6642bb89123908c85c46d8791a27",
            "tmdb_id": 25114,
            "saga": "L'Uomo Tigre",
            "season": 1,
            "episode": 46,
            "genre": ["Animazione", "Dramma"],
            "title": "Il Piccolo Lottatore",
            "fname": "/Anime & Cartoni/L'Uomo Tigre (1969) [a25114]/1.046 - Il Piccolo Lottatore.avi",
            "year": "1969",
            "actors": ["Kei Tomiyama", "Katsuji Mori", "Chisato Nakajima", "Keiichi Noda"],
            "links": [
                {
                    "url": "http://51.77.159.233:30299/ea6f6642bb89123908c85c46d8791a27"
                }
            ]
        },
        {
            "file_id": "8a08c5e2a381c6a165f2885b08acc121",
            "tmdb_id": 25114,
            "saga": "L'Uomo Tigre",
            "season": 1,
            "episode": 47,
            "genre": ["Animazione", "Dramma"],
            "title": "Re Giungla",
            "fname": "/Anime & Cartoni/L'Uomo Tigre (1969) [a25114]/1.047 - Re Giungla.avi",
            "year": "1969",
            "actors": ["Kei Tomiyama", "Katsuji Mori", "Chisato Nakajima", "Keiichi Noda"],
            "links": [
                {
                    "url": "http://51.77.159.233:30299/8a08c5e2a381c6a165f2885b08acc121"
                }
            ]
        },
        {
            "file_id": "d2f2b4ec12fd1ce37fa606c6b7d7cae0",
            "tmdb_id": 25114,
            "saga": "L'Uomo Tigre",
            "season": 1,
            "episode": 48,
            "genre": ["Animazione", "Dramma"],
            "title": "Tigre Contro Kamikaze",
            "fname": "/Anime & Cartoni/L'Uomo Tigre (1969) [a25114]/1.048 - Tigre Contro Kamikaze.avi",
            "year": "1969",
            "actors": ["Kei Tomiyama", "Katsuji Mori", "Chisato Nakajima", "Keiichi Noda"],
            "links": [
                {
                    "url": "http://51.77.159.233:30299/d2f2b4ec12fd1ce37fa606c6b7d7cae0"
                }
            ]
        },
        {
            "file_id": "b9d4acea18e7f500449dcdb2fb42c8b2",
            "tmdb_id": 25114,
            "saga": "L'Uomo Tigre",
            "season": 1,
            "episode": 49,
            "genre": ["Animazione", "Dramma"],
            "title": "Il Ritorno Dell'uomo Tigre",
            "fname": "/Anime & Cartoni/L'Uomo Tigre (1969) [a25114]/1.049 - Il Ritorno Dell'uomo Tigre.avi",
            "year": "1969",
            "actors": ["Kei Tomiyama", "Katsuji Mori", "Chisato Nakajima", "Keiichi Noda"],
            "links": [
                {
                    "url": "http://51.77.159.233:30299/b9d4acea18e7f500449dcdb2fb42c8b2"
                }
            ]
        },
        {
            "file_id": "5f8ab1c690d63537a4e2c3f21dfbb568",
            "tmdb_id": 25114,
            "saga": "L'Uomo Tigre",
            "season": 1,
            "episode": 50,
            "genre": ["Animazione", "Dramma"],
            "title": "Ricordo Di Hiroshima",
            "fname": "/Anime & Cartoni/L'Uomo Tigre (1969) [a25114]/1.050 - Ricordo Di Hiroshima.avi",
            "year": "1969",
            "actors": ["Kei Tomiyama", "Katsuji Mori", "Chisato Nakajima", "Keiichi Noda"],
            "links": [
                {
                    "url": "http://51.77.159.233:30299/5f8ab1c690d63537a4e2c3f21dfbb568"
                }
            ]
        },
        {
            "file_id": "1b8d654d9118c4d7a5b6c92c7ebe016f",
            "tmdb_id": 25114,
            "saga": "L'Uomo Tigre",
            "season": 1,
            "episode": 51,
            "genre": ["Animazione", "Dramma"],
            "title": "Difendiamo Il Titolo",
            "fname": "/Anime & Cartoni/L'Uomo Tigre (1969) [a25114]/1.051 - Difendiamo Il Titolo.avi",
            "year": "1969",
            "actors": ["Kei Tomiyama", "Katsuji Mori", "Chisato Nakajima", "Keiichi Noda"],
            "links": [
                {
                    "url": "http://51.77.159.233:30299/1b8d654d9118c4d7a5b6c92c7ebe016f"
                }
            ]
        },
        {
            "file_id": "bc1a0099664c5a13ac7a008d6d33e5b1",
            "tmdb_id": 25114,
            "saga": "L'Uomo Tigre",
            "season": 1,
            "episode": 52,
            "genre": ["Animazione", "Dramma"],
            "title": "Il Campionato Mondiale",
            "fname": "/Anime & Cartoni/L'Uomo Tigre (1969) [a25114]/1.052 - Il Campionato Mondiale.avi",
            "year": "1969",
            "actors": ["Kei Tomiyama", "Katsuji Mori", "Chisato Nakajima", "Keiichi Noda"],
            "links": [
                {
                    "url": "http://51.77.159.233:30299/bc1a0099664c5a13ac7a008d6d33e5b1"
                }
            ]
        },
        {
            "file_id": "e79c6f65e4b281d862d59cc393f62e6d",
            "tmdb_id": 25114,
            "saga": "L'Uomo Tigre",
            "season": 1,
            "episode": 53,
            "genre": ["Animazione", "Dramma"],
            "title": "I Fratelli Miracolo",
            "fname": "/Anime & Cartoni/L'Uomo Tigre (1969) [a25114]/1.053 - I Fratelli Miracolo.avi",
            "year": "1969",
            "actors": ["Kei Tomiyama", "Katsuji Mori", "Chisato Nakajima", "Keiichi Noda"],
            "links": [
                {
                    "url": "http://51.77.159.233:30299/e79c6f65e4b281d862d59cc393f62e6d"
                }
            ]
        },
        {
            "file_id": "70e1eb4bf7010d1312e26ed54dc181bc",
            "tmdb_id": 25114,
            "saga": "L'Uomo Tigre",
            "season": 1,
            "episode": 54,
            "genre": ["Animazione", "Dramma"],
            "title": "Benvenuta Micro",
            "fname": "/Anime & Cartoni/L'Uomo Tigre (1969) [a25114]/1.054 - Benvenuta Micro.avi",
            "year": "1969",
            "actors": ["Kei Tomiyama", "Katsuji Mori", "Chisato Nakajima", "Keiichi Noda"],
            "links": [
                {
                    "url": "http://51.77.159.233:30299/70e1eb4bf7010d1312e26ed54dc181bc"
                }
            ]
        },
        {
            "file_id": "2477900eb9f4ad33df204b293898bef3",
            "tmdb_id": 25114,
            "saga": "L'Uomo Tigre",
            "season": 1,
            "episode": 55,
            "genre": ["Animazione", "Dramma"],
            "title": "Citta Inquinate",
            "fname": "/Anime & Cartoni/L'Uomo Tigre (1969) [a25114]/1.055 - Citta Inquinate.avi",
            "year": "1969",
            "actors": ["Kei Tomiyama", "Katsuji Mori", "Chisato Nakajima", "Keiichi Noda"],
            "links": [
                {
                    "url": "http://51.77.159.233:30299/2477900eb9f4ad33df204b293898bef3"
                }
            ]
        },
        {
            "file_id": "48e1fcc45857f6898327706575983290",
            "tmdb_id": 25114,
            "saga": "L'Uomo Tigre",
            "season": 1,
            "episode": 56,
            "genre": ["Animazione", "Dramma"],
            "title": "Popo Africa il principe dell Oscurita",
            "fname": "/Anime & Cartoni/L'Uomo Tigre (1969) [a25114]/1.056 -  Popo Africa il principe dell Oscurita.avi",
            "year": "1969",
            "actors": ["Kei Tomiyama", "Katsuji Mori", "Chisato Nakajima", "Keiichi Noda"],
            "links": [
                {
                    "url": "http://51.77.159.233:30299/48e1fcc45857f6898327706575983290"
                }
            ]
        },
        {
            "file_id": "d151698ac63d2e4fa87c2bc320227724",
            "tmdb_id": 25114,
            "saga": "L'Uomo Tigre",
            "season": 1,
            "episode": 57,
            "genre": ["Animazione", "Dramma"],
            "title": "Avversario Imbattibile",
            "fname": "/Anime & Cartoni/L'Uomo Tigre (1969) [a25114]/1.057 - Avversario Imbattibile.avi",
            "year": "1969",
            "actors": ["Kei Tomiyama", "Katsuji Mori", "Chisato Nakajima", "Keiichi Noda"],
            "links": [
                {
                    "url": "http://51.77.159.233:30299/d151698ac63d2e4fa87c2bc320227724"
                }
            ]
        },
        {
            "file_id": "62bc1e25e1369832d07d62e1caa83ae4",
            "tmdb_id": 25114,
            "saga": "L'Uomo Tigre",
            "season": 1,
            "episode": 58,
            "genre": ["Animazione", "Dramma"],
            "title": "L Incontro",
            "fname": "/Anime & Cartoni/L'Uomo Tigre (1969) [a25114]/1.058 - L Incontro.avi",
            "year": "1969",
            "actors": ["Kei Tomiyama", "Katsuji Mori", "Chisato Nakajima", "Keiichi Noda"],
            "links": [
                {
                    "url": "http://51.77.159.233:30299/62bc1e25e1369832d07d62e1caa83ae4"
                }
            ]
        },
        {
            "file_id": "4fa731681adb8d2ec9503e46c999345c",
            "tmdb_id": 25114,
            "saga": "L'Uomo Tigre",
            "season": 1,
            "episode": 59,
            "genre": ["Animazione", "Dramma"],
            "title": "Uno Sfidante",
            "fname": "/Anime & Cartoni/L'Uomo Tigre (1969) [a25114]/1.059 - Uno Sfidante.avi",
            "year": "1969",
            "actors": ["Kei Tomiyama", "Katsuji Mori", "Chisato Nakajima", "Keiichi Noda"],
            "links": [
                {
                    "url": "http://51.77.159.233:30299/4fa731681adb8d2ec9503e46c999345c"
                }
            ]
        },
        {
            "file_id": "340b483d5957ee3d97a78ce02e9d712f",
            "tmdb_id": 25114,
            "saga": "L'Uomo Tigre",
            "season": 1,
            "episode": 60,
            "genre": ["Animazione", "Dramma"],
            "title": "Il Dottor Granky",
            "fname": "/Anime & Cartoni/L'Uomo Tigre (1969) [a25114]/1.060 - Il Dottor Granky.avi",
            "year": "1969",
            "actors": ["Kei Tomiyama", "Katsuji Mori", "Chisato Nakajima", "Keiichi Noda"],
            "links": [
                {
                    "url": "http://51.77.159.233:30299/340b483d5957ee3d97a78ce02e9d712f"
                }
            ]
        },
        {
            "file_id": "5136f1f1e8e35e687a6d7e86bac34da2",
            "tmdb_id": 25114,
            "saga": "L'Uomo Tigre",
            "season": 1,
            "episode": 61,
            "genre": ["Animazione", "Dramma"],
            "title": "La Giusta Strada",
            "fname": "/Anime & Cartoni/L'Uomo Tigre (1969) [a25114]/1.061 - La Giusta Strada.avi",
            "year": "1969",
            "actors": ["Kei Tomiyama", "Katsuji Mori", "Chisato Nakajima", "Keiichi Noda"],
            "links": [
                {
                    "url": "http://51.77.159.233:30299/5136f1f1e8e35e687a6d7e86bac34da2"
                }
            ]
        },
        {
            "file_id": "c8712cc321533eba0301f7f8f0e62244",
            "tmdb_id": 25114,
            "saga": "L'Uomo Tigre",
            "season": 1,
            "episode": 62,
            "genre": ["Animazione", "Dramma"],
            "title": "L Incubo Nero",
            "fname": "/Anime & Cartoni/L'Uomo Tigre (1969) [a25114]/1.062 - L Incubo Nero.avi",
            "year": "1969",
            "actors": ["Kei Tomiyama", "Katsuji Mori", "Chisato Nakajima", "Keiichi Noda"],
            "links": [
                {
                    "url": "http://51.77.159.233:30299/c8712cc321533eba0301f7f8f0e62244"
                }
            ]
        },
        {
            "file_id": "830f791af9ace0aecb1f02bab4471186",
            "tmdb_id": 25114,
            "saga": "L'Uomo Tigre",
            "season": 1,
            "episode": 63,
            "genre": ["Animazione", "Dramma"],
            "title": "Joe L Americano",
            "fname": "/Anime & Cartoni/L'Uomo Tigre (1969) [a25114]/1.063 - Joe L Americano.avi",
            "year": "1969",
            "actors": ["Kei Tomiyama", "Katsuji Mori", "Chisato Nakajima", "Keiichi Noda"],
            "links": [
                {
                    "url": "http://51.77.159.233:30299/830f791af9ace0aecb1f02bab4471186"
                }
            ]
        },
        {
            "file_id": "fdb3da6ba3537da3d018f92803157965",
            "tmdb_id": 25114,
            "saga": "L'Uomo Tigre",
            "season": 1,
            "episode": 64,
            "genre": ["Animazione", "Dramma"],
            "title": "\u00c8 Natale",
            "fname": "/Anime & Cartoni/L'Uomo Tigre (1969) [a25114]/1.064 - \u00c8 Natale.avi",
            "year": "1969",
            "actors": ["Kei Tomiyama", "Katsuji Mori", "Chisato Nakajima", "Keiichi Noda"],
            "links": [
                {
                    "url": "http://51.77.159.233:30299/fdb3da6ba3537da3d018f92803157965"
                }
            ]
        },
        {
            "file_id": "e8403ebeb494d1d0803d016bfe65339e",
            "tmdb_id": 25114,
            "saga": "L'Uomo Tigre",
            "season": 1,
            "episode": 65,
            "genre": ["Animazione", "Dramma"],
            "title": "Il Vero Campione",
            "fname": "/Anime & Cartoni/L'Uomo Tigre (1969) [a25114]/1.065 - Il Vero Campione.avi",
            "year": "1969",
            "actors": ["Kei Tomiyama", "Katsuji Mori", "Chisato Nakajima", "Keiichi Noda"],
            "links": [
                {
                    "url": "http://51.77.159.233:30299/e8403ebeb494d1d0803d016bfe65339e"
                }
            ]
        },
        {
            "file_id": "8bef553eb521e0aa2e7725ebe10013a4",
            "tmdb_id": 25114,
            "saga": "L'Uomo Tigre",
            "season": 1,
            "episode": 66,
            "genre": ["Animazione", "Dramma"],
            "title": "La Paura Di Tana delle Tigri",
            "fname": "/Anime & Cartoni/L'Uomo Tigre (1969) [a25114]/1.066 - La Paura Di Tana delle Tigri.avi",
            "year": "1969",
            "actors": ["Kei Tomiyama", "Katsuji Mori", "Chisato Nakajima", "Keiichi Noda"],
            "links": [
                {
                    "url": "http://51.77.159.233:30299/8bef553eb521e0aa2e7725ebe10013a4"
                }
            ]
        },
        {
            "file_id": "127166ecbf0d1f7d6506e243db726542",
            "tmdb_id": 25114,
            "saga": "L'Uomo Tigre",
            "season": 1,
            "episode": 67,
            "genre": ["Animazione", "Dramma"],
            "title": "L Altra Faccia Di Uomo Tigre",
            "fname": "/Anime & Cartoni/L'Uomo Tigre (1969) [a25114]/1.067 - L Altra Faccia Di Uomo Tigre.avi",
            "year": "1969",
            "actors": ["Kei Tomiyama", "Katsuji Mori", "Chisato Nakajima", "Keiichi Noda"],
            "links": [
                {
                    "url": "http://51.77.159.233:30299/127166ecbf0d1f7d6506e243db726542"
                }
            ]
        },
        {
            "file_id": "5db53968fdd21248913eec17c5891be9",
            "tmdb_id": 25114,
            "saga": "L'Uomo Tigre",
            "season": 1,
            "episode": 68,
            "genre": ["Animazione", "Dramma"],
            "title": "Demone Giallo",
            "fname": "/Anime & Cartoni/L'Uomo Tigre (1969) [a25114]/1.068 - Demone Giallo.avi",
            "year": "1969",
            "actors": ["Kei Tomiyama", "Katsuji Mori", "Chisato Nakajima", "Keiichi Noda"],
            "links": [
                {
                    "url": "http://51.77.159.233:30299/5db53968fdd21248913eec17c5891be9"
                }
            ]
        },
        {
            "file_id": "8bd413c4a03dc825835f6d958ed723a6",
            "tmdb_id": 25114,
            "saga": "L'Uomo Tigre",
            "season": 1,
            "episode": 69,
            "genre": ["Animazione", "Dramma"],
            "title": "La Sfida Di Junker",
            "fname": "/Anime & Cartoni/L'Uomo Tigre (1969) [a25114]/1.069 - La Sfida Di Junker.avi",
            "year": "1969",
            "actors": ["Kei Tomiyama", "Katsuji Mori", "Chisato Nakajima", "Keiichi Noda"],
            "links": [
                {
                    "url": "http://51.77.159.233:30299/8bd413c4a03dc825835f6d958ed723a6"
                }
            ]
        },
        {
            "file_id": "50f7b4d41a844e64875ba07e69c1e87f",
            "tmdb_id": 25114,
            "saga": "L'Uomo Tigre",
            "season": 1,
            "episode": 70,
            "genre": ["Animazione", "Dramma"],
            "title": "Uno Strano Incontro",
            "fname": "/Anime & Cartoni/L'Uomo Tigre (1969) [a25114]/1.070 - Uno Strano Incontro.avi",
            "year": "1969",
            "actors": ["Kei Tomiyama", "Katsuji Mori", "Chisato Nakajima", "Keiichi Noda"],
            "links": [
                {
                    "url": "http://51.77.159.233:30299/50f7b4d41a844e64875ba07e69c1e87f"
                }
            ]
        },
        {
            "file_id": "d12b976914e5e638e698c97d1dbdce4f",
            "tmdb_id": 25114,
            "saga": "L'Uomo Tigre",
            "season": 1,
            "episode": 71,
            "genre": ["Animazione", "Dramma"],
            "title": "Re Giaguaro",
            "fname": "/Anime & Cartoni/L'Uomo Tigre (1969) [a25114]/1.071 - Re Giaguaro.avi",
            "year": "1969",
            "actors": ["Kei Tomiyama", "Katsuji Mori", "Chisato Nakajima", "Keiichi Noda"],
            "links": [
                {
                    "url": "http://51.77.159.233:30299/d12b976914e5e638e698c97d1dbdce4f"
                }
            ]
        },
        {
            "file_id": "a4bd127d99a3ad927ef48c3d509d6ae9",
            "tmdb_id": 25114,
            "saga": "L'Uomo Tigre",
            "season": 1,
            "episode": 72,
            "genre": ["Animazione", "Dramma"],
            "title": "La Forza Di Daigo Daimon",
            "fname": "/Anime & Cartoni/L'Uomo Tigre (1969) [a25114]/1.072 - La Forza Di Daigo Daimon.avi",
            "year": "1969",
            "actors": ["Kei Tomiyama", "Katsuji Mori", "Chisato Nakajima", "Keiichi Noda"],
            "links": [
                {
                    "url": "http://51.77.159.233:30299/a4bd127d99a3ad927ef48c3d509d6ae9"
                }
            ]
        },
        {
            "file_id": "0099111379575d109395d57c70cc76db",
            "tmdb_id": 25114,
            "saga": "L'Uomo Tigre",
            "season": 1,
            "episode": 73,
            "genre": ["Animazione", "Dramma"],
            "title": "L'ultima Risorsa",
            "fname": "/Anime & Cartoni/L'Uomo Tigre (1969) [a25114]/1.073 - L'ultima Risorsa.avi",
            "year": "1969",
            "actors": ["Kei Tomiyama", "Katsuji Mori", "Chisato Nakajima", "Keiichi Noda"],
            "links": [
                {
                    "url": "http://51.77.159.233:30299/0099111379575d109395d57c70cc76db"
                }
            ]
        },
        {
            "file_id": "53b39c32daace004c57a40f1f2edffdb",
            "tmdb_id": 25114,
            "saga": "L'Uomo Tigre",
            "season": 1,
            "episode": 74,
            "genre": ["Animazione", "Dramma"],
            "title": "Il Terzo Traditore",
            "fname": "/Anime & Cartoni/L'Uomo Tigre (1969) [a25114]/1.074 - Il Terzo Traditore.avi",
            "year": "1969",
            "actors": ["Kei Tomiyama", "Katsuji Mori", "Chisato Nakajima", "Keiichi Noda"],
            "links": [
                {
                    "url": "http://51.77.159.233:30299/53b39c32daace004c57a40f1f2edffdb"
                }
            ]
        },
        {
            "file_id": "065806bed0e244f9bbdc8f6a094103b6",
            "tmdb_id": 25114,
            "saga": "L'Uomo Tigre",
            "season": 1,
            "episode": 75,
            "genre": ["Animazione", "Dramma"],
            "title": "La grande fuga",
            "fname": "/Anime & Cartoni/L'Uomo Tigre (1969) [a25114]/1.075 - La grande fuga.avi",
            "year": "1969",
            "actors": ["Kei Tomiyama", "Katsuji Mori", "Chisato Nakajima", "Keiichi Noda"],
            "links": [
                {
                    "url": "http://51.77.159.233:30299/065806bed0e244f9bbdc8f6a094103b6"
                }
            ]
        },
        {
            "file_id": "4afd40c226657a83b60475f2058c32f7",
            "tmdb_id": 25114,
            "saga": "L'Uomo Tigre",
            "season": 1,
            "episode": 76,
            "genre": ["Animazione", "Dramma"],
            "title": "Una Terribile Sfida",
            "fname": "/Anime & Cartoni/L'Uomo Tigre (1969) [a25114]/1.076 - Una Terribile Sfida.avi",
            "year": "1969",
            "actors": ["Kei Tomiyama", "Katsuji Mori", "Chisato Nakajima", "Keiichi Noda"],
            "links": [
                {
                    "url": "http://51.77.159.233:30299/4afd40c226657a83b60475f2058c32f7"
                }
            ]
        },
        {
            "file_id": "01d95c02a5687f1956143b6ef9ddde60",
            "tmdb_id": 25114,
            "saga": "L'Uomo Tigre",
            "season": 1,
            "episode": 77,
            "genre": ["Animazione", "Dramma"],
            "title": "Il Grande Match",
            "fname": "/Anime & Cartoni/L'Uomo Tigre (1969) [a25114]/1.077 - Il Grande Match.avi",
            "year": "1969",
            "actors": ["Kei Tomiyama", "Katsuji Mori", "Chisato Nakajima", "Keiichi Noda"],
            "links": [
                {
                    "url": "http://51.77.159.233:30299/01d95c02a5687f1956143b6ef9ddde60"
                }
            ]
        },
        {
            "file_id": "fe9d566200dea2c3160ccd04bfbf27d0",
            "tmdb_id": 25114,
            "saga": "L'Uomo Tigre",
            "season": 1,
            "episode": 78,
            "genre": ["Animazione", "Dramma"],
            "title": "Un Duello All Ultimo Sangue",
            "fname": "/Anime & Cartoni/L'Uomo Tigre (1969) [a25114]/1.078 - Un Duello All Ultimo Sangue.avi",
            "year": "1969",
            "actors": ["Kei Tomiyama", "Katsuji Mori", "Chisato Nakajima", "Keiichi Noda"],
            "links": [
                {
                    "url": "http://51.77.159.233:30299/fe9d566200dea2c3160ccd04bfbf27d0"
                }
            ]
        },
        {
            "file_id": "1f9dcdf392239191cd2d86bbbb858c4f",
            "tmdb_id": 25114,
            "saga": "L'Uomo Tigre",
            "season": 1,
            "episode": 79,
            "genre": ["Animazione", "Dramma"],
            "title": "Il Capo Della Tana",
            "fname": "/Anime & Cartoni/L'Uomo Tigre (1969) [a25114]/1.079 - Il Capo Della Tana.avi",
            "year": "1969",
            "actors": ["Kei Tomiyama", "Katsuji Mori", "Chisato Nakajima", "Keiichi Noda"],
            "links": [
                {
                    "url": "http://51.77.159.233:30299/1f9dcdf392239191cd2d86bbbb858c4f"
                }
            ]
        },
        {
            "file_id": "a920222211b29409ba0ff7607eb19c8c",
            "tmdb_id": 25114,
            "saga": "L'Uomo Tigre",
            "season": 1,
            "episode": 80,
            "genre": ["Animazione", "Dramma"],
            "title": "Due Grandi Amici",
            "fname": "/Anime & Cartoni/L'Uomo Tigre (1969) [a25114]/1.080 - Due Grandi Amici.avi",
            "year": "1969",
            "actors": ["Kei Tomiyama", "Katsuji Mori", "Chisato Nakajima", "Keiichi Noda"],
            "links": [
                {
                    "url": "http://51.77.159.233:30299/a920222211b29409ba0ff7607eb19c8c"
                }
            ]
        },
        {
            "file_id": "c48bc56df1abcc17ca521fe94568466b",
            "tmdb_id": 25114,
            "saga": "L'Uomo Tigre",
            "season": 1,
            "episode": 81,
            "genre": ["Animazione", "Dramma"],
            "title": "Un Nuovo Lottatore",
            "fname": "/Anime & Cartoni/L'Uomo Tigre (1969) [a25114]/1.081 - Un Nuovo Lottatore.avi",
            "year": "1969",
            "actors": ["Kei Tomiyama", "Katsuji Mori", "Chisato Nakajima", "Keiichi Noda"],
            "links": [
                {
                    "url": "http://51.77.159.233:30299/c48bc56df1abcc17ca521fe94568466b"
                }
            ]
        },
        {
            "file_id": "4a56a24868d00361057892a019da80ff",
            "tmdb_id": 25114,
            "saga": "L'Uomo Tigre",
            "season": 1,
            "episode": 82,
            "genre": ["Animazione", "Dramma"],
            "title": "Combattimento Disperato",
            "fname": "/Anime & Cartoni/L'Uomo Tigre (1969) [a25114]/1.082 - Combattimento Disperato.avi",
            "year": "1969",
            "actors": ["Kei Tomiyama", "Katsuji Mori", "Chisato Nakajima", "Keiichi Noda"],
            "links": [
                {
                    "url": "http://51.77.159.233:30299/4a56a24868d00361057892a019da80ff"
                }
            ]
        },
        {
            "file_id": "5e13d2f2e9d0f719e0106ee89896ad1b",
            "tmdb_id": 25114,
            "saga": "L'Uomo Tigre",
            "season": 1,
            "episode": 83,
            "genre": ["Animazione", "Dramma"],
            "title": "La Nuova Famiglia Di Micro",
            "fname": "/Anime & Cartoni/L'Uomo Tigre (1969) [a25114]/1.083 - La Nuova Famiglia Di Micro.avi",
            "year": "1969",
            "actors": ["Kei Tomiyama", "Katsuji Mori", "Chisato Nakajima", "Keiichi Noda"],
            "links": [
                {
                    "url": "http://51.77.159.233:30299/5e13d2f2e9d0f719e0106ee89896ad1b"
                }
            ]
        },
        {
            "file_id": "b3ec3a6b214365a4dac138f59797eef8",
            "tmdb_id": 25114,
            "saga": "L'Uomo Tigre",
            "season": 1,
            "episode": 84,
            "genre": ["Animazione", "Dramma"],
            "title": "Il Garofano Bianco",
            "fname": "/Anime & Cartoni/L'Uomo Tigre (1969) [a25114]/1.084 - Il Garofano Bianco.avi",
            "year": "1969",
            "actors": ["Kei Tomiyama", "Katsuji Mori", "Chisato Nakajima", "Keiichi Noda"],
            "links": [
                {
                    "url": "http://51.77.159.233:30299/b3ec3a6b214365a4dac138f59797eef8"
                }
            ]
        },
        {
            "file_id": "184ab9ac29e6c74c136583990bc3d187",
            "tmdb_id": 25114,
            "saga": "L'Uomo Tigre",
            "season": 1,
            "episode": 85,
            "genre": ["Animazione", "Dramma"],
            "title": "Caccia Mortale",
            "fname": "/Anime & Cartoni/L'Uomo Tigre (1969) [a25114]/1.085 - Caccia Mortale.avi",
            "year": "1969",
            "actors": ["Kei Tomiyama", "Katsuji Mori", "Chisato Nakajima", "Keiichi Noda"],
            "links": [
                {
                    "url": "http://51.77.159.233:30299/184ab9ac29e6c74c136583990bc3d187"
                }
            ]
        },
        {
            "file_id": "f0f8e6c7f7681453621ba324eaa0df65",
            "tmdb_id": 25114,
            "saga": "L'Uomo Tigre",
            "season": 1,
            "episode": 86,
            "genre": ["Animazione", "Dramma"],
            "title": "Diavolo Pazzo",
            "fname": "/Anime & Cartoni/L'Uomo Tigre (1969) [a25114]/1.086 - Diavolo Pazzo.avi",
            "year": "1969",
            "actors": ["Kei Tomiyama", "Katsuji Mori", "Chisato Nakajima", "Keiichi Noda"],
            "links": [
                {
                    "url": "http://51.77.159.233:30299/f0f8e6c7f7681453621ba324eaa0df65"
                }
            ]
        },
        {
            "file_id": "558e0bcee275813ffff27bcf09f86a5d",
            "tmdb_id": 25114,
            "saga": "L'Uomo Tigre",
            "season": 1,
            "episode": 87,
            "genre": ["Animazione", "Dramma"],
            "title": "Caccia A Uomo Tigre",
            "fname": "/Anime & Cartoni/L'Uomo Tigre (1969) [a25114]/1.087 - Caccia A Uomo Tigre.avi",
            "year": "1969",
            "actors": ["Kei Tomiyama", "Katsuji Mori", "Chisato Nakajima", "Keiichi Noda"],
            "links": [
                {
                    "url": "http://51.77.159.233:30299/558e0bcee275813ffff27bcf09f86a5d"
                }
            ]
        },
        {
            "file_id": "a96e9ba098b1a06dcac8174dd79c73bb",
            "tmdb_id": 25114,
            "saga": "L'Uomo Tigre",
            "season": 1,
            "episode": 88,
            "genre": ["Animazione", "Dramma"],
            "title": "La Nuvola Di Fuoco",
            "fname": "/Anime & Cartoni/L'Uomo Tigre (1969) [a25114]/1.088 - La Nuvola Di Fuoco.avi",
            "year": "1969",
            "actors": ["Kei Tomiyama", "Katsuji Mori", "Chisato Nakajima", "Keiichi Noda"],
            "links": [
                {
                    "url": "http://51.77.159.233:30299/a96e9ba098b1a06dcac8174dd79c73bb"
                }
            ]
        },
        {
            "file_id": "d6278a71d38e725892ca98e04c798524",
            "tmdb_id": 25114,
            "saga": "L'Uomo Tigre",
            "season": 1,
            "episode": 89,
            "genre": ["Animazione", "Dramma"],
            "title": "La Felicita Di Yoshibo",
            "fname": "/Anime & Cartoni/L'Uomo Tigre (1969) [a25114]/1.089 - La Felicita Di Yoshibo.avi",
            "year": "1969",
            "actors": ["Kei Tomiyama", "Katsuji Mori", "Chisato Nakajima", "Keiichi Noda"],
            "links": [
                {
                    "url": "http://51.77.159.233:30299/d6278a71d38e725892ca98e04c798524"
                }
            ]
        },
        {
            "file_id": "15f0f4a725c4739bc9ed3e9510388538",
            "tmdb_id": 25114,
            "saga": "L'Uomo Tigre",
            "season": 1,
            "episode": 90,
            "genre": ["Animazione", "Dramma"],
            "title": "Il Texano",
            "fname": "/Anime & Cartoni/L'Uomo Tigre (1969) [a25114]/1.090 - Il Texano.avi",
            "year": "1969",
            "actors": ["Kei Tomiyama", "Katsuji Mori", "Chisato Nakajima", "Keiichi Noda"],
            "links": [
                {
                    "url": "http://51.77.159.233:30299/15f0f4a725c4739bc9ed3e9510388538"
                }
            ]
        },
        {
            "file_id": "b08132b7c7a57e4989f59f4c52aac2d5",
            "tmdb_id": 25114,
            "saga": "L'Uomo Tigre",
            "season": 1,
            "episode": 91,
            "genre": ["Animazione", "Dramma"],
            "title": "La Tela Del Ragno",
            "fname": "/Anime & Cartoni/L'Uomo Tigre (1969) [a25114]/1.091 - La Tela Del Ragno.avi",
            "year": "1969",
            "actors": ["Kei Tomiyama", "Katsuji Mori", "Chisato Nakajima", "Keiichi Noda"],
            "links": [
                {
                    "url": "http://51.77.159.233:30299/b08132b7c7a57e4989f59f4c52aac2d5"
                }
            ]
        },
        {
            "file_id": "96ac55e38906e6876a70a1c6eda14fe9",
            "tmdb_id": 25114,
            "saga": "L'Uomo Tigre",
            "season": 1,
            "episode": 92,
            "genre": ["Animazione", "Dramma"],
            "title": "Mistero Nero",
            "fname": "/Anime & Cartoni/L'Uomo Tigre (1969) [a25114]/1.092 - Mistero Nero.avi",
            "year": "1969",
            "actors": ["Kei Tomiyama", "Katsuji Mori", "Chisato Nakajima", "Keiichi Noda"],
            "links": [
                {
                    "url": "http://51.77.159.233:30299/96ac55e38906e6876a70a1c6eda14fe9"
                }
            ]
        },
        {
            "file_id": "4f29fc920daa6d063a3d93e3eb8463c7",
            "tmdb_id": 25114,
            "saga": "L'Uomo Tigre",
            "season": 1,
            "episode": 93,
            "genre": ["Animazione", "Dramma"],
            "title": "Un Consiglio Prezioso",
            "fname": "/Anime & Cartoni/L'Uomo Tigre (1969) [a25114]/1.093 - Un Consiglio Prezioso.avi",
            "year": "1969",
            "actors": ["Kei Tomiyama", "Katsuji Mori", "Chisato Nakajima", "Keiichi Noda"],
            "links": [
                {
                    "url": "http://51.77.159.233:30299/4f29fc920daa6d063a3d93e3eb8463c7"
                }
            ]
        },
        {
            "file_id": "f41e042221bc234ead94bb1765729349",
            "tmdb_id": 25114,
            "saga": "L'Uomo Tigre",
            "season": 1,
            "episode": 94,
            "genre": ["Animazione", "Dramma"],
            "title": "L Onore Dell Uomo Tigre",
            "fname": "/Anime & Cartoni/L'Uomo Tigre (1969) [a25114]/1.094 - L Onore Dell Uomo Tigre.avi",
            "year": "1969",
            "actors": ["Kei Tomiyama", "Katsuji Mori", "Chisato Nakajima", "Keiichi Noda"],
            "links": [
                {
                    "url": "http://51.77.159.233:30299/f41e042221bc234ead94bb1765729349"
                }
            ]
        },
        {
            "file_id": "cf2ac3878eba3106e7a68e21f2a8a892",
            "tmdb_id": 25114,
            "saga": "L'Uomo Tigre",
            "season": 1,
            "episode": 95,
            "genre": ["Animazione", "Dramma"],
            "title": "Il Piranha",
            "fname": "/Anime & Cartoni/L'Uomo Tigre (1969) [a25114]/1.095 - Il Piranha.avi",
            "year": "1969",
            "actors": ["Kei Tomiyama", "Katsuji Mori", "Chisato Nakajima", "Keiichi Noda"],
            "links": [
                {
                    "url": "http://51.77.159.233:30299/cf2ac3878eba3106e7a68e21f2a8a892"
                }
            ]
        },
        {
            "file_id": "03a758e175f0155afa0686843a0f21eb",
            "tmdb_id": 25114,
            "saga": "L'Uomo Tigre",
            "season": 1,
            "episode": 96,
            "genre": ["Animazione", "Dramma"],
            "title": "Chi E L Uomo Tigre",
            "fname": "/Anime & Cartoni/L'Uomo Tigre (1969) [a25114]/1.096 - Chi E L Uomo Tigre.avi",
            "year": "1969",
            "actors": ["Kei Tomiyama", "Katsuji Mori", "Chisato Nakajima", "Keiichi Noda"],
            "links": [
                {
                    "url": "http://51.77.159.233:30299/03a758e175f0155afa0686843a0f21eb"
                }
            ]
        },
        {
            "file_id": "93a6ae289f97a553e5b1d53ff455157b",
            "tmdb_id": 25114,
            "saga": "L'Uomo Tigre",
            "season": 1,
            "episode": 97,
            "genre": ["Animazione", "Dramma"],
            "title": "Un Lottatore Eccezionale",
            "fname": "/Anime & Cartoni/L'Uomo Tigre (1969) [a25114]/1.097 - Un Lottatore Eccezionale.avi",
            "year": "1969",
            "actors": ["Kei Tomiyama", "Katsuji Mori", "Chisato Nakajima", "Keiichi Noda"],
            "links": [
                {
                    "url": "http://51.77.159.233:30299/93a6ae289f97a553e5b1d53ff455157b"
                }
            ]
        },
        {
            "file_id": "0c4256385b2babfbc6b7e980024a1d05",
            "tmdb_id": 25114,
            "saga": "L'Uomo Tigre",
            "season": 1,
            "episode": 98,
            "genre": ["Animazione", "Dramma"],
            "title": "Terrore Di Combattere",
            "fname": "/Anime & Cartoni/L'Uomo Tigre (1969) [a25114]/1.098 - Terrore Di Combattere.avi",
            "year": "1969",
            "actors": ["Kei Tomiyama", "Katsuji Mori", "Chisato Nakajima", "Keiichi Noda"],
            "links": [
                {
                    "url": "http://51.77.159.233:30299/0c4256385b2babfbc6b7e980024a1d05"
                }
            ]
        },
        {
            "file_id": "9ce8471bbbfe1904a1529e8bab36e16d",
            "tmdb_id": 25114,
            "saga": "L'Uomo Tigre",
            "season": 1,
            "episode": 99,
            "genre": ["Animazione", "Dramma"],
            "title": "Lupo Solitario",
            "fname": "/Anime & Cartoni/L'Uomo Tigre (1969) [a25114]/1.099 - Lupo Solitario.avi",
            "year": "1969",
            "actors": ["Kei Tomiyama", "Katsuji Mori", "Chisato Nakajima", "Keiichi Noda"],
            "links": [
                {
                    "url": "http://51.77.159.233:30299/9ce8471bbbfe1904a1529e8bab36e16d"
                }
            ]
        },
        {
            "file_id": "7a9ea7674dbfb131264c82a940f69974",
            "tmdb_id": 25114,
            "saga": "L'Uomo Tigre",
            "season": 1,
            "episode": 100,
            "genre": ["Animazione", "Dramma"],
            "title": "La Famiglia Di Yoshibo",
            "fname": "/Anime & Cartoni/L'Uomo Tigre (1969) [a25114]/1.100 - La Famiglia Di Yoshibo.avi",
            "year": "1969",
            "actors": ["Kei Tomiyama", "Katsuji Mori", "Chisato Nakajima", "Keiichi Noda"],
            "links": [
                {
                    "url": "http://51.77.159.233:30299/7a9ea7674dbfb131264c82a940f69974"
                }
            ]
        },
        {
            "file_id": "589764e2955ed3b9d8e42b85af5c3722",
            "tmdb_id": 25114,
            "saga": "L'Uomo Tigre",
            "season": 1,
            "episode": 101,
            "genre": ["Animazione", "Dramma"],
            "title": "La Sconfitta Di Ken",
            "fname": "/Anime & Cartoni/L'Uomo Tigre (1969) [a25114]/1.101 - La Sconfitta Di Ken.avi",
            "year": "1969",
            "actors": ["Kei Tomiyama", "Katsuji Mori", "Chisato Nakajima", "Keiichi Noda"],
            "links": [
                {
                    "url": "http://51.77.159.233:30299/589764e2955ed3b9d8e42b85af5c3722"
                }
            ]
        },
        {
            "file_id": "e2e58230d758d4e9e87776a0c79c921f",
            "tmdb_id": 25114,
            "saga": "L'Uomo Tigre",
            "season": 1,
            "episode": 102,
            "genre": ["Animazione", "Dramma"],
            "title": "Il trionfo della verita",
            "fname": "/Anime & Cartoni/L'Uomo Tigre (1969) [a25114]/1.102 - Il trionfo della verita.avi",
            "year": "1969",
            "actors": ["Kei Tomiyama", "Katsuji Mori", "Chisato Nakajima", "Keiichi Noda"],
            "links": [
                {
                    "url": "http://51.77.159.233:30299/e2e58230d758d4e9e87776a0c79c921f"
                }
            ]
        },
        {
            "file_id": "9ecb03ffcb7e7fc6d404efb966f15271",
            "tmdb_id": 25114,
            "saga": "L'Uomo Tigre",
            "season": 1,
            "episode": 103,
            "genre": ["Animazione", "Dramma"],
            "title": "Un Mortale Tranello",
            "fname": "/Anime & Cartoni/L'Uomo Tigre (1969) [a25114]/1.103 - Un Mortale Tranello.avi",
            "year": "1969",
            "actors": ["Kei Tomiyama", "Katsuji Mori", "Chisato Nakajima", "Keiichi Noda"],
            "links": [
                {
                    "url": "http://51.77.159.233:30299/9ecb03ffcb7e7fc6d404efb966f15271"
                }
            ]
        },
        {
            "file_id": "f0553705352c10591cb3f468a439dbaa",
            "tmdb_id": 25114,
            "saga": "L'Uomo Tigre",
            "season": 1,
            "episode": 104,
            "genre": ["Animazione", "Dramma"],
            "title": "Il Fatidico Incontro",
            "fname": "/Anime & Cartoni/L'Uomo Tigre (1969) [a25114]/1.104 - Il Fatidico Incontro.avi",
            "year": "1969",
            "actors": ["Kei Tomiyama", "Katsuji Mori", "Chisato Nakajima", "Keiichi Noda"],
            "links": [
                {
                    "url": "http://51.77.159.233:30299/f0553705352c10591cb3f468a439dbaa"
                }
            ]
        },
        {
            "file_id": "38ae35cef9e168f9fba7a4b0f8a7e4d9",
            "tmdb_id": 25114,
            "saga": "L'Uomo Tigre",
            "season": 1,
            "episode": 105,
            "genre": ["Animazione", "Dramma"],
            "title": "La Disfatta Di Tana Delle Tigri",
            "fname": "/Anime & Cartoni/L'Uomo Tigre (1969) [a25114]/1.105 - La Disfatta Di Tana Delle Tigri.avi",
            "year": "1969",
            "actors": ["Kei Tomiyama", "Katsuji Mori", "Chisato Nakajima", "Keiichi Noda"],
            "links": [
                {
                    "url": "http://51.77.159.233:30299/38ae35cef9e168f9fba7a4b0f8a7e4d9"
                }
            ]
        },
        {
            "file_id": "281af80165a17cd3a34c3a9182a14598",
            "tmdb_id": 25114,
            "saga": "L'Uomo Tigre",
            "season": 2,
            "episode": 1,
            "genre": ["Animazione", "Dramma"],
            "title": "Giuramento sul ring",
            "fname": "/Anime & Cartoni/L'Uomo Tigre (1969) [a25114]/2.001 - Giuramento sul ring.mp4",
            "year": "1969",
            "actors": ["Kei Tomiyama", "Katsuji Mori", "Chisato Nakajima", "Keiichi Noda"],
            "links": [
                {
                    "url": "http://51.77.159.233:30299/281af80165a17cd3a34c3a9182a14598"
                }
            ]
        },
        {
            "file_id": "01f55ec05ffa45adcc0168332aca90b2",
            "tmdb_id": 25114,
            "saga": "L'Uomo Tigre",
            "season": 2,
            "episode": 2,
            "genre": ["Animazione", "Dramma"],
            "title": "Un degno successore",
            "fname": "/Anime & Cartoni/L'Uomo Tigre (1969) [a25114]/2.002 - Un degno successore.mp4",
            "year": "1969",
            "actors": ["Kei Tomiyama", "Katsuji Mori", "Chisato Nakajima", "Keiichi Noda"],
            "links": [
                {
                    "url": "http://51.77.159.233:30299/01f55ec05ffa45adcc0168332aca90b2"
                }
            ]
        },
        {
            "file_id": "d9c2a1bc82ae104afa6c7002ae513c84",
            "tmdb_id": 25114,
            "saga": "L'Uomo Tigre",
            "season": 2,
            "episode": 3,
            "genre": ["Animazione", "Dramma"],
            "title": "Gi\u00f9 la maschera",
            "fname": "/Anime & Cartoni/L'Uomo Tigre (1969) [a25114]/2.003 - Gi\u00f9 la maschera.mp4",
            "year": "1969",
            "actors": ["Kei Tomiyama", "Katsuji Mori", "Chisato Nakajima", "Keiichi Noda"],
            "links": [
                {
                    "url": "http://51.77.159.233:30299/d9c2a1bc82ae104afa6c7002ae513c84"
                }
            ]
        },
        {
            "file_id": "22de74fe782a5ef139d7b07c04b53e9b",
            "tmdb_id": 25114,
            "saga": "L'Uomo Tigre",
            "season": 2,
            "episode": 4,
            "genre": ["Animazione", "Dramma"],
            "title": "Un combattimento leale",
            "fname": "/Anime & Cartoni/L'Uomo Tigre (1969) [a25114]/2.004 - Un combattimento leale.mp4",
            "year": "1969",
            "actors": ["Kei Tomiyama", "Katsuji Mori", "Chisato Nakajima", "Keiichi Noda"],
            "links": [
                {
                    "url": "http://51.77.159.233:30299/22de74fe782a5ef139d7b07c04b53e9b"
                }
            ]
        },
        {
            "file_id": "bda7f25795ae7017848bacc3701b5323",
            "tmdb_id": 25114,
            "saga": "L'Uomo Tigre",
            "season": 2,
            "episode": 5,
            "genre": ["Animazione", "Dramma"],
            "title": "I ragazzi scomparsi",
            "fname": "/Anime & Cartoni/L'Uomo Tigre (1969) [a25114]/2.005 - I ragazzi scomparsi.mp4",
            "year": "1969",
            "actors": ["Kei Tomiyama", "Katsuji Mori", "Chisato Nakajima", "Keiichi Noda"],
            "links": [
                {
                    "url": "http://51.77.159.233:30299/bda7f25795ae7017848bacc3701b5323"
                }
            ]
        },
        {
            "file_id": "ded76b177a386e5b13ac826b4e32b3e2",
            "tmdb_id": 25114,
            "saga": "L'Uomo Tigre",
            "season": 2,
            "episode": 6,
            "genre": ["Animazione", "Dramma"],
            "title": "Un patto solenne",
            "fname": "/Anime & Cartoni/L'Uomo Tigre (1969) [a25114]/2.006 - Un patto solenne.mp4",
            "year": "1969",
            "actors": ["Kei Tomiyama", "Katsuji Mori", "Chisato Nakajima", "Keiichi Noda"],
            "links": [
                {
                    "url": "http://51.77.159.233:30299/ded76b177a386e5b13ac826b4e32b3e2"
                }
            ]
        },
        {
            "file_id": "535ee90105f23f556244527e66e5037e",
            "tmdb_id": 25114,
            "saga": "L'Uomo Tigre",
            "season": 2,
            "episode": 7,
            "genre": ["Animazione", "Dramma"],
            "title": "La piramide delle tigri",
            "fname": "/Anime & Cartoni/L'Uomo Tigre (1969) [a25114]/2.007 - La piramide delle tigri.mp4",
            "year": "1969",
            "actors": ["Kei Tomiyama", "Katsuji Mori", "Chisato Nakajima", "Keiichi Noda"],
            "links": [
                {
                    "url": "http://51.77.159.233:30299/535ee90105f23f556244527e66e5037e"
                }
            ]
        },
        {
            "file_id": "bacbbbccf11efd5400dd384863a00f9a",
            "tmdb_id": 25114,
            "saga": "L'Uomo Tigre",
            "season": 2,
            "episode": 8,
            "genre": ["Animazione", "Dramma"],
            "title": "Duello all`ultimo sangue",
            "fname": "/Anime & Cartoni/L'Uomo Tigre (1969) [a25114]/2.008 - Duello all`ultimo sangue.mp4",
            "year": "1969",
            "actors": ["Kei Tomiyama", "Katsuji Mori", "Chisato Nakajima", "Keiichi Noda"],
            "links": [
                {
                    "url": "http://51.77.159.233:30299/bacbbbccf11efd5400dd384863a00f9a"
                }
            ]
        },
        {
            "file_id": "9ca75b23e85ad5885e42405c1a2727ae",
            "tmdb_id": 25114,
            "saga": "L'Uomo Tigre",
            "season": 2,
            "episode": 9,
            "genre": ["Animazione", "Dramma"],
            "title": "La vittoria dell`intelligenza",
            "fname": "/Anime & Cartoni/L'Uomo Tigre (1969) [a25114]/2.009 - La vittoria dell`intelligenza.mp4",
            "year": "1969",
            "actors": ["Kei Tomiyama", "Katsuji Mori", "Chisato Nakajima", "Keiichi Noda"],
            "links": [
                {
                    "url": "http://51.77.159.233:30299/9ca75b23e85ad5885e42405c1a2727ae"
                }
            ]
        },
        {
            "file_id": "405083ab271f2e95387064eb45773e26",
            "tmdb_id": 25114,
            "saga": "L'Uomo Tigre",
            "season": 2,
            "episode": 10,
            "genre": ["Animazione", "Dramma"],
            "title": "La sfida dell`uomo di ferro",
            "fname": "/Anime & Cartoni/L'Uomo Tigre (1969) [a25114]/2.010 - La sfida dell`uomo di ferro.mp4",
            "year": "1969",
            "actors": ["Kei Tomiyama", "Katsuji Mori", "Chisato Nakajima", "Keiichi Noda"],
            "links": [
                {
                    "url": "http://51.77.159.233:30299/405083ab271f2e95387064eb45773e26"
                }
            ]
        },
        {
            "file_id": "d450c21720b08484d0e7781129fdcdbf",
            "tmdb_id": 25114,
            "saga": "L'Uomo Tigre",
            "season": 2,
            "episode": 11,
            "genre": ["Animazione", "Dramma"],
            "title": "Una legge spietata",
            "fname": "/Anime & Cartoni/L'Uomo Tigre (1969) [a25114]/2.011 - Una legge spietata.mp4",
            "year": "1969",
            "actors": ["Kei Tomiyama", "Katsuji Mori", "Chisato Nakajima", "Keiichi Noda"],
            "links": [
                {
                    "url": "http://51.77.159.233:30299/d450c21720b08484d0e7781129fdcdbf"
                }
            ]
        },
        {
            "file_id": "ac0d5b244f7bc9a01cdc3435af5a7fe6",
            "tmdb_id": 25114,
            "saga": "L'Uomo Tigre",
            "season": 2,
            "episode": 12,
            "genre": ["Animazione", "Dramma"],
            "title": "Sparvieri infernali",
            "fname": "/Anime & Cartoni/L'Uomo Tigre (1969) [a25114]/2.012 - Sparvieri infernali.mp4",
            "year": "1969",
            "actors": ["Kei Tomiyama", "Katsuji Mori", "Chisato Nakajima", "Keiichi Noda"],
            "links": [
                {
                    "url": "http://51.77.159.233:30299/ac0d5b244f7bc9a01cdc3435af5a7fe6"
                }
            ]
        },
        {
            "file_id": "410565f023ea6661081743b210a88838",
            "tmdb_id": 25114,
            "saga": "L'Uomo Tigre",
            "season": 2,
            "episode": 13,
            "genre": ["Animazione", "Dramma"],
            "title": "Allenamento di baseball",
            "fname": "/Anime & Cartoni/L'Uomo Tigre (1969) [a25114]/2.013 - Allenamento di baseball.mp4",
            "year": "1969",
            "actors": ["Kei Tomiyama", "Katsuji Mori", "Chisato Nakajima", "Keiichi Noda"],
            "links": [
                {
                    "url": "http://51.77.159.233:30299/410565f023ea6661081743b210a88838"
                }
            ]
        },
        {
            "file_id": "d8bd3a92bd113cb69adaabd7e931ae6c",
            "tmdb_id": 25114,
            "saga": "L'Uomo Tigre",
            "season": 2,
            "episode": 14,
            "genre": ["Animazione", "Dramma"],
            "title": "La cintura delle piramidi",
            "fname": "/Anime & Cartoni/L'Uomo Tigre (1969) [a25114]/2.014 - La cintura delle piramidi.mp4",
            "year": "1969",
            "actors": ["Kei Tomiyama", "Katsuji Mori", "Chisato Nakajima", "Keiichi Noda"],
            "links": [
                {
                    "url": "http://51.77.159.233:30299/d8bd3a92bd113cb69adaabd7e931ae6c"
                }
            ]
        },
        {
            "file_id": "6855596e543d842f7b9b003554be80d8",
            "tmdb_id": 25114,
            "saga": "L'Uomo Tigre",
            "season": 2,
            "episode": 15,
            "genre": ["Animazione", "Dramma"],
            "title": "Tigre-Inoki contro sparvieri",
            "fname": "/Anime & Cartoni/L'Uomo Tigre (1969) [a25114]/2.015 - Tigre-Inoki contro sparvieri.mp4",
            "year": "1969",
            "actors": ["Kei Tomiyama", "Katsuji Mori", "Chisato Nakajima", "Keiichi Noda"],
            "links": [
                {
                    "url": "http://51.77.159.233:30299/6855596e543d842f7b9b003554be80d8"
                }
            ]
        },
        {
            "file_id": "cdfa138a98362f0d436d5d517c78c9d5",
            "tmdb_id": 25114,
            "saga": "L'Uomo Tigre",
            "season": 2,
            "episode": 16,
            "genre": ["Animazione", "Dramma"],
            "title": "La minaccia di Hassan",
            "fname": "/Anime & Cartoni/L'Uomo Tigre (1969) [a25114]/2.016 - La minaccia di Hassan.mp4",
            "year": "1969",
            "actors": ["Kei Tomiyama", "Katsuji Mori", "Chisato Nakajima", "Keiichi Noda"],
            "links": [
                {
                    "url": "http://51.77.159.233:30299/cdfa138a98362f0d436d5d517c78c9d5"
                }
            ]
        },
        {
            "file_id": "9938c06fcffacedf1218377b29fe93bd",
            "tmdb_id": 25114,
            "saga": "L'Uomo Tigre",
            "season": 2,
            "episode": 17,
            "genre": ["Animazione", "Dramma"],
            "title": "La grande sfida",
            "fname": "/Anime & Cartoni/L'Uomo Tigre (1969) [a25114]/2.017 - La grande sfida.mp4",
            "year": "1969",
            "actors": ["Kei Tomiyama", "Katsuji Mori", "Chisato Nakajima", "Keiichi Noda"],
            "links": [
                {
                    "url": "http://51.77.159.233:30299/9938c06fcffacedf1218377b29fe93bd"
                }
            ]
        },
        {
            "file_id": "e0a56c2b1aab290cddff40b53922fcca",
            "tmdb_id": 25114,
            "saga": "L'Uomo Tigre",
            "season": 2,
            "episode": 18,
            "genre": ["Animazione", "Dramma"],
            "title": "Per un secondo",
            "fname": "/Anime & Cartoni/L'Uomo Tigre (1969) [a25114]/2.018 - Per un secondo.mp4",
            "year": "1969",
            "actors": ["Kei Tomiyama", "Katsuji Mori", "Chisato Nakajima", "Keiichi Noda"],
            "links": [
                {
                    "url": "http://51.77.159.233:30299/e0a56c2b1aab290cddff40b53922fcca"
                }
            ]
        },
        {
            "file_id": "dcc3d3a0ff227a4da093303188338288",
            "tmdb_id": 25114,
            "saga": "L'Uomo Tigre",
            "season": 2,
            "episode": 19,
            "genre": ["Animazione", "Dramma"],
            "title": "Il tradimento di Argenta",
            "fname": "/Anime & Cartoni/L'Uomo Tigre (1969) [a25114]/2.019 - Il tradimento di Argenta.mp4",
            "year": "1969",
            "actors": ["Kei Tomiyama", "Katsuji Mori", "Chisato Nakajima", "Keiichi Noda"],
            "links": [
                {
                    "url": "http://51.77.159.233:30299/dcc3d3a0ff227a4da093303188338288"
                }
            ]
        },
        {
            "file_id": "57940196c1fe43c42b5dc3cae6dbe3d5",
            "tmdb_id": 25114,
            "saga": "L'Uomo Tigre",
            "season": 2,
            "episode": 20,
            "genre": ["Animazione", "Dramma"],
            "title": "Una grande amicizia",
            "fname": "/Anime & Cartoni/L'Uomo Tigre (1969) [a25114]/2.020 - Una grande amicizia.mp4",
            "year": "1969",
            "actors": ["Kei Tomiyama", "Katsuji Mori", "Chisato Nakajima", "Keiichi Noda"],
            "links": [
                {
                    "url": "http://51.77.159.233:30299/57940196c1fe43c42b5dc3cae6dbe3d5"
                }
            ]
        },
        {
            "file_id": "74069b291ac7443f6a6fddbfccf3bce0",
            "tmdb_id": 25114,
            "saga": "L'Uomo Tigre",
            "season": 2,
            "episode": 21,
            "genre": ["Animazione", "Dramma"],
            "title": "Il valore dello sport",
            "fname": "/Anime & Cartoni/L'Uomo Tigre (1969) [a25114]/2.021 - Il valore dello sport.mp4",
            "year": "1969",
            "actors": ["Kei Tomiyama", "Katsuji Mori", "Chisato Nakajima", "Keiichi Noda"],
            "links": [
                {
                    "url": "http://51.77.159.233:30299/74069b291ac7443f6a6fddbfccf3bce0"
                }
            ]
        },
        {
            "file_id": "96a3e01febb925818f7259d1da99ed67",
            "tmdb_id": 25114,
            "saga": "L'Uomo Tigre",
            "season": 2,
            "episode": 22,
            "genre": ["Animazione", "Dramma"],
            "title": "Bronzo azzurro",
            "fname": "/Anime & Cartoni/L'Uomo Tigre (1969) [a25114]/2.022 - Bronzo azzurro.mp4",
            "year": "1969",
            "actors": ["Kei Tomiyama", "Katsuji Mori", "Chisato Nakajima", "Keiichi Noda"],
            "links": [
                {
                    "url": "http://51.77.159.233:30299/96a3e01febb925818f7259d1da99ed67"
                }
            ]
        },
        {
            "file_id": "8ae8d3823130d8e84ce9f82f507dc066",
            "tmdb_id": 25114,
            "saga": "L'Uomo Tigre",
            "season": 2,
            "episode": 23,
            "genre": ["Animazione", "Dramma"],
            "title": "La sfida di Butcher",
            "fname": "/Anime & Cartoni/L'Uomo Tigre (1969) [a25114]/2.023 - La sfida di Butcher.mp4",
            "year": "1969",
            "actors": ["Kei Tomiyama", "Katsuji Mori", "Chisato Nakajima", "Keiichi Noda"],
            "links": [
                {
                    "url": "http://51.77.159.233:30299/8ae8d3823130d8e84ce9f82f507dc066"
                }
            ]
        },
        {
            "file_id": "e907537070698b874a7ab0a9a06d96ac",
            "tmdb_id": 25114,
            "saga": "L'Uomo Tigre",
            "season": 2,
            "episode": 24,
            "genre": ["Animazione", "Dramma"],
            "title": "Il grande Butcher",
            "fname": "/Anime & Cartoni/L'Uomo Tigre (1969) [a25114]/2.024 - Il grande Butcher.mp4",
            "year": "1969",
            "actors": ["Kei Tomiyama", "Katsuji Mori", "Chisato Nakajima", "Keiichi Noda"],
            "links": [
                {
                    "url": "http://51.77.159.233:30299/e907537070698b874a7ab0a9a06d96ac"
                }
            ]
        },
        {
            "file_id": "a62363f36df75b329774ecacb9005d92",
            "tmdb_id": 25114,
            "saga": "L'Uomo Tigre",
            "season": 2,
            "episode": 25,
            "genre": ["Animazione", "Dramma"],
            "title": "Due campioni",
            "fname": "/Anime & Cartoni/L'Uomo Tigre (1969) [a25114]/2.025 - Due campioni.mp4",
            "year": "1969",
            "actors": ["Kei Tomiyama", "Katsuji Mori", "Chisato Nakajima", "Keiichi Noda"],
            "links": [
                {
                    "url": "http://51.77.159.233:30299/a62363f36df75b329774ecacb9005d92"
                }
            ]
        },
        {
            "file_id": "57a5381e236879309ca1d7eca67f2259",
            "tmdb_id": 25114,
            "saga": "L'Uomo Tigre",
            "season": 2,
            "episode": 26,
            "genre": ["Animazione", "Dramma"],
            "title": "Il pazzo Stan Hansen",
            "fname": "/Anime & Cartoni/L'Uomo Tigre (1969) [a25114]/2.026 - Il pazzo Stan Hansen.mp4",
            "year": "1969",
            "actors": ["Kei Tomiyama", "Katsuji Mori", "Chisato Nakajima", "Keiichi Noda"],
            "links": [
                {
                    "url": "http://51.77.159.233:30299/57a5381e236879309ca1d7eca67f2259"
                }
            ]
        },
        {
            "file_id": "43bb805a5bece862a3d321d04dc8ac7a",
            "tmdb_id": 25114,
            "saga": "L'Uomo Tigre",
            "season": 2,
            "episode": 27,
            "genre": ["Animazione", "Dramma"],
            "title": "Viva la libert\u00e0",
            "fname": "/Anime & Cartoni/L'Uomo Tigre (1969) [a25114]/2.027 - Viva la libert\u00e0.mp4",
            "year": "1969",
            "actors": ["Kei Tomiyama", "Katsuji Mori", "Chisato Nakajima", "Keiichi Noda"],
            "links": [
                {
                    "url": "http://51.77.159.233:30299/43bb805a5bece862a3d321d04dc8ac7a"
                }
            ]
        },
        {
            "file_id": "980735bd01f76c028a503eed81bead87",
            "tmdb_id": 25114,
            "saga": "L'Uomo Tigre",
            "season": 2,
            "episode": 28,
            "genre": ["Animazione", "Dramma"],
            "title": "Il terribile Puma",
            "fname": "/Anime & Cartoni/L'Uomo Tigre (1969) [a25114]/2.028 - Il terribile Puma.mp4",
            "year": "1969",
            "actors": ["Kei Tomiyama", "Katsuji Mori", "Chisato Nakajima", "Keiichi Noda"],
            "links": [
                {
                    "url": "http://51.77.159.233:30299/980735bd01f76c028a503eed81bead87"
                }
            ]
        },
        {
            "file_id": "cb80147727afa546966ee001ae21546b",
            "tmdb_id": 25114,
            "saga": "L'Uomo Tigre",
            "season": 2,
            "episode": 29,
            "genre": ["Animazione", "Dramma"],
            "title": "Re Killium",
            "fname": "/Anime & Cartoni/L'Uomo Tigre (1969) [a25114]/2.029 - Re Killium.mp4",
            "year": "1969",
            "actors": ["Kei Tomiyama", "Katsuji Mori", "Chisato Nakajima", "Keiichi Noda"],
            "links": [
                {
                    "url": "http://51.77.159.233:30299/cb80147727afa546966ee001ae21546b"
                }
            ]
        },
        {
            "file_id": "aa3f6ce2d89b03f8fcbdc7bd495025fc",
            "tmdb_id": 25114,
            "saga": "L'Uomo Tigre",
            "season": 2,
            "episode": 30,
            "genre": ["Animazione", "Dramma"],
            "title": "Scontro reale",
            "fname": "/Anime & Cartoni/L'Uomo Tigre (1969) [a25114]/2.030 - Scontro reale.mp4",
            "year": "1969",
            "actors": ["Kei Tomiyama", "Katsuji Mori", "Chisato Nakajima", "Keiichi Noda"],
            "links": [
                {
                    "url": "http://51.77.159.233:30299/aa3f6ce2d89b03f8fcbdc7bd495025fc"
                }
            ]
        },
        {
            "file_id": "1ca5d1aaaa8ad6af04007da6061858aa",
            "tmdb_id": 25114,
            "saga": "L'Uomo Tigre",
            "season": 2,
            "episode": 31,
            "genre": ["Animazione", "Dramma"],
            "title": "Sei contro uno",
            "fname": "/Anime & Cartoni/L'Uomo Tigre (1969) [a25114]/2.031 - Sei contro uno.mp4",
            "year": "1969",
            "actors": ["Kei Tomiyama", "Katsuji Mori", "Chisato Nakajima", "Keiichi Noda"],
            "links": [
                {
                    "url": "http://51.77.159.233:30299/1ca5d1aaaa8ad6af04007da6061858aa"
                }
            ]
        },
        {
            "file_id": "2f96ace71b02c1eeb0d6211fc8d438a1",
            "tmdb_id": 25114,
            "saga": "L'Uomo Tigre",
            "season": 2,
            "episode": 32,
            "genre": ["Animazione", "Dramma"],
            "title": "Joe Forte",
            "fname": "/Anime & Cartoni/L'Uomo Tigre (1969) [a25114]/2.032 - Joe Forte.mp4",
            "year": "1969",
            "actors": ["Kei Tomiyama", "Katsuji Mori", "Chisato Nakajima", "Keiichi Noda"],
            "links": [
                {
                    "url": "http://51.77.159.233:30299/2f96ace71b02c1eeb0d6211fc8d438a1"
                }
            ]
        },
        {
            "file_id": "ef6d2329f663427f22dbbb76026d46cf",
            "tmdb_id": 25114,
            "saga": "L'Uomo Tigre",
            "season": 2,
            "episode": 33,
            "genre": ["Animazione", "Dramma"],
            "title": "Scontro finale",
            "fname": "/Anime & Cartoni/L'Uomo Tigre (1969) [a25114]/2.033 - Scontro finale.mp4",
            "year": "1969",
            "actors": ["Kei Tomiyama", "Katsuji Mori", "Chisato Nakajima", "Keiichi Noda"],
            "links": [
                {
                    "url": "http://51.77.159.233:30299/ef6d2329f663427f22dbbb76026d46cf"
                }
            ]
        }
    ]
}